Workbook

Sheet tom_demand_setup
B1: order | C1: EXPORT CSV | D1: WEIGHTS_RA | J1: Peso BG por RS | S1: EXPORT CSV | T1: WEIGHTS_RS | AD1: REF DATA | AG1: REF DATA
B2: # | C2: RequestingArea | D2: RevenueStream | E2: BudgetGroup | F2: Weight | G2: Weight-RS+BG | H2: Weight-Base | J2: RevenueStream | K2: BudgetGroup | L2: Target | M2: Check | N2: Count | O2: Check | P2: Weight | Q2: Check | S2: RevenueStream | T2: Weight | U2: Check | W2: {=_xlfn.UNIQUE(E2:E1000)} -> BudgetGroup | X2: Check | Z2: {=_xlfn.UNIQUE(C2:C1000)} -> RequestingArea | AA2: Check | AB2: hasBG? | AD2: RequestingArea | AE2: BudgetGroup | AG2: MicroPhase bmap | AH2: MicroPhase Macro | AI2: MicroPhase Demand
B3: 1 | C3: GP B2B | D3: Business Solutions | E3: =VLOOKUP($C3,$AD:$AE,2,FALSE) -> Commercial | F3: =H3*SUMIFS($H:$H,$J:$J,D3,$K:$K,E3)/G3 -> 0.1 | G3: =SUMIFS($H$2:$H$1000,$E$2:$E$1000,E3,$D$2:$D$1000,D3) -> 10 | H3: 1 | J3: eCommerce | K3: Operations | L3: =N3/O3*100 -> 9.5238095 | M3: =SUMIF($J:$J,J3,$L:$L) -> 100 | N3: =COUNTIFS(E:E,K3,D:D,J3) -> 4 | O3: =SUMIF($J:$J,J3,$N:$N) -> 42 | P3: =SUMIFS(F:F,E:E,K3,D:D,J3) -> 1 | Q3: =SUMIF($J:$J,N3,$N:$N) -> 0 | S3: eCommerce | T3: 40 | U3: =SUM(T3:T18) -> 100 | W3: Commercial | X3: =SUMIF($E:$E,W3,$F:$F) -> 6 | Z3: GP B2B | AA3: =SUMIF($C:$C,Z3,$F:$F) -> 0.64166667 | AB3: =VLOOKUP(Z3,$AD:$AE,2,FALSE) -> Commercial | AD3: CISO | AE3: CISO | AG3: IDEA > Backlog | AH3: {=_xlfn.TEXTSPLIT(AG3,">",)} -> IDEA | AI3: Backlog
B4: 2 | C4: SEO | D4: Business Solutions | E4: =VLOOKUP($C4,$AD:$AE,2,FALSE) -> Operations | F4: =H4*SUMIFS($H:$H,$J:$J,D4,$K:$K,E4)/G4 -> 0.33333333 | G4: =SUMIFS($H$2:$H$1000,$E$2:$E$1000,E4,$D$2:$D$1000,D4) -> 3 | H4: 1 | J4: eCommerce | K4: Commercial | L4: =N4/O4*100 -> 28.571429 | M4: =SUMIF($J:$J,J4,$L:$L) -> 100 | N4: =COUNTIFS(E:E,K4,D:D,J4) -> 12 | O4: =SUMIF($J:$J,J4,$N:$N) -> 42 | P4: =SUMIFS(F:F,E:E,K4,D:D,J4) -> 1 | Q4: =SUMIF($J:$J,N4,$N:$N) -> 0 | S4: Mail | T4: 22 | W4: Operations | X4: =SUMIF($E:$E,W4,$F:$F) -> 6 | Z4: SEO | AA4: =SUMIF($C:$C,Z4,$F:$F) -> 1.9166667 | AB4: =VLOOKUP(Z4,$AD:$AE,2,FALSE) -> Operations | AD4: CCO | AE4: Commercial | AG4: IDEA > Pitch | AH4: {=_xlfn.TEXTSPLIT(AG4,">",)} -> IDEA | AI4: Pitch
B5: 3 | C5: CF | D5: Business Solutions | E5: =VLOOKUP($C5,$AD:$AE,2,FALSE) -> Corporate | F5: =H5*SUMIFS($H:$H,$J:$J,D5,$K:$K,E5)/G5 -> 0.076923077 | G5: =SUMIFS($H$2:$H$1000,$E$2:$E$1000,E5,$D$2:$D$1000,D5) -> 13 | H5: 1 | J5: eCommerce | K5: Corporate | L5: =N5/O5*100 -> 42.857143 | M5: =SUMIF($J:$J,J5,$L:$L) -> 100 | N5: =COUNTIFS(E:E,K5,D:D,J5) -> 18 | O5: =SUMIF($J:$J,J5,$N:$N) -> 42 | P5: =SUMIFS(F:F,E:E,K5,D:D,J5) -> 1 | Q5: =SUMIF($J:$J,N5,$N:$N) -> 0 | S5: Business Solutions | T5: 16 | W5: Corporate | X5: =SUMIF($E:$E,W5,$F:$F) -> 6 | Z5: CF | AA5: =SUMIF($C:$C,Z5,$F:$F) -> 0.48824786 | AB5: =VLOOKUP(Z5,$AD:$AE,2,FALSE) -> Corporate | AD5: CMO | AE5: Commercial | AG5: IDEA > In Definition | AH5: {=_xlfn.TEXTSPLIT(AG5,">",)} -> IDEA | AI5: In Definition
B6: 4 | C6: SI | D6: Business Solutions | E6: =VLOOKUP($C6,$AD:$AE,2,FALSE) -> Technology | F6: =H6*SUMIFS($H:$H,$J:$J,D6,$K:$K,E6)/G6 -> 0.2 | G6: =SUMIFS($H$2:$H$1000,$E$2:$E$1000,E6,$D$2:$D$1000,D6) -> 5 | H6: 1 | J6: eCommerce | K6: Technology | L6: =N6/O6*100 -> 14.285714 | M6: =SUMIF($J:$J,J6,$L:$L) -> 100 | N6: =COUNTIFS(E:E,K6,D:D,J6) -> 6 | O6: =SUMIF($J:$J,J6,$N:$N) -> 42 | P6: =SUMIFS(F:F,E:E,K6,D:D,J6) -> 1 | Q6: =SUMIF($J:$J,N6,$N:$N) -> 0 | S6: Retail & Financial Services | T6: 10 | W6: Technology | X6: =SUMIF($E:$E,W6,$F:$F) -> 6 | Z6: SI | AA6: =SUMIF($C:$C,Z6,$F:$F) -> 1.1666667 | AB6: =VLOOKUP(Z6,$AD:$AE,2,FALSE) -> Technology | AD6: CSI | AE6: Commercial | AG6: SOLUTION > In Approval | AH6: {=_xlfn.TEXTSPLIT(AG6,">",)} -> SOLUTION | AI6: In Approval
B7: 5 | C7: CISO | D7: Business Solutions | E7: =VLOOKUP($C7,$AD:$AE,2,FALSE) -> CISO | F7: =H7*SUMIFS($H:$H,$J:$J,D7,$K:$K,E7)/G7 -> 1 | G7: =SUMIFS($H$2:$H$1000,$E$2:$E$1000,E7,$D$2:$D$1000,D7) -> 1 | H7: 1 | J7: eCommerce | K7: Data & AI | L7: =N7/O7*100 -> 2.3809524 | M7: =SUMIF($J:$J,J7,$L:$L) -> 100 | N7: =COUNTIFS(E:E,K7,D:D,J7) -> 1 | O7: =SUMIF($J:$J,J7,$N:$N) -> 42 | P7: =SUMIFS(F:F,E:E,K7,D:D,J7) -> 1 | Q7: =SUMIF($J:$J,N7,$N:$N) -> 0 | S7: Payments | T7: 8 | W7: CISO | X7: =SUMIF($E:$E,W7,$F:$F) -> 6 | Z7: CISO | AA7: =SUMIF($C:$C,Z7,$F:$F) -> 6 | AB7: =VLOOKUP(Z7,$AD:$AE,2,FALSE) -> CISO | AD7: CTTE | AE7: Commercial | AG7: SOLUTION > Ready for Approval | AH7: {=_xlfn.TEXTSPLIT(AG7,">",)} -> SOLUTION | AI7: Ready for Approval
B8: 6 | C8: IAD | D8: Business Solutions | E8: =VLOOKUP($C8,$AD:$AE,2,FALSE) -> Data & AI | F8: =H8*SUMIFS($H:$H,$J:$J,D8,$K:$K,E8)/G8 -> 1 | G8: =SUMIFS($H$2:$H$1000,$E$2:$E$1000,E8,$D$2:$D$1000,D8) -> 1 | H8: 1 | J8: eCommerce | K8: CISO | L8: =N8/O8*100 -> 2.3809524 | M8: =SUMIF($J:$J,J8,$L:$L) -> 100 | N8: =COUNTIFS(E:E,K8,D:D,J8) -> 1 | O8: =SUMIF($J:$J,J8,$N:$N) -> 42 | P8: =SUMIFS(F:F,E:E,K8,D:D,J8) -> 1 | Q8: =SUMIF($J:$J,N8,$N:$N) -> 0 | S8: Fulfilment | T8: 4 | W8: Data & AI | X8: =SUMIF($E:$E,W8,$F:$F) -> 6 | Z8: IAD | AA8: =SUMIF($C:$C,Z8,$F:$F) -> 5.1428571 | AB8: =VLOOKUP(Z8,$AD:$AE,2,FALSE) -> Data & AI | AD8: DNI | AE8: Commercial | AG8: IDEA > Ready for Solution | AH8: {=_xlfn.TEXTSPLIT(AG8,">",)} -> IDEA | AI8: Ready for Solution
B9: 7 | C9: GS | D9: Business Solutions | E9: =VLOOKUP($C9,$AD:$AE,2,FALSE) -> Commercial | F9: =H9*SUMIFS($H:$H,$J:$J,D9,$K:$K,E9)/G9 -> 0.1 | G9: =SUMIFS($H$2:$H$1000,$E$2:$E$1000,E9,$D$2:$D$1000,D9) -> 10 | H9: 1 | J9: Mail | K9: Commercial | L9: =N9/O9*100 -> 28.125 | M9: =SUMIF($J:$J,J9,$L:$L) -> 100 | N9: =COUNTIFS(E:E,K9,D:D,J9) -> 9 | O9: =SUMIF($J:$J,J9,$N:$N) -> 32 | P9: =SUMIFS(F:F,E:E,K9,D:D,J9) -> 1 | Q9: =SUMIF($J:$J,N9,$N:$N) -> 0 | S9: Banco CTT | T9: 0 | W9: 0 | X9: =SUMIF($E:$E,W9,$F:$F) -> 0 | Z9: GS | AA9: =SUMIF($C:$C,Z9,$F:$F) -> 0.64166667 | AB9: =VLOOKUP(Z9,$AD:$AE,2,FALSE) -> Commercial | AD9: ECM | AE9: Commercial | AG9: SOLUTION > High Level Design | AH9: {=_xlfn.TEXTSPLIT(AG9,">",)} -> SOLUTION | AI9: High Level Design
B10: 8 | C10: ACR | D10: Business Solutions | E10: =VLOOKUP($C10,$AD:$AE,2,FALSE) -> Corporate | F10: =H10*SUMIFS($H:$H,$J:$J,D10,$K:$K,E10)/G10 -> 0.076923077 | G10: =SUMIFS($H$2:$H$1000,$E$2:$E$1000,E10,$D$2:$D$1000,D10) -> 13 | H10: 1 | J10: Mail | K10: Operations | L10: =N10/O10*100 -> 9.375 | M10: =SUMIF($J:$J,J10,$L:$L) -> 100 | N10: =COUNTIFS(E:E,K10,D:D,J10) -> 3 | O10: =SUMIF($J:$J,J10,$N:$N) -> 32 | P10: =SUMIFS(F:F,E:E,K10,D:D,J10) -> 1 | Q10: =SUMIF($J:$J,N10,$N:$N) -> 0 | X10: =SUMIF($E:$E,W10,$F:$F) -> 0 | Z10: ACR | AA10: =SUMIF($C:$C,Z10,$F:$F) -> 0.48824786 | AB10: =VLOOKUP(Z10,$AD:$AE,2,FALSE) -> Corporate | AD10: GP B2B | AE10: Commercial | AG10: SOLUTION > Ready for Development | AH10: {=_xlfn.TEXTSPLIT(AG10,">",)} -> SOLUTION | AI10: Ready for Development
B11: 9 | C11: EDO | D11: Business Solutions | E11: =VLOOKUP($C11,$AD:$AE,2,FALSE) -> Operations | F11: =H11*SUMIFS($H:$H,$J:$J,D11,$K:$K,E11)/G11 -> 0.33333333 | G11: =SUMIFS($H$2:$H$1000,$E$2:$E$1000,E11,$D$2:$D$1000,D11) -> 3 | H11: 1 | J11: Mail | K11: Corporate | L11: =N11/O11*100 -> 40.625 | M11: =SUMIF($J:$J,J11,$L:$L) -> 100 | N11: =COUNTIFS(E:E,K11,D:D,J11) -> 13 | O11: =SUMIF($J:$J,J11,$N:$N) -> 32 | P11: =SUMIFS(F:F,E:E,K11,D:D,J11) -> 1 | Q11: =SUMIF($J:$J,N11,$N:$N) -> 0 | X11: =SUMIF($E:$E,W11,$F:$F) -> 0 | Z11: EDO | AA11: =SUMIF($C:$C,Z11,$F:$F) -> 1.9166667 | AB11: =VLOOKUP(Z11,$AD:$AE,2,FALSE) -> Operations | AD11: GP B2C | AE11: Commercial | AG11: SOLUTION > In Definition | AH11: {=_xlfn.TEXTSPLIT(AG11,">",)} -> SOLUTION | AI11: In Definition
B12: 10 | C12: SI-OPS | D12: Business Solutions | E12: =VLOOKUP($C12,$AD:$AE,2,FALSE) -> Technology | F12: =H12*SUMIFS($H:$H,$J:$J,D12,$K:$K,E12)/G12 -> 0.2 | G12: =SUMIFS($H$2:$H$1000,$E$2:$E$1000,E12,$D$2:$D$1000,D12) -> 5 | H12: 1 | J12: Mail | K12: Technology | L12: =N12/O12*100 -> 15.625 | M12: =SUMIF($J:$J,J12,$L:$L) -> 100 | N12: =COUNTIFS(E:E,K12,D:D,J12) -> 5 | O12: =SUMIF($J:$J,J12,$N:$N) -> 32 | P12: =SUMIFS(F:F,E:E,K12,D:D,J12) -> 1 | Q12: =SUMIF($J:$J,N12,$N:$N) -> 0 | X12: =SUMIF($E:$E,W12,$F:$F) -> 0 | Z12: SI-OPS | AA12: =SUMIF($C:$C,Z12,$F:$F) -> 1.1666667 | AB12: =VLOOKUP(Z12,$AD:$AE,2,FALSE) -> Technology | AD12: GP ECL | AE12: Commercial
B13: 11 | C13: DNI | D13: Business Solutions | E13: =VLOOKUP($C13,$AD:$AE,2,FALSE) -> Commercial | F13: =H13*SUMIFS($H:$H,$J:$J,D13,$K:$K,E13)/G13 -> 0.1 | G13: =SUMIFS($H$2:$H$1000,$E$2:$E$1000,E13,$D$2:$D$1000,D13) -> 10 | H13: 1 | J13: Mail | K13: Data & AI | L13: =N13/O13*100 -> 3.125 | M13: =SUMIF($J:$J,J13,$L:$L) -> 100 | N13: =COUNTIFS(E:E,K13,D:D,J13) -> 1 | O13: =SUMIF($J:$J,J13,$N:$N) -> 32 | P13: =SUMIFS(F:F,E:E,K13,D:D,J13) -> 1 | Q13: =SUMIF($J:$J,N13,$N:$N) -> 0 | X13: =SUMIF($E:$E,W13,$F:$F) -> 0 | Z13: DNI | AA13: =SUMIF($C:$C,Z13,$F:$F) -> 0.64166667 | AB13: =VLOOKUP(Z13,$AD:$AE,2,FALSE) -> Commercial | AD13: GPG | AE13: Commercial
B14: 12 | C14: AVC | D14: Business Solutions | E14: =VLOOKUP($C14,$AD:$AE,2,FALSE) -> Corporate | F14: =H14*SUMIFS($H:$H,$J:$J,D14,$K:$K,E14)/G14 -> 0.076923077 | G14: =SUMIFS($H$2:$H$1000,$E$2:$E$1000,E14,$D$2:$D$1000,D14) -> 13 | H14: 1 | J14: Mail | K14: CISO | L14: =N14/O14*100 -> 3.125 | M14: =SUMIF($J:$J,J14,$L:$L) -> 100 | N14: =COUNTIFS(E:E,K14,D:D,J14) -> 1 | O14: =SUMIF($J:$J,J14,$N:$N) -> 32 | P14: =SUMIFS(F:F,E:E,K14,D:D,J14) -> 1 | Q14: =SUMIF($J:$J,N14,$N:$N) -> 0 | X14: =SUMIF($E:$E,W14,$F:$F) -> 0 | Z14: AVC | AA14: =SUMIF($C:$C,Z14,$F:$F) -> 0.48824786 | AB14: =VLOOKUP(Z14,$AD:$AE,2,FALSE) -> Corporate | AD14: GS | AE14: Commercial
B15: 13 | C15: EM | D15: Business Solutions | E15: =VLOOKUP($C15,$AD:$AE,2,FALSE) -> Operations | F15: =H15*SUMIFS($H:$H,$J:$J,D15,$K:$K,E15)/G15 -> 0.33333333 | G15: =SUMIFS($H$2:$H$1000,$E$2:$E$1000,E15,$D$2:$D$1000,D15) -> 3 | H15: 1 | J15: Business Solutions | K15: Commercial | L15: =N15/O15*100 -> 30.30303 | M15: =SUMIF($J:$J,J15,$L:$L) -> 100 | N15: =COUNTIFS(E:E,K15,D:D,J15) -> 10 | O15: =SUMIF($J:$J,J15,$N:$N) -> 33 | P15: =SUMIFS(F:F,E:E,K15,D:D,J15) -> 1 | Q15: =SUMIF($J:$J,N15,$N:$N) -> 0 | Z15: EM | AA15: =SUMIF($C:$C,Z15,$F:$F) -> 1.9166667 | AB15: =VLOOKUP(Z15,$AD:$AE,2,FALSE) -> Operations | AD15: IDC | AE15: Commercial
B16: 14 | C16: SI-PRD | D16: Business Solutions | E16: =VLOOKUP($C16,$AD:$AE,2,FALSE) -> Technology | F16: =H16*SUMIFS($H:$H,$J:$J,D16,$K:$K,E16)/G16 -> 0.2 | G16: =SUMIFS($H$2:$H$1000,$E$2:$E$1000,E16,$D$2:$D$1000,D16) -> 5 | H16: 1 | J16: Business Solutions | K16: Operations | L16: =N16/O16*100 -> 9.0909091 | M16: =SUMIF($J:$J,J16,$L:$L) -> 100 | N16: =COUNTIFS(E:E,K16,D:D,J16) -> 3 | O16: =SUMIF($J:$J,J16,$N:$N) -> 33 | P16: =SUMIFS(F:F,E:E,K16,D:D,J16) -> 1 | Q16: =SUMIF($J:$J,N16,$N:$N) -> 0 | Z16: SI-PRD | AA16: =SUMIF($C:$C,Z16,$F:$F) -> 1.1666667 | AB16: =VLOOKUP(Z16,$AD:$AE,2,FALSE) -> Technology | AD16: ACR | AE16: Corporate
B17: 15 | C17: CSI | D17: Business Solutions | E17: =VLOOKUP($C17,$AD:$AE,2,FALSE) -> Commercial | F17: =H17*SUMIFS($H:$H,$J:$J,D17,$K:$K,E17)/G17 -> 0.1 | G17: =SUMIFS($H$2:$H$1000,$E$2:$E$1000,E17,$D$2:$D$1000,D17) -> 10 | H17: 1 | J17: Business Solutions | K17: Corporate | L17: =N17/O17*100 -> 39.393939 | M17: =SUMIF($J:$J,J17,$L:$L) -> 100 | N17: =COUNTIFS(E:E,K17,D:D,J17) -> 13 | O17: =SUMIF($J:$J,J17,$N:$N) -> 33 | P17: =SUMIFS(F:F,E:E,K17,D:D,J17) -> 1 | Q17: =SUMIF($J:$J,N17,$N:$N) -> 0 | Z17: CSI | AA17: =SUMIF($C:$C,Z17,$F:$F) -> 0.64166667 | AB17: =VLOOKUP(Z17,$AD:$AE,2,FALSE) -> Commercial | AD17: ATC | AE17: Corporate
B18: 16 | C18: GT | D18: Business Solutions | E18: =VLOOKUP($C18,$AD:$AE,2,FALSE) -> Corporate | F18: =H18*SUMIFS($H:$H,$J:$J,D18,$K:$K,E18)/G18 -> 0.076923077 | G18: =SUMIFS($H$2:$H$1000,$E$2:$E$1000,E18,$D$2:$D$1000,D18) -> 13 | H18: 1 | J18: Business Solutions | K18: Technology | L18: =N18/O18*100 -> 15.151515 | M18: =SUMIF($J:$J,J18,$L:$L) -> 100 | N18: =COUNTIFS(E:E,K18,D:D,J18) -> 5 | O18: =SUMIF($J:$J,J18,$N:$N) -> 33 | P18: =SUMIFS(F:F,E:E,K18,D:D,J18) -> 1 | Q18: =SUMIF($J:$J,N18,$N:$N) -> 0 | Z18: GT | AA18: =SUMIF($C:$C,Z18,$F:$F) -> 0.48824786 | AB18: =VLOOKUP(Z18,$AD:$AE,2,FALSE) -> Corporate | AD18: AVC | AE18: Corporate
B19: 17 | C19: BCTT | D19: Business Solutions | E19: =VLOOKUP($C19,$AD:$AE,2,FALSE) -> Technology | F19: =H19*SUMIFS($H:$H,$J:$J,D19,$K:$K,E19)/G19 -> 0.2 | G19: =SUMIFS($H$2:$H$1000,$E$2:$E$1000,E19,$D$2:$D$1000,D19) -> 5 | H19: 1 | J19: Business Solutions | K19: Data & AI | L19: =N19/O19*100 -> 3.030303 | M19: =SUMIF($J:$J,J19,$L:$L) -> 100 | N19: =COUNTIFS(E:E,K19,D:D,J19) -> 1 | O19: =SUMIF($J:$J,J19,$N:$N) -> 33 | P19: =SUMIFS(F:F,E:E,K19,D:D,J19) -> 1 | Q19: =SUMIF($J:$J,N19,$N:$N) -> 0 | Z19: BCTT | AA19: =SUMIF($C:$C,Z19,$F:$F) -> 1.1666667 | AB19: =VLOOKUP(Z19,$AD:$AE,2,FALSE) -> Technology | AD19: CF | AE19: Corporate
B20: 18 | C20: GP B2C | D20: Business Solutions | E20: =VLOOKUP($C20,$AD:$AE,2,FALSE) -> Commercial | F20: =H20*SUMIFS($H:$H,$J:$J,D20,$K:$K,E20)/G20 -> 0.1 | G20: =SUMIFS($H$2:$H$1000,$E$2:$E$1000,E20,$D$2:$D$1000,D20) -> 10 | H20: 1 | J20: Business Solutions | K20: CISO | L20: =N20/O20*100 -> 3.030303 | M20: =SUMIF($J:$J,J20,$L:$L) -> 100 | N20: =COUNTIFS(E:E,K20,D:D,J20) -> 1 | O20: =SUMIF($J:$J,J20,$N:$N) -> 33 | P20: =SUMIFS(F:F,E:E,K20,D:D,J20) -> 1 | Q20: =SUMIF($J:$J,N20,$N:$N) -> 0 | Z20: GP B2C | AA20: =SUMIF($C:$C,Z20,$F:$F) -> 0.64166667 | AB20: =VLOOKUP(Z20,$AD:$AE,2,FALSE) -> Commercial | AD20: CFO | AE20: Corporate
B21: 19 | C21: GRH | D21: Business Solutions | E21: =VLOOKUP($C21,$AD:$AE,2,FALSE) -> Corporate | F21: =H21*SUMIFS($H:$H,$J:$J,D21,$K:$K,E21)/G21 -> 0.076923077 | G21: =SUMIFS($H$2:$H$1000,$E$2:$E$1000,E21,$D$2:$D$1000,D21) -> 13 | H21: 1 | J21: Retail & Financial Services | K21: Commercial | L21: =N21/O21*100 -> 25 | M21: =SUMIF($J:$J,J21,$L:$L) -> 100 | N21: =COUNTIFS(E:E,K21,D:D,J21) -> 8 | O21: =SUMIF($J:$J,J21,$N:$N) -> 32 | P21: =SUMIFS(F:F,E:E,K21,D:D,J21) -> 1 | Q21: =SUMIF($J:$J,N21,$N:$N) -> 0 | Z21: GRH | AA21: =SUMIF($C:$C,Z21,$F:$F) -> 0.48824786 | AB21: =VLOOKUP(Z21,$AD:$AE,2,FALSE) -> Corporate | AD21: CHR | AE21: Corporate
B22: 20 | C22: SI-CRP | D22: Business Solutions | E22: =VLOOKUP($C22,$AD:$AE,2,FALSE) -> Technology | F22: =H22*SUMIFS($H:$H,$J:$J,D22,$K:$K,E22)/G22 -> 0.2 | G22: =SUMIFS($H$2:$H$1000,$E$2:$E$1000,E22,$D$2:$D$1000,D22) -> 5 | H22: 1 | J22: Retail & Financial Services | K22: Operations | L22: =N22/O22*100 -> 9.375 | M22: =SUMIF($J:$J,J22,$L:$L) -> 100 | N22: =COUNTIFS(E:E,K22,D:D,J22) -> 3 | O22: =SUMIF($J:$J,J22,$N:$N) -> 32 | P22: =SUMIFS(F:F,E:E,K22,D:D,J22) -> 1 | Q22: =SUMIF($J:$J,N22,$N:$N) -> 0 | Z22: SI-CRP | AA22: =SUMIF($C:$C,Z22,$F:$F) -> 1.1666667 | AB22: =VLOOKUP(Z22,$AD:$AE,2,FALSE) -> Technology | AD22: CL | AE22: Corporate
B23: 21 | C23: GP ECL | D23: Business Solutions | E23: =VLOOKUP($C23,$AD:$AE,2,FALSE) -> Commercial | F23: =H23*SUMIFS($H:$H,$J:$J,D23,$K:$K,E23)/G23 -> 0.1 | G23: =SUMIFS($H$2:$H$1000,$E$2:$E$1000,E23,$D$2:$D$1000,D23) -> 10 | H23: 1 | J23: Retail & Financial Services | K23: Corporate | L23: =N23/O23*100 -> 25 | M23: =SUMIF($J:$J,J23,$L:$L) -> 100 | N23: =COUNTIFS(E:E,K23,D:D,J23) -> 8 | O23: =SUMIF($J:$J,J23,$N:$N) -> 32 | P23: =SUMIFS(F:F,E:E,K23,D:D,J23) -> 1 | Q23: =SUMIF($J:$J,N23,$N:$N) -> 0 | Z23: GP ECL | AA23: =SUMIF($C:$C,Z23,$F:$F) -> 0.64166667 | AB23: =VLOOKUP(Z23,$AD:$AE,2,FALSE) -> Commercial | AD23: CMP | AE23: Corporate
B24: 22 | C24: PC | D24: Business Solutions | E24: =VLOOKUP($C24,$AD:$AE,2,FALSE) -> Corporate | F24: =H24*SUMIFS($H:$H,$J:$J,D24,$K:$K,E24)/G24 -> 0.076923077 | G24: =SUMIFS($H$2:$H$1000,$E$2:$E$1000,E24,$D$2:$D$1000,D24) -> 13 | H24: 1 | J24: Retail & Financial Services | K24: Technology | L24: =N24/O24*100 -> 15.625 | M24: =SUMIF($J:$J,J24,$L:$L) -> 100 | N24: =COUNTIFS(E:E,K24,D:D,J24) -> 5 | O24: =SUMIF($J:$J,J24,$N:$N) -> 32 | P24: =SUMIFS(F:F,E:E,K24,D:D,J24) -> 1 | Q24: =SUMIF($J:$J,N24,$N:$N) -> 0 | Z24: PC | AA24: =SUMIF($C:$C,Z24,$F:$F) -> 0.48824786 | AB24: =VLOOKUP(Z24,$AD:$AE,2,FALSE) -> Corporate | AD24: COM | AE24: Corporate
B25: 23 | C25: GPG | D25: Business Solutions | E25: =VLOOKUP($C25,$AD:$AE,2,FALSE) -> Commercial | F25: =H25*SUMIFS($H:$H,$J:$J,D25,$K:$K,E25)/G25 -> 0.1 | G25: =SUMIFS($H$2:$H$1000,$E$2:$E$1000,E25,$D$2:$D$1000,D25) -> 10 | H25: 1 | J25: Retail & Financial Services | K25: Data & AI | L25: =N25/O25*100 -> 21.875 | M25: =SUMIF($J:$J,J25,$L:$L) -> 100 | N25: =COUNTIFS(E:E,K25,D:D,J25) -> 7 | O25: =SUMIF($J:$J,J25,$N:$N) -> 32 | P25: =SUMIFS(F:F,E:E,K25,D:D,J25) -> 1 | Q25: =SUMIF($J:$J,N25,$N:$N) -> 0 | Z25: GPG | AA25: =SUMIF($C:$C,Z25,$F:$F) -> 0.64166667 | AB25: =VLOOKUP(Z25,$AD:$AE,2,FALSE) -> Commercial | AD25: DPO | AE25: Corporate
B26: 24 | C26: RS | D26: Business Solutions | E26: =VLOOKUP($C26,$AD:$AE,2,FALSE) -> Corporate | F26: =H26*SUMIFS($H:$H,$J:$J,D26,$K:$K,E26)/G26 -> 0.076923077 | G26: =SUMIFS($H$2:$H$1000,$E$2:$E$1000,E26,$D$2:$D$1000,D26) -> 13 | H26: 1 | J26: Retail & Financial Services | K26: CISO | L26: =N26/O26*100 -> 3.125 | M26: =SUMIF($J:$J,J26,$L:$L) -> 100 | N26: =COUNTIFS(E:E,K26,D:D,J26) -> 1 | O26: =SUMIF($J:$J,J26,$N:$N) -> 32 | P26: =SUMIFS(F:F,E:E,K26,D:D,J26) -> 1 | Q26: =SUMIF($J:$J,N26,$N:$N) -> 0 | Z26: RS | AA26: =SUMIF($C:$C,Z26,$F:$F) -> 0.48824786 | AB26: =VLOOKUP(Z26,$AD:$AE,2,FALSE) -> Corporate | AD26: FL | AE26: Corporate
... B38: 3 | C38: ATC | D38: eCommerce | E38: =VLOOKUP($C38,$AD:$AE,2,FALSE) -> Corporate | F38: =H38*SUMIFS($H:$H,$J:$J,D38,$K:$K,E38)/G38 -> 0.055555556 | G38: =SUMIFS($H$2:$H$1000,$E$2:$E$1000,E38,$D$2:$D$1000,D38) -> 18 | H38: 1 | J38: Fulfilment | K38: CISO | L38: =N38/O38*100 -> 3.125 | M38: =SUMIF($J:$J,J38,$L:$L) -> 100 | N38: =COUNTIFS(E:E,K38,D:D,J38) -> 1 | O38: =SUMIF($J:$J,J38,$N:$N) -> 32 | P38: =SUMIFS(F:F,E:E,K38,D:D,J38) -> 1 | Q38: =SUMIF($J:$J,N38,$N:$N) -> 0 | Z38: ATC | AA38: =SUMIF($C:$C,Z38,$F:$F) -> 0.055555556 | AB38: =VLOOKUP(Z38,$AD:$AE,2,FALSE) -> Corporate | AD38: SEO | AE38: Operations
B39: 4 | C39: CCO | D39: eCommerce | E39: =VLOOKUP($C39,$AD:$AE,2,FALSE) -> Commercial | F39: =H39*SUMIFS($H:$H,$J:$J,D39,$K:$K,E39)/G39 -> 0.083333333 | G39: =SUMIFS($H$2:$H$1000,$E$2:$E$1000,E39,$D$2:$D$1000,D39) -> 12 | H39: 1 | J39: Mail & Services | K39: Commercial | L39: 38 | Z39: CCO | AA39: =SUMIF($C:$C,Z39,$F:$F) -> 0.083333333 | AB39: =VLOOKUP(Z39,$AD:$AE,2,FALSE) -> Commercial | AD39: BCTT | AE39: Technology
B40: 5 | C40: IDC | D40: eCommerce | E40: =VLOOKUP($C40,$AD:$AE,2,FALSE) -> Commercial | F40: =H40*SUMIFS($H:$H,$J:$J,D40,$K:$K,E40)/G40 -> 0.083333333 | G40: =SUMIFS($H$2:$H$1000,$E$2:$E$1000,E40,$D$2:$D$1000,D40) -> 12 | H40: 1 | J40: Mail & Services | K40: Operations | L40: 19 | Z40: IDC | AA40: =SUMIF($C:$C,Z40,$F:$F) -> 0.083333333 | AB40: =VLOOKUP(Z40,$AD:$AE,2,FALSE) -> Commercial | AD40: CIO | AE40: Technology
B41: 6 | C41: CFO | D41: eCommerce | E41: =VLOOKUP($C41,$AD:$AE,2,FALSE) -> Corporate | F41: =H41*SUMIFS($H:$H,$J:$J,D41,$K:$K,E41)/G41 -> 0.055555556 | G41: =SUMIFS($H$2:$H$1000,$E$2:$E$1000,E41,$D$2:$D$1000,D41) -> 18 | H41: 1 | J41: Mail & Services | K41: Corporate | L41: 19 | Z41: CFO | AA41: =SUMIF($C:$C,Z41,$F:$F) -> 0.055555556 | AB41: =VLOOKUP(Z41,$AD:$AE,2,FALSE) -> Corporate | AD41: SI | AE41: Technology
B42: 7 | C42: CIO | D42: eCommerce | E42: =VLOOKUP($C42,$AD:$AE,2,FALSE) -> Technology | F42: =H42*SUMIFS($H:$H,$J:$J,D42,$K:$K,E42)/G42 -> 0.16666667 | G42: =SUMIFS($H$2:$H$1000,$E$2:$E$1000,E42,$D$2:$D$1000,D42) -> 6 | H42: 1 | J42: Mail & Services | K42: Technology | L42: 17 | Z42: CIO | AA42: =SUMIF($C:$C,Z42,$F:$F) -> 0.16666667 | AB42: =VLOOKUP(Z42,$AD:$AE,2,FALSE) -> Technology | AD42: SI-CRP | AE42: Technology
B43: 8 | C43: PRO | D43: eCommerce | E43: =VLOOKUP($C43,$AD:$AE,2,FALSE) -> Corporate | F43: =H43*SUMIFS($H:$H,$J:$J,D43,$K:$K,E43)/G43 -> 0.055555556 | G43: =SUMIFS($H$2:$H$1000,$E$2:$E$1000,E43,$D$2:$D$1000,D43) -> 18 | H43: 1 | J43: Mail & Services | K43: Data & AI | L43: 5 | Z43: PRO | AA43: =SUMIF($C:$C,Z43,$F:$F) -> 0.055555556 | AB43: =VLOOKUP(Z43,$AD:$AE,2,FALSE) -> Corporate | AD43: SI-OPS | AE43: Technology
B44: 9 | C44: CHR | D44: eCommerce | E44: =VLOOKUP($C44,$AD:$AE,2,FALSE) -> Corporate | F44: =H44*SUMIFS($H:$H,$J:$J,D44,$K:$K,E44)/G44 -> 0.055555556 | G44: =SUMIFS($H$2:$H$1000,$E$2:$E$1000,E44,$D$2:$D$1000,D44) -> 18 | H44: 1 | J44: Mail & Services | K44: CISO | L44: 2 | Z44: CHR | AA44: =SUMIF($C:$C,Z44,$F:$F) -> 0.055555556 | AB44: =VLOOKUP(Z44,$AD:$AE,2,FALSE) -> Corporate | AD44: SI-PRD | AE44: Technology
B45: 11 | C45: GP ECL | D45: eCommerce | E45: =VLOOKUP($C45,$AD:$AE,2,FALSE) -> Commercial | F45: =H45*SUMIFS($H:$H,$J:$J,D45,$K:$K,E45)/G45 -> 0.083333333 | G45: =SUMIFS($H$2:$H$1000,$E$2:$E$1000,E45,$D$2:$D$1000,D45) -> 12 | H45: 1 | Z45: COM | AD45: IAD | AE45: Data & AI
B46: 12 | C46: CISO | D46: eCommerce | E46: =VLOOKUP($C46,$AD:$AE,2,FALSE) -> CISO | F46: =H46*SUMIFS($H:$H,$J:$J,D46,$K:$K,E46)/G46 -> 1 | G46: =SUMIFS($H$2:$H$1000,$E$2:$E$1000,E46,$D$2:$D$1000,D46) -> 1 | H46: 1 | Z46: 0 | AD46: NSP | AE46: Commercial
B47: 13 | C47: IAD | D47: eCommerce | E47: =VLOOKUP($C47,$AD:$AE,2,FALSE) -> Data & AI | F47: =H47*SUMIFS($H:$H,$J:$J,D47,$K:$K,E47)/G47 -> 1 | G47: =SUMIFS($H$2:$H$1000,$E$2:$E$1000,E47,$D$2:$D$1000,D47) -> 1 | H47: 1
B48: 14 | C48: GS | D48: eCommerce | E48: =VLOOKUP($C48,$AD:$AE,2,FALSE) -> Commercial | F48: =H48*SUMIFS($H:$H,$J:$J,D48,$K:$K,E48)/G48 -> 0.083333333 | G48: =SUMIFS($H$2:$H$1000,$E$2:$E$1000,E48,$D$2:$D$1000,D48) -> 12 | H48: 1
B49: 15 | C49: EDO | D49: eCommerce | E49: =VLOOKUP($C49,$AD:$AE,2,FALSE) -> Operations | F49: =H49*SUMIFS($H:$H,$J:$J,D49,$K:$K,E49)/G49 -> 0.25 | G49: =SUMIFS($H$2:$H$1000,$E$2:$E$1000,E49,$D$2:$D$1000,D49) -> 4 | H49: 1
B50: 16 | C50: ACR | D50: eCommerce | E50: =VLOOKUP($C50,$AD:$AE,2,FALSE) -> Corporate | F50: =H50*SUMIFS($H:$H,$J:$J,D50,$K:$K,E50)/G50 -> 0.055555556 | G50: =SUMIFS($H$2:$H$1000,$E$2:$E$1000,E50,$D$2:$D$1000,D50) -> 18 | H50: 1
B51: 17 | C51: SI | D51: eCommerce | E51: =VLOOKUP($C51,$AD:$AE,2,FALSE) -> Technology | F51: =H51*SUMIFS($H:$H,$J:$J,D51,$K:$K,E51)/G51 -> 0.16666667 | G51: =SUMIFS($H$2:$H$1000,$E$2:$E$1000,E51,$D$2:$D$1000,D51) -> 6 | H51: 1
B52: 18 | C52: SEO | D52: eCommerce | E52: =VLOOKUP($C52,$AD:$AE,2,FALSE) -> Operations | F52: =H52*SUMIFS($H:$H,$J:$J,D52,$K:$K,E52)/G52 -> 0.25 | G52: =SUMIFS($H$2:$H$1000,$E$2:$E$1000,E52,$D$2:$D$1000,D52) -> 4 | H52: 1
B53: 19 | C53: CF | D53: eCommerce | E53: =VLOOKUP($C53,$AD:$AE,2,FALSE) -> Corporate | F53: =H53*SUMIFS($H:$H,$J:$J,D53,$K:$K,E53)/G53 -> 0.055555556 | G53: =SUMIFS($H$2:$H$1000,$E$2:$E$1000,E53,$D$2:$D$1000,D53) -> 18 | H53: 1
B54: 20 | C54: SI-OPS | D54: eCommerce | E54: =VLOOKUP($C54,$AD:$AE,2,FALSE) -> Technology | F54: =H54*SUMIFS($H:$H,$J:$J,D54,$K:$K,E54)/G54 -> 0.16666667 | G54: =SUMIFS($H$2:$H$1000,$E$2:$E$1000,E54,$D$2:$D$1000,D54) -> 6 | H54: 1
B55: 21 | C55: BCTT | D55: eCommerce | E55: =VLOOKUP($C55,$AD:$AE,2,FALSE) -> Technology | F55: =H55*SUMIFS($H:$H,$J:$J,D55,$K:$K,E55)/G55 -> 0.16666667 | G55: =SUMIFS($H$2:$H$1000,$E$2:$E$1000,E55,$D$2:$D$1000,D55) -> 6 | H55: 1
B56: 22 | C56: SI-PRD | D56: eCommerce | E56: =VLOOKUP($C56,$AD:$AE,2,FALSE) -> Technology | F56: =H56*SUMIFS($H:$H,$J:$J,D56,$K:$K,E56)/G56 -> 0.16666667 | G56: =SUMIFS($H$2:$H$1000,$E$2:$E$1000,E56,$D$2:$D$1000,D56) -> 6 | H56: 1
B57: 23 | C57: AVC | D57: eCommerce | E57: =VLOOKUP($C57,$AD:$AE,2,FALSE) -> Corporate | F57: =H57*SUMIFS($H:$H,$J:$J,D57,$K:$K,E57)/G57 -> 0.055555556 | G57: =SUMIFS($H$2:$H$1000,$E$2:$E$1000,E57,$D$2:$D$1000,D57) -> 18 | H57: 1
B58: 24 | C58: EM | D58: eCommerce | E58: =VLOOKUP($C58,$AD:$AE,2,FALSE) -> Operations | F58: =H58*SUMIFS($H:$H,$J:$J,D58,$K:$K,E58)/G58 -> 0.25 | G58: =SUMIFS($H$2:$H$1000,$E$2:$E$1000,E58,$D$2:$D$1000,D58) -> 4 | H58: 1
... B199: 26 | C199: CL | D199: Retail & Financial Services | E199: =VLOOKUP($C199,$AD:$AE,2,FALSE) -> Corporate | F199: =H199*SUMIFS($H:$H,$J:$J,D199,$K:$K,E199)/G199 -> 0.125 | G199: =SUMIFS($H$2:$H$1000,$E$2:$E$1000,E199,$D$2:$D$1000,D199) -> 8 | H199: 1
B200: 27 | C200: CTTE | D200: Retail & Financial Services | E200: Data & AI | F200: =H200*SUMIFS($H:$H,$J:$J,D200,$K:$K,E200)/G200 -> 0.14285714 | G200: =SUMIFS($H$2:$H$1000,$E$2:$E$1000,E200,$D$2:$D$1000,D200) -> 7 | H200: 1
B201: 28 | C201: DPO | D201: Retail & Financial Services | E201: Data & AI | F201: =H201*SUMIFS($H:$H,$J:$J,D201,$K:$K,E201)/G201 -> 0.14285714 | G201: =SUMIFS($H$2:$H$1000,$E$2:$E$1000,E201,$D$2:$D$1000,D201) -> 7 | H201: 1
B202: 29 | C202: CMP | D202: Retail & Financial Services | E202: Data & AI | F202: =H202*SUMIFS($H:$H,$J:$J,D202,$K:$K,E202)/G202 -> 0.14285714 | G202: =SUMIFS($H$2:$H$1000,$E$2:$E$1000,E202,$D$2:$D$1000,D202) -> 7 | H202: 1
B203: 30 | C203: ST | D203: Retail & Financial Services | E203: Data & AI | F203: =H203*SUMIFS($H:$H,$J:$J,D203,$K:$K,E203)/G203 -> 0.14285714 | G203: =SUMIFS($H$2:$H$1000,$E$2:$E$1000,E203,$D$2:$D$1000,D203) -> 7 | H203: 1
B204: 31 | C204: FL | D204: Retail & Financial Services | E204: Data & AI | F204: =H204*SUMIFS($H:$H,$J:$J,D204,$K:$K,E204)/G204 -> 0.14285714 | G204: =SUMIFS($H$2:$H$1000,$E$2:$E$1000,E204,$D$2:$D$1000,D204) -> 7 | H204: 1
B205: 32 | C205: TF | D205: Retail & Financial Services | E205: Data & AI | F205: =H205*SUMIFS($H:$H,$J:$J,D205,$K:$K,E205)/G205 -> 0.14285714 | G205: =SUMIFS($H$2:$H$1000,$E$2:$E$1000,E205,$D$2:$D$1000,D205) -> 7 | H205: 1

Sheet tom_demand_setup (25)
B1: order | C1: EXPORT CSV | D1: WEIGHTS_RA | J1: EXPORT CSV | K1: Peso BG por RS | U1: EXPORT CSV | V1: WEIGHTS_RS | AF1: REF DATA | AJ1: REF DATA
B2: # | C2: RequestingArea | D2: RevenueStream | E2: BudgetGroup | F2: Weight | G2: Weight-RS+BG | H2: Weight-Base | J2: RevenueStream | K2: BudgetGroup | L2: Weight | M2: Check | N2: weight | O2: Check | P2: Count | Q2: Check | R2: Weight | S2: Check | U2: RevenueStream | V2: Weight | W2: Check | Y2: {=_xlfn.UNIQUE(E2:E1003)} -> BudgetGroup | Z2: Check | AB2: {=_xlfn.UNIQUE(C2:C1003)} -> RequestingArea | AC2: Check | AD2: hasBG? | AF2: RequestingArea | AG2: BudgetGroup | AH2: BusinessGroup | AJ2: MicroPhase bmap | AK2: MicroPhase Macro | AL2: MicroPhase Demand
B3: 1 | C3: GP B2B | D3: Business Solutions | E3: =VLOOKUP($C3,$AF:$AG,2,FALSE) -> Commercial | F3: =H3*SUMIFS($H:$H,$J:$J,D3,$K:$K,E3)/G3 -> 0.11111111 | G3: =SUMIFS($H$2:$H$1003,$E$2:$E$1003,E3,$D$2:$D$1003,D3) -> 9 | H3: 1 | J3: eCommerce | K3: Operations | L3: 25 | M3: =SUMIF($J:$J,J3,$L:$L) -> 100 | N3: =P3/Q3*100 -> 9.5238095 | O3: =SUMIF($J:$J,J3,$N:$N) -> 100 | P3: =COUNTIFS(E:E,K3,D:D,J3) -> 4 | Q3: =SUMIF($J:$J,J3,$P:$P) -> 42 | R3: =SUMIFS(F:F,E:E,K3,D:D,J3) -> 20.000003 | S3: =SUMIF($J:$J,P3,$P:$P) -> 0 | U3: eCommerce | V3: 40 | W3: =SUM(V3:V18) -> 100 | Y3: Commercial | Z3: =SUMIF($E:$E,Y3,$F:$F) -> 133.00002 | AB3: GP B2B | AC3: =SUMIF($C:$C,AB3,$F:$F) -> 16.569446 | AD3: =VLOOKUP(AB3,$AF:$AG,2,FALSE) -> Commercial | AF3: CISO | AG3: CISO | AJ3: IDEA > Backlog | AK3: {=_xlfn.TEXTSPLIT(AJ3,">",)} -> IDEA | AL3: Backlog
B4: 2 | C4: SEO | D4: Business Solutions | E4: =VLOOKUP($C4,$AF:$AG,2,FALSE) -> Operations | F4: =H4*SUMIFS($H:$H,$J:$J,D4,$K:$K,E4)/G4 -> 0.33333333 | G4: =SUMIFS($H$2:$H$1003,$E$2:$E$1003,E4,$D$2:$D$1003,D4) -> 3 | H4: 1 | J4: eCommerce | K4: Commercial | L4: 25 | M4: =SUMIF($J:$J,J4,$L:$L) -> 100 | N4: =P4/Q4*100 -> 28.571429 | O4: =SUMIF($J:$J,J4,$N:$N) -> 100 | P4: =COUNTIFS(E:E,K4,D:D,J4) -> 12 | Q4: =SUMIF($J:$J,J4,$P:$P) -> 42 | R4: =SUMIFS(F:F,E:E,K4,D:D,J4) -> 28.000009 | S4: =SUMIF($J:$J,P4,$P:$P) -> 0 | U4: Mail | V4: 22 | Y4: Operations | Z4: =SUMIF($E:$E,Y4,$F:$F) -> 125.00001 | AB4: SEO | AC4: =SUMIF($C:$C,AB4,$F:$F) -> 36.666669 | AD4: =VLOOKUP(AB4,$AF:$AG,2,FALSE) -> Operations | AF4: CCO | AG4: Commercial | AJ4: IDEA > Pitch | AK4: {=_xlfn.TEXTSPLIT(AJ4,">",)} -> IDEA | AL4: Pitch
B5: 3 | C5: CF | D5: Business Solutions | E5: =VLOOKUP($C5,$AF:$AG,2,FALSE) -> Corporate | F5: =H5*SUMIFS($H:$H,$J:$J,D5,$K:$K,E5)/G5 -> 0.071428571 | G5: =SUMIFS($H$2:$H$1003,$E$2:$E$1003,E5,$D$2:$D$1003,D5) -> 14 | H5: 1 | J5: eCommerce | K5: Corporate | L5: 20 | M5: =SUMIF($J:$J,J5,$L:$L) -> 100 | N5: =P5/Q5*100 -> 42.857143 | O5: =SUMIF($J:$J,J5,$N:$N) -> 100 | P5: =COUNTIFS(E:E,K5,D:D,J5) -> 18 | Q5: =SUMIF($J:$J,J5,$P:$P) -> 42 | R5: =SUMIFS(F:F,E:E,K5,D:D,J5) -> 37.000013 | S5: =SUMIF($J:$J,P5,$P:$P) -> 0 | U5: Business Solutions | V5: 16 | Y5: Corporate | Z5: =SUMIF($E:$E,Y5,$F:$F) -> 142.00003 | AB5: CF | AC5: =SUMIF($C:$C,AB5,$F:$F) -> 7.0938665 | AD5: =VLOOKUP(AB5,$AF:$AG,2,FALSE) -> Corporate | AF5: CMO | AG5: Commercial | AJ5: IDEA > In Definition | AK5: {=_xlfn.TEXTSPLIT(AJ5,">",)} -> IDEA | AL5: In Definition
B6: 4 | C6: SI | D6: Business Solutions | E6: =VLOOKUP($C6,$AF:$AG,2,FALSE) -> Technology | F6: =H6*SUMIFS($H:$H,$J:$J,D6,$K:$K,E6)/G6 -> 0.2 | G6: =SUMIFS($H$2:$H$1003,$E$2:$E$1003,E6,$D$2:$D$1003,D6) -> 5 | H6: 1 | J6: eCommerce | K6: Technology | L6: 20 | M6: =SUMIF($J:$J,J6,$L:$L) -> 100 | N6: =P6/Q6*100 -> 14.285714 | O6: =SUMIF($J:$J,J6,$N:$N) -> 100 | P6: =COUNTIFS(E:E,K6,D:D,J6) -> 6 | Q6: =SUMIF($J:$J,J6,$P:$P) -> 42 | R6: =SUMIFS(F:F,E:E,K6,D:D,J6) -> 15.000005 | S6: =SUMIF($J:$J,P6,$P:$P) -> 0 | U6: Retail & Financial Services | V6: 10 | Y6: Technology | Z6: =SUMIF($E:$E,Y6,$F:$F) -> 120.00001 | AB6: SI | AC6: =SUMIF($C:$C,AB6,$F:$F) -> 41.000002 | AD6: =VLOOKUP(AB6,$AF:$AG,2,FALSE) -> Technology | AF6: CSI | AG6: Commercial | AJ6: SOLUTION > In Approval | AK6: {=_xlfn.TEXTSPLIT(AJ6,">",)} -> SOLUTION | AL6: In Approval
B7: 5 | C7: CISO | D7: Business Solutions | E7: =VLOOKUP($C7,$AF:$AG,2,FALSE) -> CISO | F7: =H7*SUMIFS($H:$H,$J:$J,D7,$K:$K,E7)/G7 -> 1 | G7: =SUMIFS($H$2:$H$1003,$E$2:$E$1003,E7,$D$2:$D$1003,D7) -> 1 | H7: 1 | J7: eCommerce | K7: Data & AI | L7: 5 | M7: =SUMIF($J:$J,J7,$L:$L) -> 100 | N7: =P7/Q7*100 -> 2.3809524 | O7: =SUMIF($J:$J,J7,$N:$N) -> 100 | P7: =COUNTIFS(E:E,K7,D:D,J7) -> 1 | Q7: =SUMIF($J:$J,J7,$P:$P) -> 42 | R7: =SUMIFS(F:F,E:E,K7,D:D,J7) -> 1e-06 | S7: =SUMIF($J:$J,P7,$P:$P) -> 0 | U7: Payments | V7: 8 | Y7: CISO | Z7: =SUMIF($E:$E,Y7,$F:$F) -> 105 | AB7: CISO | AC7: =SUMIF($C:$C,AB7,$F:$F) -> 105 | AD7: =VLOOKUP(AB7,$AF:$AG,2,FALSE) -> CISO | AF7: CTTE | AG7: Commercial | AJ7: SOLUTION > Ready for Approval | AK7: {=_xlfn.TEXTSPLIT(AJ7,">",)} -> SOLUTION | AL7: Ready for Approval
B8: 6 | C8: IAD | D8: Business Solutions | E8: =VLOOKUP($C8,$AF:$AG,2,FALSE) -> Data & AI | F8: =H8*SUMIFS($H:$H,$J:$J,D8,$K:$K,E8)/G8 -> 1 | G8: =SUMIFS($H$2:$H$1003,$E$2:$E$1003,E8,$D$2:$D$1003,D8) -> 1 | H8: 1 | J8: eCommerce | K8: CISO | L8: 5 | M8: =SUMIF($J:$J,J8,$L:$L) -> 100 | N8: =P8/Q8*100 -> 2.3809524 | O8: =SUMIF($J:$J,J8,$N:$N) -> 100 | P8: =COUNTIFS(E:E,K8,D:D,J8) -> 1 | Q8: =SUMIF($J:$J,J8,$P:$P) -> 42 | R8: =SUMIFS(F:F,E:E,K8,D:D,J8) -> 1e-06 | S8: =SUMIF($J:$J,P8,$P:$P) -> 0 | U8: Fulfilment | V8: 4 | Y8: Data & AI | Z8: =SUMIF($E:$E,Y8,$F:$F) -> 105 | AB8: IAD | AC8: =SUMIF($C:$C,AB8,$F:$F) -> 104.14286 | AD8: =VLOOKUP(AB8,$AF:$AG,2,FALSE) -> Data & AI | AF8: DNI | AG8: Commercial | AJ8: IDEA > Ready for Solution | AK8: {=_xlfn.TEXTSPLIT(AJ8,">",)} -> IDEA | AL8: Ready for Solution
B9: 7 | C9: GS | D9: Business Solutions | E9: =VLOOKUP($C9,$AF:$AG,2,FALSE) -> Commercial | F9: =H9*SUMIFS($H:$H,$J:$J,D9,$K:$K,E9)/G9 -> 0.11111111 | G9: =SUMIFS($H$2:$H$1003,$E$2:$E$1003,E9,$D$2:$D$1003,D9) -> 9 | H9: 1 | J9: Mail | K9: Commercial | L9: 25 | M9: =SUMIF($J:$J,J9,$L:$L) -> 100 | N9: =P9/Q9*100 -> 28.125 | O9: =SUMIF($J:$J,J9,$N:$N) -> 100 | P9: =COUNTIFS(E:E,K9,D:D,J9) -> 9 | Q9: =SUMIF($J:$J,J9,$P:$P) -> 32 | R9: =SUMIFS(F:F,E:E,K9,D:D,J9) -> 1 | S9: =SUMIF($J:$J,P9,$P:$P) -> 0 | U9: Banco CTT | V9: 0 | Y9: 0 | Z9: =SUMIF($E:$E,Y9,$F:$F) -> 0 | AB9: GS | AC9: =SUMIF($C:$C,AB9,$F:$F) -> 12.569446 | AD9: =VLOOKUP(AB9,$AF:$AG,2,FALSE) -> Commercial | AF9: ECM | AG9: Commercial | AJ9: SOLUTION > High Level Design | AK9: {=_xlfn.TEXTSPLIT(AJ9,">",)} -> SOLUTION | AL9: High Level Design
B10: 8 | C10: ACR | D10: Business Solutions | E10: =VLOOKUP($C10,$AF:$AG,2,FALSE) -> Corporate | F10: =H10*SUMIFS($H:$H,$J:$J,D10,$K:$K,E10)/G10 -> 0.071428571 | G10: =SUMIFS($H$2:$H$1003,$E$2:$E$1003,E10,$D$2:$D$1003,D10) -> 14 | H10: 1 | J10: Mail | K10: Operations | L10: 25 | M10: =SUMIF($J:$J,J10,$L:$L) -> 100 | N10: =P10/Q10*100 -> 9.375 | O10: =SUMIF($J:$J,J10,$N:$N) -> 100 | P10: =COUNTIFS(E:E,K10,D:D,J10) -> 3 | Q10: =SUMIF($J:$J,J10,$P:$P) -> 32 | R10: =SUMIFS(F:F,E:E,K10,D:D,J10) -> 1 | S10: =SUMIF($J:$J,P10,$P:$P) -> 0 | Z10: =SUMIF($E:$E,Y10,$F:$F) -> 0 | AB10: ACR | AC10: =SUMIF($C:$C,AB10,$F:$F) -> 7.0938665 | AD10: =VLOOKUP(AB10,$AF:$AG,2,FALSE) -> Corporate | AF10: GP B2B | AG10: Commercial | AJ10: SOLUTION > Ready for Development | AK10: {=_xlfn.TEXTSPLIT(AJ10,">",)} -> SOLUTION | AL10: Ready for Development
B11: 9 | C11: EDO | D11: Business Solutions | E11: =VLOOKUP($C11,$AF:$AG,2,FALSE) -> Operations | F11: =H11*SUMIFS($H:$H,$J:$J,D11,$K:$K,E11)/G11 -> 0.33333333 | G11: =SUMIFS($H$2:$H$1003,$E$2:$E$1003,E11,$D$2:$D$1003,D11) -> 3 | H11: 1 | J11: Mail | K11: Corporate | L11: 20 | M11: =SUMIF($J:$J,J11,$L:$L) -> 100 | N11: =P11/Q11*100 -> 40.625 | O11: =SUMIF($J:$J,J11,$N:$N) -> 100 | P11: =COUNTIFS(E:E,K11,D:D,J11) -> 13 | Q11: =SUMIF($J:$J,J11,$P:$P) -> 32 | R11: =SUMIFS(F:F,E:E,K11,D:D,J11) -> 1 | S11: =SUMIF($J:$J,P11,$P:$P) -> 0 | Z11: =SUMIF($E:$E,Y11,$F:$F) -> 0 | AB11: EDO | AC11: =SUMIF($C:$C,AB11,$F:$F) -> 36.666669 | AD11: =VLOOKUP(AB11,$AF:$AG,2,FALSE) -> Operations | AF11: GP B2C | AG11: Commercial | AJ11: SOLUTION > In Definition | AK11: {=_xlfn.TEXTSPLIT(AJ11,">",)} -> SOLUTION | AL11: In Definition
B12: 10 | C12: SI-OPS | D12: Business Solutions | E12: =VLOOKUP($C12,$AF:$AG,2,FALSE) -> Technology | F12: =H12*SUMIFS($H:$H,$J:$J,D12,$K:$K,E12)/G12 -> 0.2 | G12: =SUMIFS($H$2:$H$1003,$E$2:$E$1003,E12,$D$2:$D$1003,D12) -> 5 | H12: 1 | J12: Mail | K12: Technology | L12: 20 | M12: =SUMIF($J:$J,J12,$L:$L) -> 100 | N12: =P12/Q12*100 -> 15.625 | O12: =SUMIF($J:$J,J12,$N:$N) -> 100 | P12: =COUNTIFS(E:E,K12,D:D,J12) -> 5 | Q12: =SUMIF($J:$J,J12,$P:$P) -> 32 | R12: =SUMIFS(F:F,E:E,K12,D:D,J12) -> 1 | S12: =SUMIF($J:$J,P12,$P:$P) -> 0 | Z12: =SUMIF($E:$E,Y12,$F:$F) -> 0 | AB12: SI-OPS | AC12: =SUMIF($C:$C,AB12,$F:$F) -> 16.000002 | AD12: =VLOOKUP(AB12,$AF:$AG,2,FALSE) -> Technology | AF12: GP ECL | AG12: Commercial
B13: 11 | C13: DNI | D13: Business Solutions | E13: =VLOOKUP($C13,$AF:$AG,2,FALSE) -> Commercial | F13: =H13*SUMIFS($H:$H,$J:$J,D13,$K:$K,E13)/G13 -> 0.11111111 | G13: =SUMIFS($H$2:$H$1003,$E$2:$E$1003,E13,$D$2:$D$1003,D13) -> 9 | H13: 1 | J13: Mail | K13: Data & AI | L13: 5 | M13: =SUMIF($J:$J,J13,$L:$L) -> 100 | N13: =P13/Q13*100 -> 3.125 | O13: =SUMIF($J:$J,J13,$N:$N) -> 100 | P13: =COUNTIFS(E:E,K13,D:D,J13) -> 1 | Q13: =SUMIF($J:$J,J13,$P:$P) -> 32 | R13: =SUMIFS(F:F,E:E,K13,D:D,J13) -> 1 | S13: =SUMIF($J:$J,P13,$P:$P) -> 0 | Z13: =SUMIF($E:$E,Y13,$F:$F) -> 0 | AB13: DNI | AC13: =SUMIF($C:$C,AB13,$F:$F) -> 16.569446 | AD13: =VLOOKUP(AB13,$AF:$AG,2,FALSE) -> Commercial | AF13: GPG | AG13: Commercial
B14: 12 | C14: AVC | D14: Business Solutions | E14: =VLOOKUP($C14,$AF:$AG,2,FALSE) -> Corporate | F14: =H14*SUMIFS($H:$H,$J:$J,D14,$K:$K,E14)/G14 -> 0.071428571 | G14: =SUMIFS($H$2:$H$1003,$E$2:$E$1003,E14,$D$2:$D$1003,D14) -> 14 | H14: 1 | J14: Mail | K14: CISO | L14: 5 | M14: =SUMIF($J:$J,J14,$L:$L) -> 100 | N14: =P14/Q14*100 -> 3.125 | O14: =SUMIF($J:$J,J14,$N:$N) -> 100 | P14: =COUNTIFS(E:E,K14,D:D,J14) -> 1 | Q14: =SUMIF($J:$J,J14,$P:$P) -> 32 | R14: =SUMIFS(F:F,E:E,K14,D:D,J14) -> 1 | S14: =SUMIF($J:$J,P14,$P:$P) -> 0 | Z14: =SUMIF($E:$E,Y14,$F:$F) -> 0 | AB14: AVC | AC14: =SUMIF($C:$C,AB14,$F:$F) -> 7.0938665 | AD14: =VLOOKUP(AB14,$AF:$AG,2,FALSE) -> Corporate | AF14: GS | AG14: Commercial
B15: 13 | C15: EM | D15: Business Solutions | E15: =VLOOKUP($C15,$AF:$AG,2,FALSE) -> Operations | F15: =H15*SUMIFS($H:$H,$J:$J,D15,$K:$K,E15)/G15 -> 0.33333333 | G15: =SUMIFS($H$2:$H$1003,$E$2:$E$1003,E15,$D$2:$D$1003,D15) -> 3 | H15: 1 | J15: Business Solutions | K15: Commercial | L15: 25 | M15: =SUMIF($J:$J,J15,$L:$L) -> 100 | N15: =P15/Q15*100 -> 27.272727 | O15: =SUMIF($J:$J,J15,$N:$N) -> 100 | P15: =COUNTIFS(E:E,K15,D:D,J15) -> 9 | Q15: =SUMIF($J:$J,J15,$P:$P) -> 33 | R15: =SUMIFS(F:F,E:E,K15,D:D,J15) -> 1 | S15: =SUMIF($J:$J,P15,$P:$P) -> 0 | AB15: EM | AC15: =SUMIF($C:$C,AB15,$F:$F) -> 31.666669 | AD15: =VLOOKUP(AB15,$AF:$AG,2,FALSE) -> Operations | AF15: IDC | AG15: Commercial
B16: 14 | C16: SI-PRD | D16: Business Solutions | E16: =VLOOKUP($C16,$AF:$AG,2,FALSE) -> Technology | F16: =H16*SUMIFS($H:$H,$J:$J,D16,$K:$K,E16)/G16 -> 0.2 | G16: =SUMIFS($H$2:$H$1003,$E$2:$E$1003,E16,$D$2:$D$1003,D16) -> 5 | H16: 1 | J16: Business Solutions | K16: Operations | L16: 25 | M16: =SUMIF($J:$J,J16,$L:$L) -> 100 | N16: =P16/Q16*100 -> 9.0909091 | O16: =SUMIF($J:$J,J16,$N:$N) -> 100 | P16: =COUNTIFS(E:E,K16,D:D,J16) -> 3 | Q16: =SUMIF($J:$J,J16,$P:$P) -> 33 | R16: =SUMIFS(F:F,E:E,K16,D:D,J16) -> 1 | S16: =SUMIF($J:$J,P16,$P:$P) -> 0 | AB16: SI-PRD | AC16: =SUMIF($C:$C,AB16,$F:$F) -> 16.000002 | AD16: =VLOOKUP(AB16,$AF:$AG,2,FALSE) -> Technology | AF16: ACR | AG16: Corporate
B17: 15 | C17: CSI | D17: Business Solutions | E17: =VLOOKUP($C17,$AF:$AG,2,FALSE) -> Commercial | F17: =H17*SUMIFS($H:$H,$J:$J,D17,$K:$K,E17)/G17 -> 0.11111111 | G17: =SUMIFS($H$2:$H$1003,$E$2:$E$1003,E17,$D$2:$D$1003,D17) -> 9 | H17: 1 | J17: Business Solutions | K17: Corporate | L17: 20 | M17: =SUMIF($J:$J,J17,$L:$L) -> 100 | N17: =P17/Q17*100 -> 42.424242 | O17: =SUMIF($J:$J,J17,$N:$N) -> 100 | P17: =COUNTIFS(E:E,K17,D:D,J17) -> 14 | Q17: =SUMIF($J:$J,J17,$P:$P) -> 33 | R17: =SUMIFS(F:F,E:E,K17,D:D,J17) -> 1 | S17: =SUMIF($J:$J,P17,$P:$P) -> 0 | AB17: CSI | AC17: =SUMIF($C:$C,AB17,$F:$F) -> 10.569446 | AD17: =VLOOKUP(AB17,$AF:$AG,2,FALSE) -> Commercial | AF17: ATC | AG17: Corporate
B18: 16 | C18: GT | D18: Business Solutions | E18: =VLOOKUP($C18,$AF:$AG,2,FALSE) -> Corporate | F18: =H18*SUMIFS($H:$H,$J:$J,D18,$K:$K,E18)/G18 -> 0.071428571 | G18: =SUMIFS($H$2:$H$1003,$E$2:$E$1003,E18,$D$2:$D$1003,D18) -> 14 | H18: 1 | J18: Business Solutions | K18: Technology | L18: 20 | M18: =SUMIF($J:$J,J18,$L:$L) -> 100 | N18: =P18/Q18*100 -> 15.151515 | O18: =SUMIF($J:$J,J18,$N:$N) -> 100 | P18: =COUNTIFS(E:E,K18,D:D,J18) -> 5 | Q18: =SUMIF($J:$J,J18,$P:$P) -> 33 | R18: =SUMIFS(F:F,E:E,K18,D:D,J18) -> 1 | S18: =SUMIF($J:$J,P18,$P:$P) -> 0 | U18: RevenueStream;BudgetGroup;Weight | AB18: GT | AC18: =SUMIF($C:$C,AB18,$F:$F) -> 7.0938665 | AD18: =VLOOKUP(AB18,$AF:$AG,2,FALSE) -> Corporate | AF18: AVC | AG18: Corporate
B19: 17 | C19: BCTT | D19: Business Solutions | E19: =VLOOKUP($C19,$AF:$AG,2,FALSE) -> Technology | F19: =H19*SUMIFS($H:$H,$J:$J,D19,$K:$K,E19)/G19 -> 0.2 | G19: =SUMIFS($H$2:$H$1003,$E$2:$E$1003,E19,$D$2:$D$1003,D19) -> 5 | H19: 1 | J19: Business Solutions | K19: Data & AI | L19: 5 | M19: =SUMIF($J:$J,J19,$L:$L) -> 100 | N19: =P19/Q19*100 -> 3.030303 | O19: =SUMIF($J:$J,J19,$N:$N) -> 100 | P19: =COUNTIFS(E:E,K19,D:D,J19) -> 1 | Q19: =SUMIF($J:$J,J19,$P:$P) -> 33 | R19: =SUMIFS(F:F,E:E,K19,D:D,J19) -> 1 | S19: =SUMIF($J:$J,P19,$P:$P) -> 0 | AB19: BCTT | AC19: =SUMIF($C:$C,AB19,$F:$F) -> 16.000002 | AD19: =VLOOKUP(AB19,$AF:$AG,2,FALSE) -> Technology | AF19: CF | AG19: Corporate
B20: 18 | C20: GP B2C | D20: Business Solutions | E20: =VLOOKUP($C20,$AF:$AG,2,FALSE) -> Commercial | F20: =H20*SUMIFS($H:$H,$J:$J,D20,$K:$K,E20)/G20 -> 0.11111111 | G20: =SUMIFS($H$2:$H$1003,$E$2:$E$1003,E20,$D$2:$D$1003,D20) -> 9 | H20: 1 | J20: Business Solutions | K20: CISO | L20: 5 | M20: =SUMIF($J:$J,J20,$L:$L) -> 100 | N20: =P20/Q20*100 -> 3.030303 | O20: =SUMIF($J:$J,J20,$N:$N) -> 100 | P20: =COUNTIFS(E:E,K20,D:D,J20) -> 1 | Q20: =SUMIF($J:$J,J20,$P:$P) -> 33 | R20: =SUMIFS(F:F,E:E,K20,D:D,J20) -> 1 | S20: =SUMIF($J:$J,P20,$P:$P) -> 0 | AB20: GP B2C | AC20: =SUMIF($C:$C,AB20,$F:$F) -> 9.5694464 | AD20: =VLOOKUP(AB20,$AF:$AG,2,FALSE) -> Commercial | AF20: CFO | AG20: Corporate
B21: 19 | C21: GRH | D21: Business Solutions | E21: =VLOOKUP($C21,$AF:$AG,2,FALSE) -> Corporate | F21: =H21*SUMIFS($H:$H,$J:$J,D21,$K:$K,E21)/G21 -> 0.071428571 | G21: =SUMIFS($H$2:$H$1003,$E$2:$E$1003,E21,$D$2:$D$1003,D21) -> 14 | H21: 1 | J21: Retail & Financial Services | K21: Commercial | L21: 25 | M21: =SUMIF($J:$J,J21,$L:$L) -> 100 | N21: =P21/Q21*100 -> 25 | O21: =SUMIF($J:$J,J21,$N:$N) -> 100 | P21: =COUNTIFS(E:E,K21,D:D,J21) -> 8 | Q21: =SUMIF($J:$J,J21,$P:$P) -> 32 | R21: =SUMIFS(F:F,E:E,K21,D:D,J21) -> 1 | S21: =SUMIF($J:$J,P21,$P:$P) -> 0 | AB21: GRH | AC21: =SUMIF($C:$C,AB21,$F:$F) -> 7.0938665 | AD21: =VLOOKUP(AB21,$AF:$AG,2,FALSE) -> Corporate | AF21: CHR | AG21: Corporate
B22: 20 | C22: SI-CRP | D22: Business Solutions | E22: =VLOOKUP($C22,$AF:$AG,2,FALSE) -> Technology | F22: =H22*SUMIFS($H:$H,$J:$J,D22,$K:$K,E22)/G22 -> 0.2 | G22: =SUMIFS($H$2:$H$1003,$E$2:$E$1003,E22,$D$2:$D$1003,D22) -> 5 | H22: 1 | J22: Retail & Financial Services | K22: Operations | L22: 25 | M22: =SUMIF($J:$J,J22,$L:$L) -> 100 | N22: =P22/Q22*100 -> 9.375 | O22: =SUMIF($J:$J,J22,$N:$N) -> 100 | P22: =COUNTIFS(E:E,K22,D:D,J22) -> 3 | Q22: =SUMIF($J:$J,J22,$P:$P) -> 32 | R22: =SUMIFS(F:F,E:E,K22,D:D,J22) -> 1 | S22: =SUMIF($J:$J,P22,$P:$P) -> 0 | AB22: SI-CRP | AC22: =SUMIF($C:$C,AB22,$F:$F) -> 16.000002 | AD22: =VLOOKUP(AB22,$AF:$AG,2,FALSE) -> Technology | AF22: CL | AG22: Corporate
B23: 21 | C23: GP ECL | D23: Business Solutions | E23: =VLOOKUP($C23,$AF:$AG,2,FALSE) -> Commercial | F23: =H23*SUMIFS($H:$H,$J:$J,D23,$K:$K,E23)/G23 -> 0.11111111 | G23: =SUMIFS($H$2:$H$1003,$E$2:$E$1003,E23,$D$2:$D$1003,D23) -> 9 | H23: 1 | J23: Retail & Financial Services | K23: Corporate | L23: 20 | M23: =SUMIF($J:$J,J23,$L:$L) -> 100 | N23: =P23/Q23*100 -> 25 | O23: =SUMIF($J:$J,J23,$N:$N) -> 100 | P23: =COUNTIFS(E:E,K23,D:D,J23) -> 8 | Q23: =SUMIF($J:$J,J23,$P:$P) -> 32 | R23: =SUMIFS(F:F,E:E,K23,D:D,J23) -> 1 | S23: =SUMIF($J:$J,P23,$P:$P) -> 0 | AB23: GP ECL | AC23: =SUMIF($C:$C,AB23,$F:$F) -> 16.569446 | AD23: =VLOOKUP(AB23,$AF:$AG,2,FALSE) -> Commercial | AF23: CMP | AG23: Corporate
B24: 22 | C24: PC | D24: Business Solutions | E24: =VLOOKUP($C24,$AF:$AG,2,FALSE) -> Corporate | F24: =H24*SUMIFS($H:$H,$J:$J,D24,$K:$K,E24)/G24 -> 0.071428571 | G24: =SUMIFS($H$2:$H$1003,$E$2:$E$1003,E24,$D$2:$D$1003,D24) -> 14 | H24: 1 | J24: Retail & Financial Services | K24: Technology | L24: 20 | M24: =SUMIF($J:$J,J24,$L:$L) -> 100 | N24: =P24/Q24*100 -> 15.625 | O24: =SUMIF($J:$J,J24,$N:$N) -> 100 | P24: =COUNTIFS(E:E,K24,D:D,J24) -> 5 | Q24: =SUMIF($J:$J,J24,$P:$P) -> 32 | R24: =SUMIFS(F:F,E:E,K24,D:D,J24) -> 1 | S24: =SUMIF($J:$J,P24,$P:$P) -> 0 | AB24: PC | AC24: =SUMIF($C:$C,AB24,$F:$F) -> 7.0938665 | AD24: =VLOOKUP(AB24,$AF:$AG,2,FALSE) -> Corporate | AF24: COM | AG24: Corporate
B25: 23 | C25: GPG | D25: Business Solutions | E25: =VLOOKUP($C25,$AF:$AG,2,FALSE) -> Commercial | F25: =H25*SUMIFS($H:$H,$J:$J,D25,$K:$K,E25)/G25 -> 0.11111111 | G25: =SUMIFS($H$2:$H$1003,$E$2:$E$1003,E25,$D$2:$D$1003,D25) -> 9 | H25: 1 | J25: Retail & Financial Services | K25: Data & AI | L25: 5 | M25: =SUMIF($J:$J,J25,$L:$L) -> 100 | N25: =P25/Q25*100 -> 21.875 | O25: =SUMIF($J:$J,J25,$N:$N) -> 100 | P25: =COUNTIFS(E:E,K25,D:D,J25) -> 7 | Q25: =SUMIF($J:$J,J25,$P:$P) -> 32 | R25: =SUMIFS(F:F,E:E,K25,D:D,J25) -> 1 | S25: =SUMIF($J:$J,P25,$P:$P) -> 0 | AB25: GPG | AC25: =SUMIF($C:$C,AB25,$F:$F) -> 9.5694464 | AD25: =VLOOKUP(AB25,$AF:$AG,2,FALSE) -> Commercial | AF25: DPO | AG25: Corporate
B26: 24 | C26: RS | D26: Business Solutions | E26: =VLOOKUP($C26,$AF:$AG,2,FALSE) -> Corporate | F26: =H26*SUMIFS($H:$H,$J:$J,D26,$K:$K,E26)/G26 -> 0.071428571 | G26: =SUMIFS($H$2:$H$1003,$E$2:$E$1003,E26,$D$2:$D$1003,D26) -> 14 | H26: 1 | J26: Retail & Financial Services | K26: CISO | L26: 5 | M26: =SUMIF($J:$J,J26,$L:$L) -> 100 | N26: =P26/Q26*100 -> 3.125 | O26: =SUMIF($J:$J,J26,$N:$N) -> 100 | P26: =COUNTIFS(E:E,K26,D:D,J26) -> 1 | Q26: =SUMIF($J:$J,J26,$P:$P) -> 32 | R26: =SUMIFS(F:F,E:E,K26,D:D,J26) -> 1 | S26: =SUMIF($J:$J,P26,$P:$P) -> 0 | AB26: RS | AC26: =SUMIF($C:$C,AB26,$F:$F) -> 7.0938665 | AD26: =VLOOKUP(AB26,$AF:$AG,2,FALSE) -> Corporate | AF26: FL | AG26: Corporate
B27: 25 | C27: ECM | D27: Business Solutions | E27: =VLOOKUP($C27,$AF:$AG,2,FALSE) -> Commercial | F27: =H27*SUMIFS($H:$H,$J:$J,D27,$K:$K,E27)/G27 -> 0.11111111 | G27: =SUMIFS($H$2:$H$1003,$E$2:$E$1003,E27,$D$2:$D$1003,D27) -> 9 | H27: 1 | J27: Payments | K27: Commercial | L27: 25 | M27: =SUMIF($J:$J,J27,$L:$L) -> 100 | N27: =P27/Q27*100 -> 28.125 | O27: =SUMIF($J:$J,J27,$N:$N) -> 100 | P27: =COUNTIFS(E:E,K27,D:D,J27) -> 9 | Q27: =SUMIF($J:$J,J27,$P:$P) -> 32 | R27: =SUMIFS(F:F,E:E,K27,D:D,J27) -> 1 | S27: =SUMIF($J:$J,P27,$P:$P) -> 0 | AB27: ECM | AC27: =SUMIF($C:$C,AB27,$F:$F) -> 3.5694464 | AD27: =VLOOKUP(AB27,$AF:$AG,2,FALSE) -> Commercial | AF27: GRH | AG27: Corporate
B28: 26 | C28: CL | D28: Business Solutions | E28: =VLOOKUP($C28,$AF:$AG,2,FALSE) -> Corporate | F28: =H28*SUMIFS($H:$H,$J:$J,D28,$K:$K,E28)/G28 -> 0.071428571 | G28: =SUMIFS($H$2:$H$1003,$E$2:$E$1003,E28,$D$2:$D$1003,D28) -> 14 | H28: 1 | J28: Payments | K28: Operations | L28: 25 | M28: =SUMIF($J:$J,J28,$L:$L) -> 100 | N28: =P28/Q28*100 -> 9.375 | O28: =SUMIF($J:$J,J28,$N:$N) -> 100 | P28: =COUNTIFS(E:E,K28,D:D,J28) -> 3 | Q28: =SUMIF($J:$J,J28,$P:$P) -> 32 | R28: =SUMIFS(F:F,E:E,K28,D:D,J28) -> 1 | S28: =SUMIF($J:$J,P28,$P:$P) -> 0 | AB28: CL | AC28: =SUMIF($C:$C,AB28,$F:$F) -> 7.0938665 | AD28: =VLOOKUP(AB28,$AF:$AG,2,FALSE) -> Corporate | AF28: GT | AG28: Corporate
B29: 27 | C29: CTTE | D29: Business Solutions | E29: =VLOOKUP($C29,$AF:$AG,2,FALSE) -> Commercial | F29: =H29*SUMIFS($H:$H,$J:$J,D29,$K:$K,E29)/G29 -> 0.11111111 | G29: =SUMIFS($H$2:$H$1003,$E$2:$E$1003,E29,$D$2:$D$1003,D29) -> 9 | H29: 1 | J29: Payments | K29: Corporate | L29: 20 | M29: =SUMIF($J:$J,J29,$L:$L) -> 100 | N29: =P29/Q29*100 -> 40.625 | O29: =SUMIF($J:$J,J29,$N:$N) -> 100 | P29: =COUNTIFS(E:E,K29,D:D,J29) -> 13 | Q29: =SUMIF($J:$J,J29,$P:$P) -> 32 | R29: =SUMIFS(F:F,E:E,K29,D:D,J29) -> 1 | S29: =SUMIF($J:$J,P29,$P:$P) -> 0 | AB29: CTTE | AC29: =SUMIF($C:$C,AB29,$F:$F) -> 9.5873036 | AD29: =VLOOKUP(AB29,$AF:$AG,2,FALSE) -> Commercial | AF29: PC | AG29: Corporate
B30: 28 | C30: DPO | D30: Business Solutions | E30: =VLOOKUP($C30,$AF:$AG,2,FALSE) -> Corporate | F30: =H30*SUMIFS($H:$H,$J:$J,D30,$K:$K,E30)/G30 -> 0.071428571 | G30: =SUMIFS($H$2:$H$1003,$E$2:$E$1003,E30,$D$2:$D$1003,D30) -> 14 | H30: 1 | J30: Payments | K30: Technology | L30: 20 | M30: =SUMIF($J:$J,J30,$L:$L) -> 100 | N30: =P30/Q30*100 -> 15.625 | O30: =SUMIF($J:$J,J30,$N:$N) -> 100 | P30: =COUNTIFS(E:E,K30,D:D,J30) -> 5 | Q30: =SUMIF($J:$J,J30,$P:$P) -> 32 | R30: =SUMIFS(F:F,E:E,K30,D:D,J30) -> 1 | S30: =SUMIF($J:$J,P30,$P:$P) -> 0 | AB30: DPO | AC30: =SUMIF($C:$C,AB30,$F:$F) -> 7.1117236 | AD30: =VLOOKUP(AB30,$AF:$AG,2,FALSE) -> Corporate | AF30: PRO | AG30: Corporate
... B35: 33 | C35: NSP | D35: Business Solutions | E35: =VLOOKUP($C35,$AF:$AG,2,FALSE) -> Corporate | F35: =H35*SUMIFS($H:$H,$J:$J,D35,$K:$K,E35)/G35 -> 0.071428571 | G35: =SUMIFS($H$2:$H$1003,$E$2:$E$1003,E35,$D$2:$D$1003,D35) -> 14 | H35: 1 | J35: Fulfilment | K35: Corporate | L35: 20 | M35: =SUMIF($J:$J,J35,$L:$L) -> 100 | N35: =P35/Q35*100 -> 40.625 | O35: =SUMIF($J:$J,J35,$N:$N) -> 100 | P35: =COUNTIFS(E:E,K35,D:D,J35) -> 13 | Q35: =SUMIF($J:$J,J35,$P:$P) -> 32 | R35: =SUMIFS(F:F,E:E,K35,D:D,J35) -> 1 | S35: =SUMIF($J:$J,P35,$P:$P) -> 0 | AB35: NSP | AC35: =SUMIF($C:$C,AB35,$F:$F) -> 6.7380952 | AD35: =VLOOKUP(AB35,$AF:$AG,2,FALSE) -> Corporate | AF35: EDO | AG35: Operations
B36: 1 | C36: COO | D36: eCommerce | E36: =VLOOKUP($C36,$AF:$AG,2,FALSE) -> Operations | F36: 20 | G36: =SUMIFS($H$2:$H$1003,$E$2:$E$1003,E36,$D$2:$D$1003,D36) -> 4 | H36: 1 | J36: Fulfilment | K36: Technology | L36: 20 | M36: =SUMIF($J:$J,J36,$L:$L) -> 100 | N36: =P36/Q36*100 -> 15.625 | O36: =SUMIF($J:$J,J36,$N:$N) -> 100 | P36: =COUNTIFS(E:E,K36,D:D,J36) -> 5 | Q36: =SUMIF($J:$J,J36,$P:$P) -> 32 | R36: =SUMIFS(F:F,E:E,K36,D:D,J36) -> 1 | S36: =SUMIF($J:$J,P36,$P:$P) -> 0 | AB36: COO | AC36: =SUMIF($C:$C,AB36,$F:$F) -> 20.000001 | AD36: =VLOOKUP(AB36,$AF:$AG,2,FALSE) -> Operations | AF36: EM | AG36: Operations
B37: 2 | C37: CMO | D37: eCommerce | E37: =VLOOKUP($C37,$AF:$AG,2,FALSE) -> Commercial | F37: 12 | G37: =SUMIFS($H$2:$H$1003,$E$2:$E$1003,E37,$D$2:$D$1003,D37) -> 12 | H37: 1 | J37: Fulfilment | K37: Data & AI | L37: 5 | M37: =SUMIF($J:$J,J37,$L:$L) -> 100 | N37: =P37/Q37*100 -> 3.125 | O37: =SUMIF($J:$J,J37,$N:$N) -> 100 | P37: =COUNTIFS(E:E,K37,D:D,J37) -> 1 | Q37: =SUMIF($J:$J,J37,$P:$P) -> 32 | R37: =SUMIFS(F:F,E:E,K37,D:D,J37) -> 1 | S37: =SUMIF($J:$J,P37,$P:$P) -> 0 | AB37: CMO | AC37: =SUMIF($C:$C,AB37,$F:$F) -> 12.000001 | AD37: =VLOOKUP(AB37,$AF:$AG,2,FALSE) -> Commercial | AF37: EM | AG37: Operations
B38: 3 | C38: ATC | D38: eCommerce | E38: =VLOOKUP($C38,$AF:$AG,2,FALSE) -> Corporate | F38: 12 | G38: =SUMIFS($H$2:$H$1003,$E$2:$E$1003,E38,$D$2:$D$1003,D38) -> 18 | H38: 1 | J38: Fulfilment | K38: CISO | L38: 5 | M38: =SUMIF($J:$J,J38,$L:$L) -> 100 | N38: =P38/Q38*100 -> 3.125 | O38: =SUMIF($J:$J,J38,$N:$N) -> 100 | P38: =COUNTIFS(E:E,K38,D:D,J38) -> 1 | Q38: =SUMIF($J:$J,J38,$P:$P) -> 32 | R38: =SUMIFS(F:F,E:E,K38,D:D,J38) -> 1 | S38: =SUMIF($J:$J,P38,$P:$P) -> 0 | AB38: ATC | AC38: =SUMIF($C:$C,AB38,$F:$F) -> 12.000001 | AD38: =VLOOKUP(AB38,$AF:$AG,2,FALSE) -> Corporate | AF38: SEO | AG38: Operations
B39: 4 | C39: CCO | D39: eCommerce | E39: =VLOOKUP($C39,$AF:$AG,2,FALSE) -> Commercial | F39: 8 | G39: =SUMIFS($H$2:$H$1003,$E$2:$E$1003,E39,$D$2:$D$1003,D39) -> 12 | H39: 1 | J39: Mail & Services | K39: Commercial | L39: 25 | N39: 38 | AB39: CCO | AC39: =SUMIF($C:$C,AB39,$F:$F) -> 8.000001 | AD39: =VLOOKUP(AB39,$AF:$AG,2,FALSE) -> Commercial | AF39: BCTT | AG39: Technology
B40: 5 | C40: IDC | D40: eCommerce | E40: =VLOOKUP($C40,$AF:$AG,2,FALSE) -> Commercial | F40: 8 | G40: =SUMIFS($H$2:$H$1003,$E$2:$E$1003,E40,$D$2:$D$1003,D40) -> 12 | H40: 1 | J40: Mail & Services | K40: Operations | L40: 25 | N40: 19 | AB40: IDC | AC40: =SUMIF($C:$C,AB40,$F:$F) -> 8.000001 | AD40: =VLOOKUP(AB40,$AF:$AG,2,FALSE) -> Commercial | AF40: CIO | AG40: Technology
B41: 6 | C41: CFO | D41: eCommerce | E41: =VLOOKUP($C41,$AF:$AG,2,FALSE) -> Corporate | F41: 12 | G41: =SUMIFS($H$2:$H$1003,$E$2:$E$1003,E41,$D$2:$D$1003,D41) -> 18 | H41: 1 | J41: Mail & Services | K41: Corporate | L41: 20 | N41: 19 | AB41: CFO | AC41: =SUMIF($C:$C,AB41,$F:$F) -> 12.000001 | AD41: =VLOOKUP(AB41,$AF:$AG,2,FALSE) -> Corporate | AF41: SI | AG41: Technology
B42: 7 | C42: CIO | D42: eCommerce | E42: =VLOOKUP($C42,$AF:$AG,2,FALSE) -> Technology | F42: 15 | G42: =SUMIFS($H$2:$H$1003,$E$2:$E$1003,E42,$D$2:$D$1003,D42) -> 6 | H42: 1 | J42: Mail & Services | K42: Technology | L42: 20 | N42: 17 | AB42: CIO | AC42: =SUMIF($C:$C,AB42,$F:$F) -> 15.000001 | AD42: =VLOOKUP(AB42,$AF:$AG,2,FALSE) -> Technology | AF42: SI-CRP | AG42: Technology
B43: 8 | C43: PRO | D43: eCommerce | E43: =VLOOKUP($C43,$AF:$AG,2,FALSE) -> Corporate | F43: 7 | G43: =SUMIFS($H$2:$H$1003,$E$2:$E$1003,E43,$D$2:$D$1003,D43) -> 18 | H43: 1 | J43: Mail & Services | K43: Data & AI | L43: 5 | N43: 5 | AB43: PRO | AC43: =SUMIF($C:$C,AB43,$F:$F) -> 7.000001 | AD43: =VLOOKUP(AB43,$AF:$AG,2,FALSE) -> Corporate | AF43: SI-OPS | AG43: Technology
B44: 9 | C44: CHR | D44: eCommerce | E44: =VLOOKUP($C44,$AF:$AG,2,FALSE) -> Corporate | F44: 3 | G44: =SUMIFS($H$2:$H$1003,$E$2:$E$1003,E44,$D$2:$D$1003,D44) -> 18 | H44: 1 | J44: Mail & Services | K44: CISO | L44: 5 | N44: 2 | AB44: CHR | AC44: =SUMIF($C:$C,AB44,$F:$F) -> 3.000001 | AD44: =VLOOKUP(AB44,$AF:$AG,2,FALSE) -> Corporate | AF44: SI-PRD | AG44: Technology
B45: 11 | C45: COM | D45: eCommerce | E45: =VLOOKUP($C45,$AF:$AG,2,FALSE) -> Corporate | F45: 3 | G45: =SUMIFS($H$2:$H$1003,$E$2:$E$1003,E45,$D$2:$D$1003,D45) -> 18 | H45: 1 | AB45: COM | AC45: =SUMIF($C:$C,AB45,$F:$F) -> 3.000001 | AD45: =VLOOKUP(AB45,$AF:$AG,2,FALSE) -> Corporate | AF45: IAD | AG45: Data & AI
B46: 12 | C46: GP ECL | D46: eCommerce | E46: =VLOOKUP($C46,$AF:$AG,2,FALSE) -> Commercial | F46: 1e-06 | G46: =SUMIFS($H$2:$H$1003,$E$2:$E$1003,E46,$D$2:$D$1003,D46) -> 12 | H46: 1 | AB46: SSJ | AC46: =SUMIF($C:$C,AB46,$F:$F) -> 4.4444444 | AD46: =VLOOKUP(AB46,$AF:$AG,2,FALSE) -> Corporate | AF46: NSP | AG46: Corporate
B47: 13 | C47: CISO | D47: eCommerce | E47: =VLOOKUP($C47,$AF:$AG,2,FALSE) -> CISO | F47: 1e-06 | G47: =SUMIFS($H$2:$H$1003,$E$2:$E$1003,E47,$D$2:$D$1003,D47) -> 1 | H47: 1 | AB47: RC | AD47: =VLOOKUP(AB47,$AF:$AG,2,FALSE) -> Corporate | AF47: SSJ | AG47: Corporate
B48: 14 | C48: IAD | D48: eCommerce | E48: =VLOOKUP($C48,$AF:$AG,2,FALSE) -> Data & AI | F48: 1e-06 | G48: =SUMIFS($H$2:$H$1003,$E$2:$E$1003,E48,$D$2:$D$1003,D48) -> 1 | H48: 1 | AB48: 0 | AF48: RC | AG48: Corporate
B49: 15 | C49: GS | D49: eCommerce | E49: =VLOOKUP($C49,$AF:$AG,2,FALSE) -> Commercial | F49: 1e-06 | G49: =SUMIFS($H$2:$H$1003,$E$2:$E$1003,E49,$D$2:$D$1003,D49) -> 12 | H49: 1
B50: 16 | C50: EDO | D50: eCommerce | E50: =VLOOKUP($C50,$AF:$AG,2,FALSE) -> Operations | F50: 1e-06 | G50: =SUMIFS($H$2:$H$1003,$E$2:$E$1003,E50,$D$2:$D$1003,D50) -> 4 | H50: 1
B51: 17 | C51: ACR | D51: eCommerce | E51: =VLOOKUP($C51,$AF:$AG,2,FALSE) -> Corporate | F51: 1e-06 | G51: =SUMIFS($H$2:$H$1003,$E$2:$E$1003,E51,$D$2:$D$1003,D51) -> 18 | H51: 1
B52: 18 | C52: SI | D52: eCommerce | E52: =VLOOKUP($C52,$AF:$AG,2,FALSE) -> Technology | F52: 1e-06 | G52: =SUMIFS($H$2:$H$1003,$E$2:$E$1003,E52,$D$2:$D$1003,D52) -> 6 | H52: 1
B53: 19 | C53: SEO | D53: eCommerce | E53: =VLOOKUP($C53,$AF:$AG,2,FALSE) -> Operations | F53: 1e-06 | G53: =SUMIFS($H$2:$H$1003,$E$2:$E$1003,E53,$D$2:$D$1003,D53) -> 4 | H53: 1
B54: 20 | C54: CF | D54: eCommerce | E54: =VLOOKUP($C54,$AF:$AG,2,FALSE) -> Corporate | F54: 1e-06 | G54: =SUMIFS($H$2:$H$1003,$E$2:$E$1003,E54,$D$2:$D$1003,D54) -> 18 | H54: 1
B55: 21 | C55: SI-OPS | D55: eCommerce | E55: =VLOOKUP($C55,$AF:$AG,2,FALSE) -> Technology | F55: 1e-06 | G55: =SUMIFS($H$2:$H$1003,$E$2:$E$1003,E55,$D$2:$D$1003,D55) -> 6 | H55: 1
B56: 22 | C56: BCTT | D56: eCommerce | E56: =VLOOKUP($C56,$AF:$AG,2,FALSE) -> Technology | F56: 1e-06 | G56: =SUMIFS($H$2:$H$1003,$E$2:$E$1003,E56,$D$2:$D$1003,D56) -> 6 | H56: 1
B57: 23 | C57: SI-PRD | D57: eCommerce | E57: =VLOOKUP($C57,$AF:$AG,2,FALSE) -> Technology | F57: 1e-06 | G57: =SUMIFS($H$2:$H$1003,$E$2:$E$1003,E57,$D$2:$D$1003,D57) -> 6 | H57: 1
B58: 24 | C58: AVC | D58: eCommerce | E58: =VLOOKUP($C58,$AF:$AG,2,FALSE) -> Corporate | F58: 1e-06 | G58: =SUMIFS($H$2:$H$1003,$E$2:$E$1003,E58,$D$2:$D$1003,D58) -> 18 | H58: 1
B59: 25 | C59: EM | D59: eCommerce | E59: =VLOOKUP($C59,$AF:$AG,2,FALSE) -> Operations | F59: 1e-06 | G59: =SUMIFS($H$2:$H$1003,$E$2:$E$1003,E59,$D$2:$D$1003,D59) -> 4 | H59: 1
B60: 26 | C60: DNI | D60: eCommerce | E60: =VLOOKUP($C60,$AF:$AG,2,FALSE) -> Commercial | F60: 1e-06 | G60: =SUMIFS($H$2:$H$1003,$E$2:$E$1003,E60,$D$2:$D$1003,D60) -> 12 | H60: 1
... B77: 43 | C77: CTTE | D77: eCommerce | E77: =VLOOKUP($C77,$AF:$AG,2,FALSE) -> Commercial | F77: 1e-06 | G77: =SUMIFS($H$2:$H$1003,$E$2:$E$1003,E77,$D$2:$D$1003,D77) -> 12 | H77: 1
B78: 1 | C78: GP ECL | D78: Fulfilment | E78: =VLOOKUP($C78,$AF:$AG,2,FALSE) -> Commercial | F78: =H78*SUMIFS($H:$H,$J:$J,D78,$K:$K,E78)/G78 -> 0.11111111 | G78: =SUMIFS($H$2:$H$1003,$E$2:$E$1003,E78,$D$2:$D$1003,D78) -> 9 | H78: 1
B79: 2 | C79: SEO | D79: Fulfilment | E79: =VLOOKUP($C79,$AF:$AG,2,FALSE) -> Operations | F79: =H79*SUMIFS($H:$H,$J:$J,D79,$K:$K,E79)/G79 -> 0.33333333 | G79: =SUMIFS($H$2:$H$1003,$E$2:$E$1003,E79,$D$2:$D$1003,D79) -> 3 | H79: 1
B80: 3 | C80: CF | D80: Fulfilment | E80: =VLOOKUP($C80,$AF:$AG,2,FALSE) -> Corporate | F80: =H80*SUMIFS($H:$H,$J:$J,D80,$K:$K,E80)/G80 -> 0.076923077 | G80: =SUMIFS($H$2:$H$1003,$E$2:$E$1003,E80,$D$2:$D$1003,D80) -> 13 | H80: 1
B81: 4 | C81: SI | D81: Fulfilment | E81: =VLOOKUP($C81,$AF:$AG,2,FALSE) -> Technology | F81: =H81*SUMIFS($H:$H,$J:$J,D81,$K:$K,E81)/G81 -> 0.2 | G81: =SUMIFS($H$2:$H$1003,$E$2:$E$1003,E81,$D$2:$D$1003,D81) -> 5 | H81: 1
B82: 5 | C82: CISO | D82: Fulfilment | E82: =VLOOKUP($C82,$AF:$AG,2,FALSE) -> CISO | F82: =H82*SUMIFS($H:$H,$J:$J,D82,$K:$K,E82)/G82 -> 1 | G82: =SUMIFS($H$2:$H$1003,$E$2:$E$1003,E82,$D$2:$D$1003,D82) -> 1 | H82: 1
B83: 6 | C83: IAD | D83: Fulfilment | E83: =VLOOKUP($C83,$AF:$AG,2,FALSE) -> Data & AI | F83: =H83*SUMIFS($H:$H,$J:$J,D83,$K:$K,E83)/G83 -> 1 | G83: =SUMIFS($H$2:$H$1003,$E$2:$E$1003,E83,$D$2:$D$1003,D83) -> 1 | H83: 1
B84: 7 | C84: GS | D84: Fulfilment | E84: =VLOOKUP($C84,$AF:$AG,2,FALSE) -> Commercial | F84: =H84*SUMIFS($H:$H,$J:$J,D84,$K:$K,E84)/G84 -> 0.11111111 | G84: =SUMIFS($H$2:$H$1003,$E$2:$E$1003,E84,$D$2:$D$1003,D84) -> 9 | H84: 1
B85: 8 | C85: ACR | D85: Fulfilment | E85: =VLOOKUP($C85,$AF:$AG,2,FALSE) -> Corporate | F85: =H85*SUMIFS($H:$H,$J:$J,D85,$K:$K,E85)/G85 -> 0.076923077 | G85: =SUMIFS($H$2:$H$1003,$E$2:$E$1003,E85,$D$2:$D$1003,D85) -> 13 | H85: 1
B86: 9 | C86: EDO | D86: Fulfilment | E86: =VLOOKUP($C86,$AF:$AG,2,FALSE) -> Operations | F86: =H86*SUMIFS($H:$H,$J:$J,D86,$K:$K,E86)/G86 -> 0.33333333 | G86: =SUMIFS($H$2:$H$1003,$E$2:$E$1003,E86,$D$2:$D$1003,D86) -> 3 | H86: 1
B87: 10 | C87: SI-OPS | D87: Fulfilment | E87: =VLOOKUP($C87,$AF:$AG,2,FALSE) -> Technology | F87: =H87*SUMIFS($H:$H,$J:$J,D87,$K:$K,E87)/G87 -> 0.2 | G87: =SUMIFS($H$2:$H$1003,$E$2:$E$1003,E87,$D$2:$D$1003,D87) -> 5 | H87: 1
B88: 11 | C88: DNI | D88: Fulfilment | E88: =VLOOKUP($C88,$AF:$AG,2,FALSE) -> Commercial | F88: =H88*SUMIFS($H:$H,$J:$J,D88,$K:$K,E88)/G88 -> 0.11111111 | G88: =SUMIFS($H$2:$H$1003,$E$2:$E$1003,E88,$D$2:$D$1003,D88) -> 9 | H88: 1
B89: 12 | C89: AVC | D89: Fulfilment | E89: =VLOOKUP($C89,$AF:$AG,2,FALSE) -> Corporate | F89: =H89*SUMIFS($H:$H,$J:$J,D89,$K:$K,E89)/G89 -> 0.076923077 | G89: =SUMIFS($H$2:$H$1003,$E$2:$E$1003,E89,$D$2:$D$1003,D89) -> 13 | H89: 1
... B199: 26 | C199: CL | D199: Retail & Financial Services | E199: =VLOOKUP($C199,$AF:$AG,2,FALSE) -> Corporate | F199: =H199*SUMIFS($H:$H,$J:$J,D199,$K:$K,E199)/G199 -> 0.125 | G199: =SUMIFS($H$2:$H$1003,$E$2:$E$1003,E199,$D$2:$D$1003,D199) -> 8 | H199: 1
B200: 27 | C200: CTTE | D200: Retail & Financial Services | E200: Data & AI | F200: =H200*SUMIFS($H:$H,$J:$J,D200,$K:$K,E200)/G200 -> 0.14285714 | G200: =SUMIFS($H$2:$H$1003,$E$2:$E$1003,E200,$D$2:$D$1003,D200) -> 7 | H200: 1
B201: 28 | C201: DPO | D201: Retail & Financial Services | E201: Data & AI | F201: =H201*SUMIFS($H:$H,$J:$J,D201,$K:$K,E201)/G201 -> 0.14285714 | G201: =SUMIFS($H$2:$H$1003,$E$2:$E$1003,E201,$D$2:$D$1003,D201) -> 7 | H201: 1
B202: 29 | C202: CMP | D202: Retail & Financial Services | E202: Data & AI | F202: =H202*SUMIFS($H:$H,$J:$J,D202,$K:$K,E202)/G202 -> 0.14285714 | G202: =SUMIFS($H$2:$H$1003,$E$2:$E$1003,E202,$D$2:$D$1003,D202) -> 7 | H202: 1
B203: 30 | C203: ST | D203: Retail & Financial Services | E203: Data & AI | F203: =H203*SUMIFS($H:$H,$J:$J,D203,$K:$K,E203)/G203 -> 0.14285714 | G203: =SUMIFS($H$2:$H$1003,$E$2:$E$1003,E203,$D$2:$D$1003,D203) -> 7 | H203: 1
B204: 31 | C204: FL | D204: Retail & Financial Services | E204: Data & AI | F204: =H204*SUMIFS($H:$H,$J:$J,D204,$K:$K,E204)/G204 -> 0.14285714 | G204: =SUMIFS($H$2:$H$1003,$E$2:$E$1003,E204,$D$2:$D$1003,D204) -> 7 | H204: 1
B205: 32 | C205: TF | D205: Retail & Financial Services | E205: Data & AI | F205: =H205*SUMIFS($H:$H,$J:$J,D205,$K:$K,E205)/G205 -> 0.14285714 | G205: =SUMIFS($H$2:$H$1003,$E$2:$E$1003,E205,$D$2:$D$1003,D205) -> 7 | H205: 1
B206: 1 | C206: GP B2B | D206: Mail & Services | E206: =VLOOKUP($C206,$AF:$AG,2,FALSE) -> Commercial | F206: 16 | G206: 1 | H206: 1
B207: 2 | C207: GP ECL | D207: Mail & Services | E207: =VLOOKUP($C207,$AF:$AG,2,FALSE) -> Commercial | F207: 16 | G207: =SUMIFS($H$2:$H$1003,$E$2:$E$1003,E207,$D$2:$D$1003,D207) -> 9 | H207: 1
B208: 3 | C208: DNI | D208: Mail & Services | E208: =VLOOKUP($C208,$AF:$AG,2,FALSE) -> Commercial | F208: 16 | G208: =SUMIFS($H$2:$H$1003,$E$2:$E$1003,E208,$D$2:$D$1003,D208) -> 9 | H208: 1
B209: 4 | C209: GS | D209: Mail & Services | E209: =VLOOKUP($C209,$AF:$AG,2,FALSE) -> Commercial | F209: 12 | G209: =SUMIFS($H$2:$H$1003,$E$2:$E$1003,E209,$D$2:$D$1003,D209) -> 9 | H209: 1
B210: 5 | C210: CSI | D210: Mail & Services | E210: =VLOOKUP($C210,$AF:$AG,2,FALSE) -> Commercial | F210: 10 | G210: =SUMIFS($H$2:$H$1003,$E$2:$E$1003,E210,$D$2:$D$1003,D210) -> 9 | H210: 1
B211: 6 | C211: GP B2C | D211: Mail & Services | E211: =VLOOKUP($C211,$AF:$AG,2,FALSE) -> Commercial | F211: 9 | G211: =SUMIFS($H$2:$H$1003,$E$2:$E$1003,E211,$D$2:$D$1003,D211) -> 9 | H211: 1
B212: 7 | C212: CTTE | D212: Mail & Services | E212: =VLOOKUP($C212,$AF:$AG,2,FALSE) -> Commercial | F212: 9 | G212: =SUMIFS($H$2:$H$1003,$E$2:$E$1003,E212,$D$2:$D$1003,D212) -> 9 | H212: 1
B213: 8 | C213: GPG | D213: Mail & Services | E213: =VLOOKUP($C213,$AF:$AG,2,FALSE) -> Commercial | F213: 9 | G213: =SUMIFS($H$2:$H$1003,$E$2:$E$1003,E213,$D$2:$D$1003,D213) -> 9 | H213: 1
B214: 9 | C214: ECM | D214: Mail & Services | E214: =VLOOKUP($C214,$AF:$AG,2,FALSE) -> Commercial | F214: 3 | G214: =SUMIFS($H$2:$H$1003,$E$2:$E$1003,E214,$D$2:$D$1003,D214) -> 9 | H214: 1
B215: 10 | C215: SEO | D215: Mail & Services | E215: =VLOOKUP($C215,$AF:$AG,2,FALSE) -> Operations | F215: 35 | G215: =SUMIFS($H$2:$H$1003,$E$2:$E$1003,E215,$D$2:$D$1003,D215) -> 2
B216: 11 | C216: EDO | D216: Mail & Services | E216: =VLOOKUP($C216,$AF:$AG,2,FALSE) -> Operations | F216: 35 | G216: =SUMIFS($H$2:$H$1003,$E$2:$E$1003,E216,$D$2:$D$1003,D216) -> 2 | H216: 1
B217: 12 | C217: EM | D217: Mail & Services | E217: =VLOOKUP($C217,$AF:$AG,2,FALSE) -> Operations | F217: 30 | G217: =SUMIFS($H$2:$H$1003,$E$2:$E$1003,E217,$D$2:$D$1003,D217) -> 2 | H217: 1
B218: 13 | C218: ACR | D218: Mail & Services | E218: =VLOOKUP($C218,$AF:$AG,2,FALSE) -> Corporate | F218: 6.6666667 | G218: =SUMIFS($H$2:$H$1003,$E$2:$E$1003,E218,$D$2:$D$1003,D218) -> 16 | H218: 1
B219: 14 | C219: CF | D219: Mail & Services | E219: =VLOOKUP($C219,$AF:$AG,2,FALSE) -> Corporate | F219: 6.6666667 | G219: =SUMIFS($H$2:$H$1003,$E$2:$E$1003,E219,$D$2:$D$1003,D219) -> 16 | H219: 1
B220: 15 | C220: RS | D220: Mail & Services | E220: =VLOOKUP($C220,$AF:$AG,2,FALSE) -> Corporate | F220: 6.6666667 | G220: =SUMIFS($H$2:$H$1003,$E$2:$E$1003,E220,$D$2:$D$1003,D220) -> 16 | H220: 1
B221: 16 | C221: AVC | D221: Mail & Services | E221: =VLOOKUP($C221,$AF:$AG,2,FALSE) -> Corporate | F221: 6.6666667 | G221: =SUMIFS($H$2:$H$1003,$E$2:$E$1003,E221,$D$2:$D$1003,D221) -> 16 | H221: 1
B222: 17 | C222: GRH | D222: Mail & Services | E222: =VLOOKUP($C222,$AF:$AG,2,FALSE) -> Corporate | F222: 6.6666667 | G222: =SUMIFS($H$2:$H$1003,$E$2:$E$1003,E222,$D$2:$D$1003,D222) -> 16 | H222: 1
B223: 18 | C223: GT | D223: Mail & Services | E223: =VLOOKUP($C223,$AF:$AG,2,FALSE) -> Corporate | F223: 6.6666667 | G223: =SUMIFS($H$2:$H$1003,$E$2:$E$1003,E223,$D$2:$D$1003,D223) -> 16 | H223: 1
B224: 19 | C224: CL | D224: Mail & Services | E224: =VLOOKUP($C224,$AF:$AG,2,FALSE) -> Corporate | F224: 6.6666667 | G224: =SUMIFS($H$2:$H$1003,$E$2:$E$1003,E224,$D$2:$D$1003,D224) -> 16 | H224: 1
B225: 22 | C225: PC | D225: Mail & Services | E225: =VLOOKUP($C225,$AF:$AG,2,FALSE) -> Corporate | F225: 6.6666667 | G225: =SUMIFS($H$2:$H$1003,$E$2:$E$1003,E225,$D$2:$D$1003,D225) -> 16 | H225: 1
B226: 28 | C226: DPO | D226: Mail & Services | E226: =VLOOKUP($C226,$AF:$AG,2,FALSE) -> Corporate | F226: 6.6666667 | G226: =SUMIFS($H$2:$H$1003,$E$2:$E$1003,E226,$D$2:$D$1003,D226) -> 16 | H226: 1
B227: 29 | C227: CMP | D227: Mail & Services | E227: =VLOOKUP($C227,$AF:$AG,2,FALSE) -> Corporate | F227: 6.6666667 | G227: =SUMIFS($H$2:$H$1003,$E$2:$E$1003,E227,$D$2:$D$1003,D227) -> 16 | H227: 1
... B282: 45 | C282: CTTE | D282: eCommerce-new | E282: =VLOOKUP($C282,$AF:$AG,2,FALSE) -> Commercial | F282: 1e-06 | G282: =SUMIFS($H$2:$H$1003,$E$2:$E$1003,E282,$D$2:$D$1003,D282) -> 12 | H282: 1

Sheet support >>
A1: backup

Sheet ideas-output
A1: Queue | B1: Method | C1: GlobalRank | D1: ID | E1: Name | F1: RequestingArea | G1: RevenueStream | H1: BudgetGroup | I1: MicroPhase | J1: PriorityRA | K1: WSJF_Score | L1: Value | M1: Urgency | N1: Risk | O1: Size | P1: TOP_X | Q1: 122
A2: LATER | B2: SainteLague | C2: 22 | D2: 129487 | E2: [PUDOS] - Lockers Locky - PT​ | F2: CMO | G2: eCommerce | H2: Commercial | I2: In Solution | J2: 0 | K2: 0.09 | L2: 3 | M2: 3 | N2: 3 | O2: 100 | P2: =AND(C2<$Q$1,IF(ISBLANK(C2),0,C2)>0) -> TRUE
A3: LATER | B3: SainteLague | C3: 23 | D3: 125697 | E3: DeMinimis EUA - Solução para retomar os envios de Bens para os EUA para os clientes não contratuais | F3: GP B2B | G3: Mail & Services | H3: Commercial | I3: In Definition | J3: 1 | K3: 3 | L3: 3 | M3: 3 | N3: 3 | O3: 3 | P3: =AND(C3<$Q$1,IF(ISBLANK(C3),0,C3)>0) -> TRUE
A4: LATER | B4: SainteLague | C4: 24 | D4: 130701 | E4: Nuevos desarrollos Normalización de direcciones | F4: COO | G4: eCommerce | H4: Operations | I4: In Solution | J4: 1 | K4: 0.03 | L4: 1 | M4: 1 | N4: 1 | O4: 100 | P4: =AND(C4<$Q$1,IF(ISBLANK(C4),0,C4)>0) -> TRUE
A5: LATER | B5: SainteLague | C5: 25 | D5: 122320 | E5: Implementação de modulo de Planeamento de Transportes em Drivian e Descontinuação do Sigest | F5: SEO | G5: Mail & Services | H5: Operations | I5: High Level Design | J5: 1 | K5: 4.5 | L5: 4 | M5: 2 | N5: 3 | O5: 2 | P5: =AND(C5<$Q$1,IF(ISBLANK(C5),0,C5)>0) -> TRUE
A6: LATER | B6: SainteLague | C6: 26 | D6: 130413 | E6: [Desconexión SGC] - Creación nuevo estado "No realizado" | F6: ATC | G6: eCommerce | H6: Corporate | I6: In Solution | J6: 3 | K6: 0.03 | L6: 1 | M6: 1 | N6: 1 | O6: 100 | P6: =AND(C6<$Q$1,IF(ISBLANK(C6),0,C6)>0) -> TRUE
A7: LATER | B7: SainteLague | C7: 27 | D7: 124871 | E7: Auditoria 2.0 - Criação de Data Lake para implementação de Auditoria Contínua e Auditoria à Distancia - Entrega Modelos Analíticos | F7: ACR | G7: Mail & Services | H7: Corporate | I7: In Definition | J7: 1 | K7: 0.03 | L7: 1 | M7: 1 | N7: 1 | O7: 100 | P7: =AND(C7<$Q$1,IF(ISBLANK(C7),0,C7)>0) -> TRUE
A8: LATER | B8: SainteLague | C8: 28 | D8: 130989 | E8: Desconexión de SGC - Definición del RoadMap | F8: CIO | G8: eCommerce | H8: Technology | I8: Backlog | J8: 1 | K8: 0.03 | L8: 1 | M8: 1 | N8: 1 | O8: 100 | P8: =AND(C8<$Q$1,IF(ISBLANK(C8),0,C8)>0) -> TRUE
A9: LATER | B9: SainteLague | C9: 29 | D9: 132298 | E9: Github Migration - Aplicações Canais Digitais | F9: SI | G9: Mail & Services | H9: Technology | I9: Ready for Approval | J9: 1 | K9: 5 | L9: 4 | M9: 3 | N9: 3 | O9: 2 | P9: =AND(C9<$Q$1,IF(ISBLANK(C9),0,C9)>0) -> TRUE
A10: LATER | B10: SainteLague | C10: 30 | D10: 130577 | E10: [Salesforce Sales] - Multi oportunidad en Cuentas | F10: CCO | G10: eCommerce | H10: Commercial | I10: High Level Design | J10: 3 | K10: 0.03 | L10: 1 | M10: 1 | N10: 1 | O10: 100 | P10: =AND(C10<$Q$1,IF(ISBLANK(C10),0,C10)>0) -> TRUE
A11: LATER | B11: SainteLague | C11: 31 | D11: 126574 | E11: DLP (Data Loss Prevention) - Wave 1 | F11: CISO | G11: Mail & Services | H11: CISO | I11: Backlog | J11: 2 | K11: 0.03 | L11: 1 | M11: 1 | N11: 1 | O11: 100 | P11: =AND(C11<$Q$1,IF(ISBLANK(C11),0,C11)>0) -> TRUE
A12: LATER | B12: SainteLague | C12: 32 | D12: 130894 | E12: Expansión de lectura en contenedores (Propios y de clientes) | F12: COO | G12: eCommerce | H12: Operations | I12: In Definition | J12: 2 | K12: 0.03 | L12: 1 | M12: 1 | N12: 1 | O12: 100 | P12: =AND(C12<$Q$1,IF(ISBLANK(C12),0,C12)>0) -> TRUE
A13: LATER | B13: SainteLague | C13: 33 | D13: 60579 | E13: Nexus | P&S | Implementação da oferta ibérica | F13: GP ECL | G13: Mail & Services | H13: Commercial | I13: High Level Design | J13: 1 | K13: 0.03 | L13: 1 | M13: 1 | N13: 1 | O13: 100 | P13: =AND(C13<$Q$1,IF(ISBLANK(C13),0,C13)>0) -> TRUE
... A881: NEXT | B881: WSJF | C881: 21 | D881: 130343 | E881: [Nuevo Producto]-[Minerva]-Producto 48h a Islas Canarias | F881: CMO | G881: eCommerce | H881: Commercial | I881: Ready for Development | J881: 4 | K881: 0.03 | L881: 1 | M881: 1 | N881: 1 | O881: 100 | P881: =AND(C881<$Q$1,IF(ISBLANK(C881),0,C881)>0) -> TRUE
A882: PRODUCTION | B882: sainte-lague | D882: 132113 | E882: Reduce SalesForce Storage before contract renewal | F882: CIO | G882: eCommerce | H882: Technology | I882: In Production | J882: 999 | L882: 4 | M882: 1 | N882: 3 | O882: 1 | P882: =AND(C882<$Q$1,IF(ISBLANK(C882),0,C882)>0) -> FALSE
A883: PRODUCTION | B883: sainte-lague | D883: 131163 | E883: [Web Pública] - Localizador de puntos - Actualizar texto de enlace | F883: CMO | G883: eCommerce | H883: Commercial | I883: In Production | J883: 999 | L883: 1 | M883: 1 | N883: 1 | O883: 100 | P883: =AND(C883<$Q$1,IF(ISBLANK(C883),0,C883)>0) -> FALSE
A884: PRODUCTION | B884: sainte-lague | D884: 131144 | E884: [Salesforce] Adición del campo Dirección en objeto user | F884: CIO | G884: eCommerce | H884: Technology | I884: In Production | J884: 999 | L884: 2 | M884: 1 | N884: 1 | O884: 1 | P884: =AND(C884<$Q$1,IF(ISBLANK(C884),0,C884)>0) -> FALSE
A885: PRODUCTION | B885: sainte-lague | D885: 131138 | E885: [WebHook] - Shein - LastMile - Modificación de destino HD a Pudo y su comunicación al cliente. | F885: COM | G885: eCommerce | H885: Corporate | I885: In Production | J885: 999 | L885: 1 | M885: 1 | N885: 1 | O885: 100 | P885: =AND(C885<$Q$1,IF(ISBLANK(C885),0,C885)>0) -> FALSE
A886: PRODUCTION | B886: sainte-lague | D886: 131009 | E886: Nuevo universo de envios Senda fin de semana | F886: COO | G886: eCommerce | H886: Operations | I886: In Production | J886: 42 | L886: 1 | M886: 1 | N886: 1 | O886: 100 | P886: =AND(C886<$Q$1,IF(ISBLANK(C886),0,C886)>0) -> FALSE
A887: PRODUCTION | B887: sainte-lague | D887: 130965 | E887: [SGC] - Omitir mensajes de Franquicias | F887: CCO | G887: eCommerce | H887: Commercial | I887: In Production | J887: 42 | L887: 1 | M887: 1 | N887: 1 | O887: 100 | P887: =AND(C887<$Q$1,IF(ISBLANK(C887),0,C887)>0) -> FALSE
A888: PRODUCTION | B888: sainte-lague | D888: 130928 | E888: Kafka - Upgrade MSK en AWS | F888: CIO | G888: eCommerce | H888: Technology | I888: In Production | J888: 7 | L888: 3 | M888: 3 | N888: 1 | O888: 100 | P888: =AND(C888<$Q$1,IF(ISBLANK(C888),0,C888)>0) -> FALSE
A889: PRODUCTION | B889: sainte-lague | D889: 130906 | E889: Tasa Gasoil Portugal | F889: COO | G889: eCommerce | H889: Operations | I889: In Production | J889: 5 | L889: 1 | M889: 1 | N889: 1 | O889: 100 | P889: =AND(C889<$Q$1,IF(ISBLANK(C889),0,C889)>0) -> FALSE
A890: PRODUCTION | B890: sainte-lague | D890: 130776 | E890: Actualizar lista de esquemas de documentación que permiten asociado | F890: COO | G890: eCommerce | H890: Operations | I890: In Production | J890: 0 | L890: 1 | M890: 1 | N890: 1 | O890: 100 | P890: =AND(C890<$Q$1,IF(ISBLANK(C890),0,C890)>0) -> FALSE
A891: PRODUCTION | B891: sainte-lague | D891: 130725 | E891: [DHL Parcel] Envíos PT - PT | F891: IDC | G891: eCommerce | H891: Commercial | I891: In Production | J891: 1 | L891: 1 | M891: 1 | N891: 1 | O891: 100 | P891: =AND(C891<$Q$1,IF(ISBLANK(C891),0,C891)>0) -> FALSE
A892: PRODUCTION | B892: sainte-lague | D892: 130712 | E892: [Notificaciones] - [Mail] - [Modificación] - Actualizar template notificaciones Custom para modificar imágenes | F892: CMO | G892: eCommerce | H892: Commercial | I892: In Production | J892: 0 | L892: 1 | M892: 1 | N892: 1 | O892: 100 | P892: =AND(C892<$Q$1,IF(ISBLANK(C892),0,C892)>0) -> FALSE
A893: PRODUCTION | B893: sainte-lague | D893: 130640 | E893: Portal Proveedores Linehaul - Incluir concepto peaje en la facturación | F893: COO | G893: eCommerce | H893: Operations | I893: In Production | J893: 0 | L893: 1 | M893: 1 | N893: 1 | O893: 100 | P893: =AND(C893<$Q$1,IF(ISBLANK(C893),0,C893)>0) -> FALSE
... A987: PRODUCTION | B987: sainte-lague | D987: 31832 | E987: Solução de Gestão de Despesas de colaborador | F987: CF | G987: Mail & Services | H987: Corporate | I987: In Production | J987: 999 | L987: 1 | M987: 1 | N987: 1 | O987: 100 | P987: =AND(C987<$Q$1,IF(ISBLANK(C987),0,C987)>0) -> FALSE
P988: =AND(C988<$Q$1,IF(ISBLANK(C988),0,C988)>0) -> FALSE
P989: =AND(C989<$Q$1,IF(ISBLANK(C989),0,C989)>0) -> FALSE
P990: =AND(C990<$Q$1,IF(ISBLANK(C990),0,C990)>0) -> FALSE
P991: =AND(C991<$Q$1,IF(ISBLANK(C991),0,C991)>0) -> FALSE
P992: =AND(C992<$Q$1,IF(ISBLANK(C992),0,C992)>0) -> FALSE
P993: =AND(C993<$Q$1,IF(ISBLANK(C993),0,C993)>0) -> FALSE
P994: =AND(C994<$Q$1,IF(ISBLANK(C994),0,C994)>0) -> FALSE
P995: =AND(C995<$Q$1,IF(ISBLANK(C995),0,C995)>0) -> FALSE
P996: =AND(C996<$Q$1,IF(ISBLANK(C996),0,C996)>0) -> FALSE
P997: =AND(C997<$Q$1,IF(ISBLANK(C997),0,C997)>0) -> FALSE
P998: =AND(C998<$Q$1,IF(ISBLANK(C998),0,C998)>0) -> FALSE
P999: =AND(C999<$Q$1,IF(ISBLANK(C999),0,C999)>0) -> FALSE

Sheet pivot
A3: Count of ID | B3: Column Labels
A4: Row Labels | B4: TRUE | C4: FALSE | D4: Grand Total
A5: LATER | B5: 100 | C5: 759 | D5: 859
A6: eCommerce | B6: 50 | C6: 398 | D6: 448
A7: Commercial | B7: 13 | C7: 216 | D7: 229
A8: Corporate | B8: 12 | C8: 94 | D8: 106
A9: Operations | B9: 13 | C9: 29 | D9: 42
A10: Technology | B10: 12 | C10: 59 | D10: 71
A11: Mail & Services | B11: 50 | C11: 361 | D11: 411
A12: CISO | B12: 6 | C12: 2 | D12: 8
A13: Commercial | B13: 11 | C13: 178 | D13: 189
A14: Corporate | B14: 11 | C14: 64 | D14: 75
A15: Operations | B15: 11 | C15: 13 | D15: 24
A16: Technology | B16: 11 | C16: 104 | D16: 115
A17: NEXT | B17: 1 | D17: 1
A18: eCommerce | B18: 1 | D18: 1
A19: Commercial | B19: 1 | D19: 1
A20: NOW | B20: 20 | D20: 20
A21: eCommerce | B21: 15 | D21: 15
A22: Commercial | B22: 5 | D22: 5
A23: Corporate | B23: 3 | D23: 3
A24: Operations | B24: 6 | D24: 6
A25: Technology | B25: 1 | D25: 1
A26: Mail & Services | B26: 5 | D26: 5
A27: CISO | B27: 1 | D27: 1
A28: Corporate | B28: 2 | D28: 2
A29: Technology | B29: 2 | D29: 2
A30: PRODUCTION | C30: 106 | D30: 106
A31: (blank)
A32: Grand Total | B32: 121 | C32: 865 | D32: 986

Sheet backup >> 

Sheet weights (base2026.02)
B1: EXPORT CSV | C1: WEIGHTS_RA | I1: Peso BG por RS | N1: EXPORT CSV | O1: WEIGHTS_RS | Y1: REF DATA | AB1: REF DATA
B2: RequestingArea | C2: RevenueStream | D2: BudgetGroup | E2: Weight | F2: Weight-RS+BG | G2: Weight-Base | I2: RevenueStream | J2: BudgetGroup | K2: Weight | L2: Check | N2: RevenueStream | O2: Weight | P2: Check | R2: {=_xlfn.UNIQUE(D2:D1000)} -> BudgetGroup | S2: Check | U2: {=_xlfn.UNIQUE(B2:B1000)} -> RequestingArea | V2: Check | W2: hasBG? | Y2: RequestingArea | Z2: BudgetGroup | AB2: MicroPhase bmap | AC2: MicroPhase Macro | AD2: MicroPhase Demand
B3: CISO | C3: Business Solutions | D3: =VLOOKUP($B3,$Y:$Z,2,FALSE) -> CISO | E3: =G3*SUMIFS($K:$K,$I:$I,C3,$J:$J,D3)/F3 -> 5 | F3: =SUMIFS($G$2:$G$1000,$D$2:$D$1000,D3,$C$2:$C$1000,C3) -> 5 | G3: 5 | I3: eCommerce | J3: CISO | K3: 5 | L3: =SUMIF($I:$I,I3,$K:$K) -> 100 | N3: eCommerce | O3: 26 | P3: =SUM(O3:O18) -> 100 | R3: CISO | S3: =SUMIF($D:$D,R3,$E:$E) -> 30 | U3: CISO | V3: =SUMIF($B:$B,U3,$E:$E) -> 30 | W3: =VLOOKUP(U3,$Y:$Z,2,FALSE) -> CISO | Y3: CISO | Z3: CISO | AB3: IDEA > Backlog | AC3: {=_xlfn.TEXTSPLIT(AB3,">",)} -> IDEA | AD3: Backlog
B4: CSI | C4: Business Solutions | D4: =VLOOKUP($B4,$Y:$Z,2,FALSE) -> Commercial | E4: =G4*SUMIFS($K:$K,$I:$I,C4,$J:$J,D4)/F4 -> 4 | F4: =SUMIFS($G$2:$G$1000,$D$2:$D$1000,D4,$C$2:$C$1000,C4) -> 100 | G4: 10 | I4: eCommerce | J4: Commercial | K4: 25 | L4: =SUMIF($I:$I,I4,$K:$K) -> 100 | N4: Mail | O4: 22 | R4: Commercial | S4: =SUMIF($D:$D,R4,$E:$E) -> 185 | U4: CSI | V4: =SUMIF($B:$B,U4,$E:$E) -> 16.652406 | W4: =VLOOKUP(U4,$Y:$Z,2,FALSE) -> Commercial | Y4: CCO | Z4: Commercial | AB4: IDEA > Pitch | AC4: {=_xlfn.TEXTSPLIT(AB4,">",)} -> IDEA | AD4: Pitch
B5: CTTE | C5: Business Solutions | D5: =VLOOKUP($B5,$Y:$Z,2,FALSE) -> Commercial | E5: =G5*SUMIFS($K:$K,$I:$I,C5,$J:$J,D5)/F5 -> 4 | F5: =SUMIFS($G$2:$G$1000,$D$2:$D$1000,D5,$C$2:$C$1000,C5) -> 100 | G5: 10 | I5: eCommerce | J5: Corporate | K5: 20 | L5: =SUMIF($I:$I,I5,$K:$K) -> 100 | N5: Business Solutions | O5: 16 | R5: Corporate | S5: =SUMIF($D:$D,R5,$E:$E) -> 135 | U5: CTTE | V5: =SUMIF($B:$B,U5,$E:$E) -> 16.652406 | W5: =VLOOKUP(U5,$Y:$Z,2,FALSE) -> Commercial | Y5: CMO | Z5: Commercial | AB5: IDEA > In Definition | AC5: {=_xlfn.TEXTSPLIT(AB5,">",)} -> IDEA | AD5: In Definition
B6: DNI | C6: Business Solutions | D6: =VLOOKUP($B6,$Y:$Z,2,FALSE) -> Commercial | E6: =G6*SUMIFS($K:$K,$I:$I,C6,$J:$J,D6)/F6 -> 4 | F6: =SUMIFS($G$2:$G$1000,$D$2:$D$1000,D6,$C$2:$C$1000,C6) -> 100 | G6: 10 | I6: eCommerce | J6: Operations | K6: 25 | L6: =SUMIF($I:$I,I6,$K:$K) -> 100 | N6: Retail & Financial Services | O6: 14 | R6: Operations | S6: =SUMIF($D:$D,R6,$E:$E) -> 105 | U6: DNI | V6: =SUMIF($B:$B,U6,$E:$E) -> 16.652406 | W6: =VLOOKUP(U6,$Y:$Z,2,FALSE) -> Commercial | Y6: CSI | Z6: Commercial | AB6: SOLUTION > In Approval | AC6: {=_xlfn.TEXTSPLIT(AB6,">",)} -> SOLUTION | AD6: In Approval
B7: ECM | C7: Business Solutions | D7: =VLOOKUP($B7,$Y:$Z,2,FALSE) -> Commercial | E7: =G7*SUMIFS($K:$K,$I:$I,C7,$J:$J,D7)/F7 -> 4 | F7: =SUMIFS($G$2:$G$1000,$D$2:$D$1000,D7,$C$2:$C$1000,C7) -> 100 | G7: 10 | I7: eCommerce | J7: Technology | K7: 15 | L7: =SUMIF($I:$I,I7,$K:$K) -> 100 | N7: Payments | O7: 12 | R7: Technology | S7: =SUMIF($D:$D,R7,$E:$E) -> 110 | U7: ECM | V7: =SUMIF($B:$B,U7,$E:$E) -> 16.652406 | W7: =VLOOKUP(U7,$Y:$Z,2,FALSE) -> Commercial | Y7: CTTE | Z7: Commercial | AB7: SOLUTION > Ready for Approval | AC7: {=_xlfn.TEXTSPLIT(AB7,">",)} -> SOLUTION | AD7: Ready for Approval
B8: GP B2B | C8: Business Solutions | D8: =VLOOKUP($B8,$Y:$Z,2,FALSE) -> Commercial | E8: =G8*SUMIFS($K:$K,$I:$I,C8,$J:$J,D8)/F8 -> 8 | F8: =SUMIFS($G$2:$G$1000,$D$2:$D$1000,D8,$C$2:$C$1000,C8) -> 100 | G8: 20 | I8: eCommerce | J8: Data & AI | K8: 10 | L8: =SUMIF($I:$I,I8,$K:$K) -> 100 | N8: Fulfilment | O8: 10 | R8: Data & AI | S8: =SUMIF($D:$D,R8,$E:$E) -> 35 | U8: GP B2B | V8: =SUMIF($B:$B,U8,$E:$E) -> 23.379679 | W8: =VLOOKUP(U8,$Y:$Z,2,FALSE) -> Commercial | Y8: DNI | Z8: Commercial | AB8: IDEA > Ready for Solution | AC8: {=_xlfn.TEXTSPLIT(AB8,">",)} -> IDEA | AD8: Ready for Solution
B9: GP B2C | C9: Business Solutions | D9: =VLOOKUP($B9,$Y:$Z,2,FALSE) -> Commercial | E9: =G9*SUMIFS($K:$K,$I:$I,C9,$J:$J,D9)/F9 -> 4 | F9: =SUMIFS($G$2:$G$1000,$D$2:$D$1000,D9,$C$2:$C$1000,C9) -> 100 | G9: 10 | I9: Mail | J9: CISO | K9: 5 | L9: =SUMIF($I:$I,I9,$K:$K) -> 100 | N9: Banco CTT | O9: 0 | R9: 0 | S9: =SUMIF($D:$D,R9,$E:$E) -> 0 | U9: GP B2C | V9: =SUMIF($B:$B,U9,$E:$E) -> 19.379679 | W9: =VLOOKUP(U9,$Y:$Z,2,FALSE) -> Commercial | Y9: ECM | Z9: Commercial | AB9: SOLUTION > High Level Design | AC9: {=_xlfn.TEXTSPLIT(AB9,">",)} -> SOLUTION | AD9: High Level Design
B10: GP ECL | C10: Business Solutions | D10: =VLOOKUP($B10,$Y:$Z,2,FALSE) -> Commercial | E10: =G10*SUMIFS($K:$K,$I:$I,C10,$J:$J,D10)/F10 -> 4 | F10: =SUMIFS($G$2:$G$1000,$D$2:$D$1000,D10,$C$2:$C$1000,C10) -> 100 | G10: 10 | I10: Mail | J10: Commercial | K10: 30 | L10: =SUMIF($I:$I,I10,$K:$K) -> 100 | S10: =SUMIF($D:$D,R10,$E:$E) -> 0 | U10: GP ECL | V10: =SUMIF($B:$B,U10,$E:$E) -> 21.122995 | W10: =VLOOKUP(U10,$Y:$Z,2,FALSE) -> Commercial | Y10: GP B2B | Z10: Commercial | AB10: SOLUTION > Ready for Development | AC10: {=_xlfn.TEXTSPLIT(AB10,">",)} -> SOLUTION | AD10: Ready for Development
B11: GPG | C11: Business Solutions | D11: =VLOOKUP($B11,$Y:$Z,2,FALSE) -> Commercial | E11: =G11*SUMIFS($K:$K,$I:$I,C11,$J:$J,D11)/F11 -> 4 | F11: =SUMIFS($G$2:$G$1000,$D$2:$D$1000,D11,$C$2:$C$1000,C11) -> 100 | G11: 10 | I11: Mail | J11: Corporate | K11: 20 | L11: =SUMIF($I:$I,I11,$K:$K) -> 100 | S11: =SUMIF($D:$D,R11,$E:$E) -> 0 | U11: GPG | V11: =SUMIF($B:$B,U11,$E:$E) -> 19.379679 | W11: =VLOOKUP(U11,$Y:$Z,2,FALSE) -> Commercial | Y11: GP B2C | Z11: Commercial | AB11: SOLUTION > In Definition | AC11: {=_xlfn.TEXTSPLIT(AB11,">",)} -> SOLUTION | AD11: In Definition
B12: GS | C12: Business Solutions | D12: =VLOOKUP($B12,$Y:$Z,2,FALSE) -> Commercial | E12: =G12*SUMIFS($K:$K,$I:$I,C12,$J:$J,D12)/F12 -> 4 | F12: =SUMIFS($G$2:$G$1000,$D$2:$D$1000,D12,$C$2:$C$1000,C12) -> 100 | G12: 10 | I12: Mail | J12: Operations | K12: 20 | L12: =SUMIF($I:$I,I12,$K:$K) -> 100 | S12: =SUMIF($D:$D,R12,$E:$E) -> 0 | U12: GS | V12: =SUMIF($B:$B,U12,$E:$E) -> 26.304813 | W12: =VLOOKUP(U12,$Y:$Z,2,FALSE) -> Commercial | Y12: GP ECL | Z12: Commercial
B13: ACR | C13: Business Solutions | D13: =VLOOKUP($B13,$Y:$Z,2,FALSE) -> Corporate | E13: =G13*SUMIFS($K:$K,$I:$I,C13,$J:$J,D13)/F13 -> 1.4285714 | F13: =SUMIFS($G$2:$G$1000,$D$2:$D$1000,D13,$C$2:$C$1000,C13) -> 140 | G13: 10 | I13: Mail | J13: Technology | K13: 20 | L13: =SUMIF($I:$I,I13,$K:$K) -> 100 | S13: =SUMIF($D:$D,R13,$E:$E) -> 0 | U13: ACR | V13: =SUMIF($B:$B,U13,$E:$E) -> 9.1233766 | W13: =VLOOKUP(U13,$Y:$Z,2,FALSE) -> Corporate | Y13: GPG | Z13: Commercial
B14: AVC | C14: Business Solutions | D14: =VLOOKUP($B14,$Y:$Z,2,FALSE) -> Corporate | E14: =G14*SUMIFS($K:$K,$I:$I,C14,$J:$J,D14)/F14 -> 1.4285714 | F14: =SUMIFS($G$2:$G$1000,$D$2:$D$1000,D14,$C$2:$C$1000,C14) -> 140 | G14: 10 | I14: Mail | J14: Data & AI | K14: 5 | L14: =SUMIF($I:$I,I14,$K:$K) -> 100 | S14: =SUMIF($D:$D,R14,$E:$E) -> 0 | U14: AVC | V14: =SUMIF($B:$B,U14,$E:$E) -> 9.1233766 | W14: =VLOOKUP(U14,$Y:$Z,2,FALSE) -> Corporate | Y14: GS | Z14: Commercial
B15: CF | C15: Business Solutions | D15: =VLOOKUP($B15,$Y:$Z,2,FALSE) -> Corporate | E15: =G15*SUMIFS($K:$K,$I:$I,C15,$J:$J,D15)/F15 -> 2.8571429 | F15: =SUMIFS($G$2:$G$1000,$D$2:$D$1000,D15,$C$2:$C$1000,C15) -> 140 | G15: 20 | I15: Business Solutions | J15: CISO | K15: 5 | L15: =SUMIF($I:$I,I15,$K:$K) -> 100 | U15: CF | V15: =SUMIF($B:$B,U15,$E:$E) -> 18.246753 | W15: =VLOOKUP(U15,$Y:$Z,2,FALSE) -> Corporate | Y15: IDC | Z15: Commercial
B16: CL | C16: Business Solutions | D16: =VLOOKUP($B16,$Y:$Z,2,FALSE) -> Corporate | E16: =G16*SUMIFS($K:$K,$I:$I,C16,$J:$J,D16)/F16 -> 1.4285714 | F16: =SUMIFS($G$2:$G$1000,$D$2:$D$1000,D16,$C$2:$C$1000,C16) -> 140 | G16: 10 | I16: Business Solutions | J16: Commercial | K16: 40 | L16: =SUMIF($I:$I,I16,$K:$K) -> 100 | U16: CL | V16: =SUMIF($B:$B,U16,$E:$E) -> 9.1233766 | W16: =VLOOKUP(U16,$Y:$Z,2,FALSE) -> Corporate | Y16: ACR | Z16: Corporate
B17: CMP | C17: Business Solutions | D17: =VLOOKUP($B17,$Y:$Z,2,FALSE) -> Corporate | E17: =G17*SUMIFS($K:$K,$I:$I,C17,$J:$J,D17)/F17 -> 1.4285714 | F17: =SUMIFS($G$2:$G$1000,$D$2:$D$1000,D17,$C$2:$C$1000,C17) -> 140 | G17: 10 | I17: Business Solutions | J17: Corporate | K17: 20 | L17: =SUMIF($I:$I,I17,$K:$K) -> 100 | U17: CMP | V17: =SUMIF($B:$B,U17,$E:$E) -> 9.1233766 | W17: =VLOOKUP(U17,$Y:$Z,2,FALSE) -> Corporate | Y17: ATC | Z17: Corporate
B18: DPO | C18: Business Solutions | D18: =VLOOKUP($B18,$Y:$Z,2,FALSE) -> Corporate | E18: =G18*SUMIFS($K:$K,$I:$I,C18,$J:$J,D18)/F18 -> 1.4285714 | F18: =SUMIFS($G$2:$G$1000,$D$2:$D$1000,D18,$C$2:$C$1000,C18) -> 140 | G18: 10 | I18: Business Solutions | J18: Operations | K18: 10 | L18: =SUMIF($I:$I,I18,$K:$K) -> 100 | U18: DPO | V18: =SUMIF($B:$B,U18,$E:$E) -> 9.1233766 | W18: =VLOOKUP(U18,$Y:$Z,2,FALSE) -> Corporate | Y18: AVC | Z18: Corporate
B19: FL | C19: Business Solutions | D19: =VLOOKUP($B19,$Y:$Z,2,FALSE) -> Corporate | E19: =G19*SUMIFS($K:$K,$I:$I,C19,$J:$J,D19)/F19 -> 1.4285714 | F19: =SUMIFS($G$2:$G$1000,$D$2:$D$1000,D19,$C$2:$C$1000,C19) -> 140 | G19: 10 | I19: Business Solutions | J19: Technology | K19: 20 | L19: =SUMIF($I:$I,I19,$K:$K) -> 100 | U19: FL | V19: =SUMIF($B:$B,U19,$E:$E) -> 9.1233766 | W19: =VLOOKUP(U19,$Y:$Z,2,FALSE) -> Corporate | Y19: CF | Z19: Corporate
B20: GRH | C20: Business Solutions | D20: =VLOOKUP($B20,$Y:$Z,2,FALSE) -> Corporate | E20: =G20*SUMIFS($K:$K,$I:$I,C20,$J:$J,D20)/F20 -> 1.4285714 | F20: =SUMIFS($G$2:$G$1000,$D$2:$D$1000,D20,$C$2:$C$1000,C20) -> 140 | G20: 10 | I20: Business Solutions | J20: Data & AI | K20: 5 | L20: =SUMIF($I:$I,I20,$K:$K) -> 100 | U20: GRH | V20: =SUMIF($B:$B,U20,$E:$E) -> 9.1233766 | W20: =VLOOKUP(U20,$Y:$Z,2,FALSE) -> Corporate | Y20: CFO | Z20: Corporate
B21: GT | C21: Business Solutions | D21: =VLOOKUP($B21,$Y:$Z,2,FALSE) -> Corporate | E21: =G21*SUMIFS($K:$K,$I:$I,C21,$J:$J,D21)/F21 -> 1.4285714 | F21: =SUMIFS($G$2:$G$1000,$D$2:$D$1000,D21,$C$2:$C$1000,C21) -> 140 | G21: 10 | I21: Retail & Financial Services | J21: CISO | K21: 5 | L21: =SUMIF($I:$I,I21,$K:$K) -> 100 | U21: GT | V21: =SUMIF($B:$B,U21,$E:$E) -> 9.1233766 | W21: =VLOOKUP(U21,$Y:$Z,2,FALSE) -> Corporate | Y21: CHR | Z21: Corporate
B22: PC | C22: Business Solutions | D22: =VLOOKUP($B22,$Y:$Z,2,FALSE) -> Corporate | E22: =G22*SUMIFS($K:$K,$I:$I,C22,$J:$J,D22)/F22 -> 1.4285714 | F22: =SUMIFS($G$2:$G$1000,$D$2:$D$1000,D22,$C$2:$C$1000,C22) -> 140 | G22: 10 | I22: Retail & Financial Services | J22: Commercial | K22: 30 | L22: =SUMIF($I:$I,I22,$K:$K) -> 100 | U22: PC | V22: =SUMIF($B:$B,U22,$E:$E) -> 10.032468 | W22: =VLOOKUP(U22,$Y:$Z,2,FALSE) -> Corporate | Y22: CL | Z22: Corporate
B23: RS | C23: Business Solutions | D23: =VLOOKUP($B23,$Y:$Z,2,FALSE) -> Corporate | E23: =G23*SUMIFS($K:$K,$I:$I,C23,$J:$J,D23)/F23 -> 1.4285714 | F23: =SUMIFS($G$2:$G$1000,$D$2:$D$1000,D23,$C$2:$C$1000,C23) -> 140 | G23: 10 | I23: Retail & Financial Services | J23: Corporate | K23: 30 | L23: =SUMIF($I:$I,I23,$K:$K) -> 100 | U23: RS | V23: =SUMIF($B:$B,U23,$E:$E) -> 9.1233766 | W23: =VLOOKUP(U23,$Y:$Z,2,FALSE) -> Corporate | Y23: CMP | Z23: Corporate
B24: ST | C24: Business Solutions | D24: =VLOOKUP($B24,$Y:$Z,2,FALSE) -> Corporate | E24: =G24*SUMIFS($K:$K,$I:$I,C24,$J:$J,D24)/F24 -> 1.4285714 | F24: =SUMIFS($G$2:$G$1000,$D$2:$D$1000,D24,$C$2:$C$1000,C24) -> 140 | G24: 10 | I24: Retail & Financial Services | J24: Operations | K24: 10 | L24: =SUMIF($I:$I,I24,$K:$K) -> 100 | U24: ST | V24: =SUMIF($B:$B,U24,$E:$E) -> 9.1233766 | W24: =VLOOKUP(U24,$Y:$Z,2,FALSE) -> Corporate | Y24: COM | Z24: Corporate
B25: TF | C25: Business Solutions | D25: =VLOOKUP($B25,$Y:$Z,2,FALSE) -> Corporate | E25: =G25*SUMIFS($K:$K,$I:$I,C25,$J:$J,D25)/F25 -> 1.4285714 | F25: =SUMIFS($G$2:$G$1000,$D$2:$D$1000,D25,$C$2:$C$1000,C25) -> 140 | G25: 10 | I25: Retail & Financial Services | J25: Technology | K25: 20 | L25: =SUMIF($I:$I,I25,$K:$K) -> 100 | U25: TF | V25: =SUMIF($B:$B,U25,$E:$E) -> 9.1233766 | W25: =VLOOKUP(U25,$Y:$Z,2,FALSE) -> Corporate | Y25: DPO | Z25: Corporate
B26: EDO | C26: Business Solutions | D26: =VLOOKUP($B26,$Y:$Z,2,FALSE) -> Operations | E26: =G26*SUMIFS($K:$K,$I:$I,C26,$J:$J,D26)/F26 -> 3.3333333 | F26: =SUMIFS($G$2:$G$1000,$D$2:$D$1000,D26,$C$2:$C$1000,C26) -> 30 | G26: 10 | I26: Retail & Financial Services | J26: Data & AI | K26: 5 | L26: =SUMIF($I:$I,I26,$K:$K) -> 100 | U26: EDO | V26: =SUMIF($B:$B,U26,$E:$E) -> 36.333333 | W26: =VLOOKUP(U26,$Y:$Z,2,FALSE) -> Operations | Y26: FL | Z26: Corporate
... B38: CTTE | C38: eCommerce | D38: =VLOOKUP($B38,$Y:$Z,2,FALSE) -> Commercial | E38: =G38*SUMIFS($K:$K,$I:$I,C38,$J:$J,D38)/F38 -> 1.4705882 | F38: =SUMIFS($G$2:$G$1000,$D$2:$D$1000,D38,$C$2:$C$1000,C38) -> 170 | G38: 10 | I38: Fulfilment | J38: Data & AI | K38: 5 | L38: =SUMIF($I:$I,I38,$K:$K) -> 100 | U38: CFO | V38: =SUMIF($B:$B,U38,$E:$E) -> 1.8181818 | W38: =VLOOKUP(U38,$Y:$Z,2,FALSE) -> Corporate | Y38: SEO | Z38: Operations
B39: DNI | C39: eCommerce | D39: =VLOOKUP($B39,$Y:$Z,2,FALSE) -> Commercial | E39: =G39*SUMIFS($K:$K,$I:$I,C39,$J:$J,D39)/F39 -> 1.4705882 | F39: =SUMIFS($G$2:$G$1000,$D$2:$D$1000,D39,$C$2:$C$1000,C39) -> 170 | G39: 10 | U39: CHR | V39: =SUMIF($B:$B,U39,$E:$E) -> 0.90909091 | W39: =VLOOKUP(U39,$Y:$Z,2,FALSE) -> Corporate | Y39: BCTT | Z39: Technology
B40: ECM | C40: eCommerce | D40: =VLOOKUP($B40,$Y:$Z,2,FALSE) -> Commercial | E40: =G40*SUMIFS($K:$K,$I:$I,C40,$J:$J,D40)/F40 -> 1.4705882 | F40: =SUMIFS($G$2:$G$1000,$D$2:$D$1000,D40,$C$2:$C$1000,C40) -> 170 | G40: 10 | U40: COM | V40: =SUMIF($B:$B,U40,$E:$E) -> 0.90909091 | W40: =VLOOKUP(U40,$Y:$Z,2,FALSE) -> Corporate | Y40: CIO | Z40: Technology
B41: GP B2B | C41: eCommerce | D41: =VLOOKUP($B41,$Y:$Z,2,FALSE) -> Commercial | E41: =G41*SUMIFS($K:$K,$I:$I,C41,$J:$J,D41)/F41 -> 1.4705882 | F41: =SUMIFS($G$2:$G$1000,$D$2:$D$1000,D41,$C$2:$C$1000,C41) -> 170 | G41: 10 | U41: PRO | V41: =SUMIF($B:$B,U41,$E:$E) -> 0.90909091 | W41: =VLOOKUP(U41,$Y:$Z,2,FALSE) -> Corporate | Y41: SI | Z41: Technology
B42: GP B2C | C42: eCommerce | D42: =VLOOKUP($B42,$Y:$Z,2,FALSE) -> Commercial | E42: =G42*SUMIFS($K:$K,$I:$I,C42,$J:$J,D42)/F42 -> 1.4705882 | F42: =SUMIFS($G$2:$G$1000,$D$2:$D$1000,D42,$C$2:$C$1000,C42) -> 170 | G42: 10 | U42: COO | V42: =SUMIF($B:$B,U42,$E:$E) -> 8.3333333 | W42: =VLOOKUP(U42,$Y:$Z,2,FALSE) -> Operations | Y42: SI-CRP | Z42: Technology
B43: GP ECL | C43: eCommerce | D43: =VLOOKUP($B43,$Y:$Z,2,FALSE) -> Commercial | E43: =G43*SUMIFS($K:$K,$I:$I,C43,$J:$J,D43)/F43 -> 2.9411765 | F43: =SUMIFS($G$2:$G$1000,$D$2:$D$1000,D43,$C$2:$C$1000,C43) -> 170 | G43: 20 | U43: CIO | V43: =SUMIF($B:$B,U43,$E:$E) -> 3.75 | W43: =VLOOKUP(U43,$Y:$Z,2,FALSE) -> Technology | Y43: SI-OPS | Z43: Technology
B44: GPG | C44: eCommerce | D44: =VLOOKUP($B44,$Y:$Z,2,FALSE) -> Commercial | E44: =G44*SUMIFS($K:$K,$I:$I,C44,$J:$J,D44)/F44 -> 1.4705882 | F44: =SUMIFS($G$2:$G$1000,$D$2:$D$1000,D44,$C$2:$C$1000,C44) -> 170 | G44: 10 | U44: IAD | V44: =SUMIF($B:$B,U44,$E:$E) -> 35 | W44: =VLOOKUP(U44,$Y:$Z,2,FALSE) -> Data & AI | Y44: SI-PRD | Z44: Technology
B45: GS | C45: eCommerce | D45: =VLOOKUP($B45,$Y:$Z,2,FALSE) -> Commercial | E45: =G45*SUMIFS($K:$K,$I:$I,C45,$J:$J,D45)/F45 -> 2.9411765 | F45: =SUMIFS($G$2:$G$1000,$D$2:$D$1000,D45,$C$2:$C$1000,C45) -> 170 | G45: 20 | U45: 0 | Y45: IAD | Z45: Data & AI
B46: IDC | C46: eCommerce | D46: =VLOOKUP($B46,$Y:$Z,2,FALSE) -> Commercial | E46: =G46*SUMIFS($K:$K,$I:$I,C46,$J:$J,D46)/F46 -> 2.9411765 | F46: =SUMIFS($G$2:$G$1000,$D$2:$D$1000,D46,$C$2:$C$1000,C46) -> 170 | G46: 20
B47: ACR | C47: eCommerce | D47: =VLOOKUP($B47,$Y:$Z,2,FALSE) -> Corporate | E47: =G47*SUMIFS($K:$K,$I:$I,C47,$J:$J,D47)/F47 -> 0.90909091 | F47: =SUMIFS($G$2:$G$1000,$D$2:$D$1000,D47,$C$2:$C$1000,C47) -> 220 | G47: 10
B48: ATC | C48: eCommerce | D48: =VLOOKUP($B48,$Y:$Z,2,FALSE) -> Corporate | E48: =G48*SUMIFS($K:$K,$I:$I,C48,$J:$J,D48)/F48 -> 1.8181818 | F48: =SUMIFS($G$2:$G$1000,$D$2:$D$1000,D48,$C$2:$C$1000,C48) -> 220 | G48: 20
B49: AVC | C49: eCommerce | D49: =VLOOKUP($B49,$Y:$Z,2,FALSE) -> Corporate | E49: =G49*SUMIFS($K:$K,$I:$I,C49,$J:$J,D49)/F49 -> 0.90909091 | F49: =SUMIFS($G$2:$G$1000,$D$2:$D$1000,D49,$C$2:$C$1000,C49) -> 220 | G49: 10
B50: CF | C50: eCommerce | D50: =VLOOKUP($B50,$Y:$Z,2,FALSE) -> Corporate | E50: =G50*SUMIFS($K:$K,$I:$I,C50,$J:$J,D50)/F50 -> 1.8181818 | F50: =SUMIFS($G$2:$G$1000,$D$2:$D$1000,D50,$C$2:$C$1000,C50) -> 220 | G50: 20
B51: CFO | C51: eCommerce | D51: =VLOOKUP($B51,$Y:$Z,2,FALSE) -> Corporate | E51: =G51*SUMIFS($K:$K,$I:$I,C51,$J:$J,D51)/F51 -> 1.8181818 | F51: =SUMIFS($G$2:$G$1000,$D$2:$D$1000,D51,$C$2:$C$1000,C51) -> 220 | G51: 20
B52: CHR | C52: eCommerce | D52: =VLOOKUP($B52,$Y:$Z,2,FALSE) -> Corporate | E52: =G52*SUMIFS($K:$K,$I:$I,C52,$J:$J,D52)/F52 -> 0.90909091 | F52: =SUMIFS($G$2:$G$1000,$D$2:$D$1000,D52,$C$2:$C$1000,C52) -> 220 | G52: 10
B53: CL | C53: eCommerce | D53: =VLOOKUP($B53,$Y:$Z,2,FALSE) -> Corporate | E53: =G53*SUMIFS($K:$K,$I:$I,C53,$J:$J,D53)/F53 -> 0.90909091 | F53: =SUMIFS($G$2:$G$1000,$D$2:$D$1000,D53,$C$2:$C$1000,C53) -> 220 | G53: 10
B54: CMP | C54: eCommerce | D54: =VLOOKUP($B54,$Y:$Z,2,FALSE) -> Corporate | E54: =G54*SUMIFS($K:$K,$I:$I,C54,$J:$J,D54)/F54 -> 0.90909091 | F54: =SUMIFS($G$2:$G$1000,$D$2:$D$1000,D54,$C$2:$C$1000,C54) -> 220 | G54: 10
B55: COM | C55: eCommerce | D55: =VLOOKUP($B55,$Y:$Z,2,FALSE) -> Corporate | E55: =G55*SUMIFS($K:$K,$I:$I,C55,$J:$J,D55)/F55 -> 0.90909091 | F55: =SUMIFS($G$2:$G$1000,$D$2:$D$1000,D55,$C$2:$C$1000,C55) -> 220 | G55: 10
B56: DPO | C56: eCommerce | D56: =VLOOKUP($B56,$Y:$Z,2,FALSE) -> Corporate | E56: =G56*SUMIFS($K:$K,$I:$I,C56,$J:$J,D56)/F56 -> 0.90909091 | F56: =SUMIFS($G$2:$G$1000,$D$2:$D$1000,D56,$C$2:$C$1000,C56) -> 220 | G56: 10
B57: FL | C57: eCommerce | D57: =VLOOKUP($B57,$Y:$Z,2,FALSE) -> Corporate | E57: =G57*SUMIFS($K:$K,$I:$I,C57,$J:$J,D57)/F57 -> 0.90909091 | F57: =SUMIFS($G$2:$G$1000,$D$2:$D$1000,D57,$C$2:$C$1000,C57) -> 220 | G57: 10
... B198: SI-PRD | C198: Retail & Financial Services | D198: =VLOOKUP($B198,$Y:$Z,2,FALSE) -> Technology | E198: =G198*SUMIFS($K:$K,$I:$I,C198,$J:$J,D198)/F198 -> 3.3333333 | F198: =SUMIFS($G$2:$G$1000,$D$2:$D$1000,D198,$C$2:$C$1000,C198) -> 60 | G198: 10
B199: IAD | C199: Business Solutions | D199: Data & AI | E199: =G199*SUMIFS($K:$K,$I:$I,C199,$J:$J,D199)/F199 -> 5 | F199: =SUMIFS($G$2:$G$1000,$D$2:$D$1000,D199,$C$2:$C$1000,C199) -> 20 | G199: 20
B200: IAD | C200: eCommerce | D200: Data & AI | E200: =G200*SUMIFS($K:$K,$I:$I,C200,$J:$J,D200)/F200 -> 10 | F200: =SUMIFS($G$2:$G$1000,$D$2:$D$1000,D200,$C$2:$C$1000,C200) -> 20 | G200: 20
B201: IAD | C201: Fulfilment | D201: Data & AI | E201: =G201*SUMIFS($K:$K,$I:$I,C201,$J:$J,D201)/F201 -> 5 | F201: =SUMIFS($G$2:$G$1000,$D$2:$D$1000,D201,$C$2:$C$1000,C201) -> 20 | G201: 20
B202: IAD | C202: Mail | D202: Data & AI | E202: =G202*SUMIFS($K:$K,$I:$I,C202,$J:$J,D202)/F202 -> 5 | F202: =SUMIFS($G$2:$G$1000,$D$2:$D$1000,D202,$C$2:$C$1000,C202) -> 20 | G202: 20
B203: IAD | C203: Payments | D203: Data & AI | E203: =G203*SUMIFS($K:$K,$I:$I,C203,$J:$J,D203)/F203 -> 5 | F203: =SUMIFS($G$2:$G$1000,$D$2:$D$1000,D203,$C$2:$C$1000,C203) -> 20 | G203: 20
B204: IAD | C204: Retail & Financial Services | D204: Data & AI | E204: =G204*SUMIFS($K:$K,$I:$I,C204,$J:$J,D204)/F204 -> 5 | F204: =SUMIFS($G$2:$G$1000,$D$2:$D$1000,D204,$C$2:$C$1000,C204) -> 20 | G204: 20

Sheet TOM25-26 DEMAND WEIGHTS
A1: DEMAND 2025
A2: PORTUGAL | W2: ESPAÑA
A3: PRODUCTS | B3: 0.38 | E3: OPERATIONS | F3: 0.19 | I3: CORPORATE | J3: 0.19 | M3: TECHNOLOGY | N3: 0.19 | Q3: DAT | R3: 0.05 | W3: operations | X3: commercial | Y3: corporate | Z3: commercial | AA3: commercial | AB3: corporate | AC3: technology | AD3: corporate | AE3: corporate | AF3: corporate
A4: GP ECL | B4: 0.16 | E4: EDO | F4: 0.35 | I4: ACR | J4: 0.066666667 | K4: =J4*100 -> 6.6666667 | M4: SI | N4: 0.3 | W4: COO | X4: CMO | Y4: ATC | Z4: CCO | AA4: IDC | AB4: CFO | AC4: CIO | AD4: PRO | AE4: CHR | AF4: COM | AH4: COO | AI4: =AJ4*100 -> 20 | AJ4: 0.2
A5: GP B2B | B5: 0.16 | E5: SEO | F5: 0.35 | I5: CF | J5: 0.066666667 | K5: =J5*100 -> 6.6666667 | M5: CISO | N5: 0.2 | W5: 0.2 | X5: 0.12 | Y5: 0.12 | Z5: 0.08 | AA5: 0.08 | AB5: 0.12 | AC5: 0.15 | AD5: 0.07 | AE5: 0.03 | AF5: 0.03 | AH5: CMO | AI5: =AJ5*100 -> 12 | AJ5: 0.12
A6: DNI | B6: 0.16 | E6: EM | F6: 0.3 | I6: RS | J6: 0.066666667 | K6: =J6*100 -> 6.6666667 | M6: BCTT | N6: 0.2 | AH6: ATC | AI6: =AJ6*100 -> 12 | AJ6: 0.12
A7: GS | B7: 0.12 | I7: AVC | J7: 0.066666667 | K7: =J7*100 -> 6.6666667 | M7: SI-PRD | N7: 0.1 | AH7: CCO | AI7: =AJ7*100 -> 8 | AJ7: 0.08
A8: CSI | B8: 0.1 | I8: GRH | J8: 0.066666667 | K8: =J8*100 -> 6.6666667 | M8: SI-OPS | N8: 0.1 | AH8: IDC | AI8: =AJ8*100 -> 8 | AJ8: 0.08
A9: GP B2C | B9: 0.09 | I9: GT | J9: 0.066666667 | K9: =J9*100 -> 6.6666667 | M9: SI-CRP | N9: 0.1 | AH9: CFO | AI9: =AJ9*100 -> 12 | AJ9: 0.12
A10: CTTE | B10: 0.09 | I10: CL | J10: 0.066666667 | K10: =J10*100 -> 6.6666667 | AH10: CIO | AI10: =AJ10*100 -> 15 | AJ10: 0.15
A11: GPG | B11: 0.09 | I11: ED | J11: 0.066666667 | K11: =J11*100 -> 6.6666667 | AH11: PRO | AI11: =AJ11*100 -> 7 | AJ11: 0.07
A12: ECM | B12: 0.03 | I12: CMP | J12: 0.066666667 | K12: =J12*100 -> 6.6666667 | AH12: CHR | AI12: =AJ12*100 -> 3 | AJ12: 0.03
I13: ST | J13: 0.066666667 | K13: =J13*100 -> 6.6666667 | AH13: COM | AI13: =AJ13*100 -> 3 | AJ13: 0.03
I14: GFC | J14: 0.066666667 | K14: =J14*100 -> 6.6666667
I15: TF | J15: 0.066666667 | K15: =J15*100 -> 6.6666667
I16: DPO | J16: 0.066666667 | K16: =J16*100 -> 6.6666667
I17: SSJ | J17: 0.066666667 | K17: =J17*100 -> 6.6666667
I18: FL | J18: 0.066666667 | K18: =J18*100 -> 6.6666667
A20: DEMAND 2026
A21: eCOMMERCE | B21: =VLOOKUP(A21,tom_demand_setup!$S:$T,2,FALSE) -> 40 | C21: =(B23+F23+J23+N23+R23+V23)=100 -> TRUE
A22: check | B22: =B23=SUM(B24:B32) -> TRUE | E22: check | F22: =F23=SUM(F24:F32) -> TRUE | I22: check | J22: =J23=SUM(J24:J32) -> TRUE | M22: check | N22: =N23=SUM(N24:N32) -> TRUE | Q22: check | R22: =R23=SUM(R24:R32) -> TRUE | U22: check | V22: =V23=SUM(V24:V32) -> TRUE
A23: Commercial | B23: 25 | C23: =B23*($B$21/100) -> 10 | E23: Operations | F23: 25 | G23: =F23*($B$21/100) -> 10 | I23: Corporate | J23: 20 | K23: =J23*($B$21/100) -> 8 | M23: Technology | N23: 20 | O23: =N23*($B$21/100) -> 8 | Q23: Data & AI | R23: 5 | S23: =R23*($B$21/100) -> 2 | U23: CISO | V23: 5 | W23: =V23*($B$21/100) -> 2 | X23: 25
A24: CMO | B24: 4 | C24: =B24*($B$21/100) -> 1.6 | E24: COO | F24: 8 | G24: =F24*($B$21/100) -> 3.2 | I24: ATC | J24: 8 | K24: =J24*($B$21/100) -> 3.2 | M24: CIO | N24: 20 | O24: =N24*($B$21/100) -> 8 | Q24: DAI | R24: 5 | S24: =R24*($B$21/100) -> 2 | U24: CISO | V24: 5 | W24: =V24*($B$21/100) -> 2 | X24: 25
A25: CCO | B25: 4 | C25: =B25*($B$21/100) -> 1.6 | E25: EDO | F25: 8 | G25: =F25*($B$21/100) -> 3.2 | I25: CFO | J25: 8 | K25: =J25*($B$21/100) -> 3.2 | O25: =N25*($B$21/100) -> 0 | S25: =R25*($B$21/100) -> 0 | W25: =V25*($B$21/100) -> 0 | X25: 20
A26: IDC | B26: 4 | C26: =B26*($B$21/100) -> 1.6 | E26: SEO | F26: 8 | G26: =F26*($B$21/100) -> 3.2 | I26: PRO | J26: 2 | K26: =J26*($B$21/100) -> 0.8 | O26: =N26*($B$21/100) -> 0 | S26: =R26*($B$21/100) -> 0 | W26: =V26*($B$21/100) -> 0 | X26: 20
A27: GP ECL | B27: 5 | C27: =B27*($B$21/100) -> 2 | E27: EM | F27: 1 | G27: =F27*($B$21/100) -> 0.4 | I27: CHR | J27: 1 | K27: =J27*($B$21/100) -> 0.4 | O27: =N27*($B$21/100) -> 0 | S27: =R27*($B$21/100) -> 0 | W27: =V27*($B$21/100) -> 0 | X27: 5
A28: DNI | B28: 2 | C28: =B28*($B$21/100) -> 0.8 | G28: =F28*($B$21/100) -> 0 | I28: COM | J28: 1 | K28: =J28*($B$21/100) -> 0.4 | O28: =N28*($B$21/100) -> 0 | S28: =R28*($B$21/100) -> 0 | W28: =V28*($B$21/100) -> 0 | X28: 5
A29: GS | B29: 2 | C29: =B29*($B$21/100) -> 0.8 | G29: =F29*($B$21/100) -> 0 | K29: =J29*($B$21/100) -> 0 | O29: =N29*($B$21/100) -> 0 | S29: =R29*($B$21/100) -> 0 | W29: =V29*($B$21/100) -> 0
A30: CSI | B30: 2 | C30: =B30*($B$21/100) -> 0.8 | G30: =F30*($B$21/100) -> 0 | K30: =J30*($B$21/100) -> 0 | O30: =N30*($B$21/100) -> 0 | S30: =R30*($B$21/100) -> 0 | W30: =V30*($B$21/100) -> 0
A31: GP B2C | B31: 2 | C31: =B31*($B$21/100) -> 0.8 | G31: =F31*($B$21/100) -> 0 | K31: =J31*($B$21/100) -> 0 | O31: =N31*($B$21/100) -> 0 | S31: =R31*($B$21/100) -> 0 | W31: =V31*($B$21/100) -> 0
A34: MAIL | B34: =VLOOKUP(A34,tom_demand_setup!$S:$T,2,FALSE) -> 22 | C34: =(B36+F36+J36+N36+R36+V36)=100 -> TRUE
A35: check | B35: =B36=SUM(B37:B52) -> TRUE | E35: check | F35: =F36=SUM(F37:F52) -> TRUE | I35: check | J35: =J36=SUM(J37:J52) -> TRUE | M35: check | N35: =N36=SUM(N37:N52) -> TRUE | Q35: check | R35: =R36=SUM(R37:R52) -> TRUE | U35: check | V35: =V36=SUM(V37:V52) -> TRUE
A36: Commercial | B36: 25 | C36: =B36*($B$34/100) -> 5.5 | E36: Operations | F36: 25 | G36: =F36*($B$34/100) -> 5.5 | I36: Corporate | J36: 20 | K36: =J36*($B$34/100) -> 4.4 | M36: Technology | N36: 20 | O36: =N36*($B$34/100) -> 4.4 | Q36: Data & AI | R36: 5 | S36: =R36*($B$34/100) -> 1.1 | U36: CISO | V36: 5 | W36: =V36*($B$34/100) -> 1.1 | X36: 25
A37: GP B2B | B37: 5 | C37: =B37*($B$34/100) -> 1.1 | E37: EDO | F37: 10 | G37: =F37*($B$34/100) -> 2.2 | I37: ACR | J37: 2 | K37: =J37*($B$34/100) -> 0.44 | M37: SI | N37: 10 | O37: =N37*($B$34/100) -> 2.2 | Q37: DAI | R37: 5 | S37: =R37*($B$34/100) -> 1.1 | U37: CISO | V37: 5 | W37: =V37*($B$34/100) -> 1.1 | X37: 25
A38: DNI | B38: 5 | C38: =B38*($B$34/100) -> 1.1 | E38: SEO | F38: 10 | G38: =F38*($B$34/100) -> 2.2 | I38: CF | J38: 2 | K38: =J38*($B$34/100) -> 0.44 | M38: BCTT | N38: 10 | O38: =N38*($B$34/100) -> 2.2 | S38: =R38*($B$34/100) -> 0 | W38: =V38*($B$34/100) -> 0
A39: GS | B39: 5 | C39: =B39*($B$34/100) -> 1.1 | E39: EM | F39: 5 | G39: =F39*($B$34/100) -> 1.1 | I39: RS | J39: 1 | K39: =J39*($B$34/100) -> 0.22 | O39: =N39*($B$34/100) -> 0 | S39: =R39*($B$34/100) -> 0 | W39: =V39*($B$34/100) -> 0
A40: CSI | B40: 5 | C40: =B40*($B$34/100) -> 1.1 | G40: =F40*($B$34/100) -> 0 | I40: AVC | J40: 2 | K40: =J40*($B$34/100) -> 0.44 | O40: =N40*($B$34/100) -> 0 | S40: =R40*($B$34/100) -> 0 | W40: =V40*($B$34/100) -> 0
A41: GP B2C | B41: 5 | C41: =B41*($B$34/100) -> 1.1 | G41: =F41*($B$34/100) -> 0 | I41: GRH | J41: 2 | K41: =J41*($B$34/100) -> 0.44 | O41: =N41*($B$34/100) -> 0 | S41: =R41*($B$34/100) -> 0 | W41: =V41*($B$34/100) -> 0
C42: =B42*($B$34/100) -> 0 | G42: =F42*($B$34/100) -> 0 | I42: GT | J42: 2 | K42: =J42*($B$34/100) -> 0.44 | O42: =N42*($B$34/100) -> 0 | S42: =R42*($B$34/100) -> 0 | W42: =V42*($B$34/100) -> 0
C43: =B43*($B$34/100) -> 0 | G43: =F43*($B$34/100) -> 0 | I43: CL | J43: 1 | K43: =J43*($B$34/100) -> 0.22 | O43: =N43*($B$34/100) -> 0 | S43: =R43*($B$34/100) -> 0 | W43: =V43*($B$34/100) -> 0
C44: =B44*($B$34/100) -> 0 | G44: =F44*($B$34/100) -> 0 | I44: ED | J44: 1 | K44: =J44*($B$34/100) -> 0.22 | O44: =N44*($B$34/100) -> 0 | S44: =R44*($B$34/100) -> 0 | W44: =V44*($B$34/100) -> 0
C45: =B45*($B$34/100) -> 0 | G45: =F45*($B$34/100) -> 0 | I45: CMP | J45: 1 | K45: =J45*($B$34/100) -> 0.22 | O45: =N45*($B$34/100) -> 0 | S45: =R45*($B$34/100) -> 0 | W45: =V45*($B$34/100) -> 0
C46: =B46*($B$34/100) -> 0 | G46: =F46*($B$34/100) -> 0 | I46: ST | J46: 1 | K46: =J46*($B$34/100) -> 0.22 | O46: =N46*($B$34/100) -> 0 | S46: =R46*($B$34/100) -> 0 | W46: =V46*($B$34/100) -> 0
C47: =B47*($B$34/100) -> 0 | G47: =F47*($B$34/100) -> 0 | I47: GFC | J47: 1 | K47: =J47*($B$34/100) -> 0.22 | O47: =N47*($B$34/100) -> 0 | S47: =R47*($B$34/100) -> 0 | W47: =V47*($B$34/100) -> 0
C48: =B48*($B$34/100) -> 0 | G48: =F48*($B$34/100) -> 0 | I48: TF | J48: 1 | K48: =J48*($B$34/100) -> 0.22 | O48: =N48*($B$34/100) -> 0 | S48: =R48*($B$34/100) -> 0 | W48: =V48*($B$34/100) -> 0
C49: =B49*($B$34/100) -> 0 | G49: =F49*($B$34/100) -> 0 | I49: DPO | J49: 1 | K49: =J49*($B$34/100) -> 0.22 | O49: =N49*($B$34/100) -> 0 | S49: =R49*($B$34/100) -> 0 | W49: =V49*($B$34/100) -> 0
C50: =B50*($B$34/100) -> 0 | G50: =F50*($B$34/100) -> 0 | I50: SSJ | J50: 1 | K50: =J50*($B$34/100) -> 0.22 | O50: =N50*($B$34/100) -> 0 | S50: =R50*($B$34/100) -> 0 | W50: =V50*($B$34/100) -> 0
C51: =B51*($B$34/100) -> 0 | G51: =F51*($B$34/100) -> 0 | I51: PC | J51: 1 | K51: =J51*($B$34/100) -> 0.22 | O51: =N51*($B$34/100) -> 0 | S51: =R51*($B$34/100) -> 0 | W51: =V51*($B$34/100) -> 0
A54: BUSINESS SOLUTIONS | B54: =VLOOKUP(A54,tom_demand_setup!$S:$T,2,FALSE) -> 16 | C54: =(B56+F56+J56+N56+R56+V56)=100 -> FALSE
A55: check | B55: =B56=SUM(B57:B61) -> TRUE | E55: check | F55: =F56=SUM(F57:F61) -> FALSE | I55: check | J55: =J56=SUM(J57:J61) -> FALSE | M55: check | N55: =N56=SUM(N57:N61) -> TRUE | Q55: check | R55: =R56=SUM(R57:R61) -> TRUE | U55: check | V55: =V56=SUM(V57:V61) -> TRUE
A56: Commercial | B56: 50 | C56: =B56*($B$72/100) -> 4 | E56: Operations | F56: 20 | G56: =F56*($B$72/100) -> 1.6 | I56: Corporate | J56: 20 | K56: =J56*($B$72/100) -> 1.6 | M56: Technology | N56: 20 | O56: =N56*($B$72/100) -> 1.6 | Q56: Data & AI | R56: 5 | S56: =R56*($B$72/100) -> 0.4 | U56: CISO | V56: 5 | W56: =V56*($B$72/100) -> 0.4
A57: GP B2B | B57: 50 | C57: =B57*($B$72/100) -> 4 | G57: =F57*($B$72/100) -> 0 | J57: 0 | K57: =J57*($B$72/100) -> 0 | M57: SI | N57: 20 | O57: =N57*($B$72/100) -> 1.6 | Q57: DAI | R57: 5 | S57: =R57*($B$72/100) -> 0.4 | U57: CISO | V57: 5 | W57: =V57*($B$72/100) -> 0.4
C58: =B58*($B$54/100) -> 0 | G58: =F58*($B$54/100) -> 0 | K58: =J58*($B$54/100) -> 0 | O58: =N58*($B$54/100) -> 0 | S58: =R58*($B$54/100) -> 0 | W58: =V58*($B$54/100) -> 0
C59: =B59*($B$54/100) -> 0 | G59: =F59*($B$54/100) -> 0 | K59: =J59*($B$54/100) -> 0 | O59: =N59*($B$54/100) -> 0 | S59: =R59*($B$54/100) -> 0 | W59: =V59*($B$54/100) -> 0
C60: =B60*($B$54/100) -> 0 | G60: =F60*($B$54/100) -> 0 | K60: =J60*($B$54/100) -> 0 | O60: =N60*($B$54/100) -> 0 | S60: =R60*($B$54/100) -> 0 | W60: =V60*($B$54/100) -> 0
A63: FULFILMENT | B63: =VLOOKUP(A63,tom_demand_setup!$S:$T,2,FALSE) -> 4 | C63: =(B65+F65+J65+N65+R65+V65)=100 -> TRUE
A64: check | B64: =B65=SUM(B66:B70) -> TRUE | E64: check | F64: =F65=SUM(F66:F70) -> TRUE | I64: check | J64: =J65=SUM(J66:J70) -> TRUE | M64: check | N64: =N65=SUM(N66:N70) -> TRUE | Q64: check | R64: =R65=SUM(R66:R70) -> TRUE | U64: check | V64: =V65=SUM(V66:V70) -> TRUE
A65: Commercial | B65: 45 | C65: =B65*($B$63/100) -> 1.8 | E65: Operations | F65: 25 | G65: =F65*($B$63/100) -> 1 | I65: Corporate | J65: 0 | K65: =J65*($B$63/100) -> 0 | M65: Technology | N65: 20 | O65: =N65*($B$63/100) -> 0.8 | Q65: Data & AI | R65: 5 | S65: =R65*($B$63/100) -> 0.2 | U65: CISO | V65: 5 | W65: =V65*($B$63/100) -> 0.2
A66: GP ECL | B66: 45 | C66: =B66*($B$63/100) -> 1.8 | E66: EDO | F66: 13 | G66: =F66*($B$63/100) -> 0.52 | K66: =J66*($B$63/100) -> 0 | M66: SI | N66: 20 | O66: =N66*($B$63/100) -> 0.8 | Q66: DAI | R66: 5 | S66: =R66*($B$63/100) -> 0.2 | U66: CISO | V66: 5 | W66: =V66*($B$63/100) -> 0.2
C67: =B67*($B$63/100) -> 0 | E67: SEO | F67: 12 | G67: =F67*($B$63/100) -> 0.48 | K67: =J67*($B$63/100) -> 0 | O67: =N67*($B$63/100) -> 0 | S67: =R67*($B$63/100) -> 0 | W67: =V67*($B$63/100) -> 0
C68: =B68*($B$63/100) -> 0 | G68: =F68*($B$63/100) -> 0 | K68: =J68*($B$63/100) -> 0 | O68: =N68*($B$63/100) -> 0 | S68: =R68*($B$63/100) -> 0 | W68: =V68*($B$63/100) -> 0
C69: =B69*($B$63/100) -> 0 | G69: =F69*($B$63/100) -> 0 | K69: =J69*($B$63/100) -> 0 | O69: =N69*($B$63/100) -> 0 | S69: =R69*($B$63/100) -> 0 | W69: =V69*($B$63/100) -> 0
A72: PAYMENTS | B72: =VLOOKUP(A72,tom_demand_setup!$S:$T,2,FALSE) -> 8 | C72: =(B74+F74+J74+N74+R74+V74)=100 -> TRUE
A73: check | B73: =B74=SUM(B75:B79) -> TRUE | E73: check | F73: =F74=SUM(F75:F79) -> TRUE | I73: check | J73: =J74=SUM(J75:J79) -> TRUE | M73: check | N73: =N74=SUM(N75:N79) -> TRUE | Q73: check | R73: =R74=SUM(R75:R79) -> TRUE | U73: check | V73: =V74=SUM(V75:V79) -> TRUE
A74: Commercial | B74: 80 | C74: =B74*($B$72/100) -> 6.4 | E74: Operations | F74: 0 | G74: =F74*($B$72/100) -> 0 | I74: Corporate | J74: 0 | K74: =J74*($B$72/100) -> 0 | M74: Technology | N74: 10 | O74: =N74*($B$72/100) -> 0.8 | Q74: Data & AI | R74: 5 | S74: =R74*($B$72/100) -> 0.4 | U74: CISO | V74: 5 | W74: =V74*($B$72/100) -> 0.4
A75: GPG | B75: 80 | C75: =B75*($B$72/100) -> 6.4 | G75: =F75*($B$72/100) -> 0 | J75: 0 | K75: =J75*($B$72/100) -> 0 | M75: SI | N75: 10 | O75: =N75*($B$72/100) -> 0.8 | Q75: DAI | R75: 5 | S75: =R75*($B$72/100) -> 0.4 | U75: CISO | V75: 5 | W75: =V75*($B$72/100) -> 0.4
C76: =B76*($B$72/100) -> 0 | G76: =F76*($B$72/100) -> 0 | K76: =J76*($B$72/100) -> 0 | O76: =N76*($B$72/100) -> 0 | S76: =R76*($B$72/100) -> 0 | W76: =V76*($B$72/100) -> 0
C77: =B77*($B$72/100) -> 0 | G77: =F77*($B$72/100) -> 0 | K77: =J77*($B$72/100) -> 0 | O77: =N77*($B$72/100) -> 0 | S77: =R77*($B$72/100) -> 0 | W77: =V77*($B$72/100) -> 0
C78: =B78*($B$72/100) -> 0 | G78: =F78*($B$72/100) -> 0 | K78: =J78*($B$72/100) -> 0 | O78: =N78*($B$72/100) -> 0 | S78: =R78*($B$72/100) -> 0 | W78: =V78*($B$72/100) -> 0
A81: RETAIL & FINANCIAL SERVICES | B81: =VLOOKUP(A81,tom_demand_setup!$S:$T,2,FALSE) -> 10 | C81: =(B83+F83+J83+N83+R83+V83)=100 -> TRUE
A82: check | B82: =B83=SUM(B84:B88) -> TRUE | E82: check | F82: =F83=SUM(F84:F88) -> TRUE | I82: check | J82: =J83=SUM(J84:J88) -> TRUE | M82: check | N82: =N83=SUM(N84:N88) -> TRUE | Q82: check | R82: =R83=SUM(R84:R88) -> TRUE | U82: check | V82: =V83=SUM(V84:V88) -> TRUE
A83: Commercial | B83: 50 | C83: =B83*($B$81/100) -> 5 | E83: Operations | F83: 0 | G83: =F83*($B$81/100) -> 0 | I83: Corporate | J83: 20 | K83: =J83*($B$81/100) -> 2 | M83: Technology | N83: 20 | O83: =N83*($B$81/100) -> 2 | Q83: Data & AI | R83: 5 | S83: =R83*($B$81/100) -> 0.5 | U83: CISO | V83: 5 | W83: =V83*($B$81/100) -> 0.5
A84: GP B2C | B84: 25 | C84: =B84*($B$81/100) -> 2.5 | G84: =F84*($B$81/100) -> 0 | I84: CF | J84: 20 | K84: =J84*($B$81/100) -> 2 | M84: SI | N84: 20 | O84: =N84*($B$81/100) -> 2 | Q84: DAI | R84: 5 | S84: =R84*($B$81/100) -> 0.5 | U84: CISO | V84: 5 | W84: =V84*($B$81/100) -> 0.5
C85: =B85*($B$81/100) -> 0 | G85: =F85*($B$81/100) -> 0 | K85: =J85*($B$81/100) -> 0 | O85: =N85*($B$81/100) -> 0 | S85: =R85*($B$81/100) -> 0 | W85: =V85*($B$81/100) -> 0
A86: GS | B86: 25 | C86: =B86*($B$81/100) -> 2.5 | G86: =F86*($B$81/100) -> 0 | K86: =J86*($B$81/100) -> 0 | O86: =N86*($B$81/100) -> 0 | S86: =R86*($B$81/100) -> 0 | W86: =V86*($B$81/100) -> 0
C87: =B87*($B$81/100) -> 0 | G87: =F87*($B$81/100) -> 0 | K87: =J87*($B$81/100) -> 0 | O87: =N87*($B$81/100) -> 0 | S87: =R87*($B$81/100) -> 0 | W87: =V87*($B$81/100) -> 0

Sheet tom_demand_setup (old)
B1: order | C1: EXPORT CSV | D1: WEIGHTS_RA | J1: Peso BG por RS | Q1: EXPORT CSV | R1: WEIGHTS_RS | AB1: REF DATA | AE1: REF DATA
B2: # | C2: RequestingArea | D2: RevenueStream | E2: BudgetGroup | F2: Weight | G2: Weight-RS+BG | H2: Weight-Base | J2: RevenueStream | K2: BudgetGroup | L2: Count | M2: Check | N2: Weight | O2: Check | Q2: RevenueStream | R2: Weight | S2: Check | U2: {=_xlfn.UNIQUE(E2:E1000)} -> BudgetGroup | V2: Check | X2: {=_xlfn.UNIQUE(C2:C1000)} -> RequestingArea | Y2: Check | Z2: hasBG? | AB2: RequestingArea | AC2: BudgetGroup | AE2: MicroPhase bmap | AF2: MicroPhase Macro | AG2: MicroPhase Demand
B3: 1 | C3: GP B2B | D3: Business Solutions | E3: =VLOOKUP($C3,$AB:$AC,2,FALSE) -> Commercial | F3: =H3*SUMIFS($L:$L,$J:$J,D3,$K:$K,E3)/G3 -> 1 | G3: =SUMIFS($H$2:$H$1000,$E$2:$E$1000,E3,$D$2:$D$1000,D3) -> 9 | H3: 1 | J3: eCommerce | K3: CISO | L3: =COUNTIFS(E:E,K3,D:D,J3) -> 1 | M3: =SUMIF($J:$J,J3,$L:$L) -> 42 | N3: =SUMIFS(F:F,E:E,K3,D:D,J3) -> 1 | O3: =SUMIF($J:$J,L3,$L:$L) -> 0 | Q3: eCommerce | R3: 40 | S3: =SUM(R3:R18) -> 100 | U3: Commercial | V3: =SUMIF($E:$E,U3,$F:$F) -> 56 | X3: GP B2B | Y3: =SUMIF($C:$C,X3,$F:$F) -> 6 | Z3: =VLOOKUP(X3,$AB:$AC,2,FALSE) -> Commercial | AB3: CISO | AC3: CISO | AE3: IDEA > Backlog | AF3: {=_xlfn.TEXTSPLIT(AE3,">",)} -> IDEA | AG3: Backlog
B4: 2 | C4: SEO | D4: Business Solutions | E4: =VLOOKUP($C4,$AB:$AC,2,FALSE) -> Operations | F4: =H4*SUMIFS($L:$L,$J:$J,D4,$K:$K,E4)/G4 -> 1 | G4: =SUMIFS($H$2:$H$1000,$E$2:$E$1000,E4,$D$2:$D$1000,D4) -> 3 | H4: 1 | J4: eCommerce | K4: Commercial | L4: =COUNTIFS(E:E,K4,D:D,J4) -> 12 | M4: =SUMIF($J:$J,J4,$L:$L) -> 42 | N4: =SUMIFS(F:F,E:E,K4,D:D,J4) -> 12 | O4: =SUMIF($J:$J,L4,$L:$L) -> 0 | Q4: Mail | R4: 22 | U4: Operations | V4: =SUMIF($E:$E,U4,$F:$F) -> 22 | X4: SEO | Y4: =SUMIF($C:$C,X4,$F:$F) -> 7 | Z4: =VLOOKUP(X4,$AB:$AC,2,FALSE) -> Operations | AB4: CCO | AC4: Commercial | AE4: IDEA > Pitch | AF4: {=_xlfn.TEXTSPLIT(AE4,">",)} -> IDEA | AG4: Pitch
B5: 3 | C5: CF | D5: Business Solutions | E5: =VLOOKUP($C5,$AB:$AC,2,FALSE) -> Corporate | F5: =H5*SUMIFS($L:$L,$J:$J,D5,$K:$K,E5)/G5 -> 1 | G5: =SUMIFS($H$2:$H$1000,$E$2:$E$1000,E5,$D$2:$D$1000,D5) -> 13 | H5: 1 | J5: eCommerce | K5: Corporate | L5: =COUNTIFS(E:E,K5,D:D,J5) -> 18 | M5: =SUMIF($J:$J,J5,$L:$L) -> 42 | N5: =SUMIFS(F:F,E:E,K5,D:D,J5) -> 18 | O5: =SUMIF($J:$J,L5,$L:$L) -> 0 | Q5: Business Solutions | R5: 16 | U5: Corporate | V5: =SUMIF($E:$E,U5,$F:$F) -> 78 | X5: CF | Y5: =SUMIF($C:$C,X5,$F:$F) -> 6 | Z5: =VLOOKUP(X5,$AB:$AC,2,FALSE) -> Corporate | AB5: CMO | AC5: Commercial | AE5: IDEA > In Definition | AF5: {=_xlfn.TEXTSPLIT(AE5,">",)} -> IDEA | AG5: In Definition
B6: 4 | C6: SI | D6: Business Solutions | E6: =VLOOKUP($C6,$AB:$AC,2,FALSE) -> Technology | F6: =H6*SUMIFS($L:$L,$J:$J,D6,$K:$K,E6)/G6 -> 1 | G6: =SUMIFS($H$2:$H$1000,$E$2:$E$1000,E6,$D$2:$D$1000,D6) -> 5 | H6: 1 | J6: eCommerce | K6: Operations | L6: =COUNTIFS(E:E,K6,D:D,J6) -> 4 | M6: =SUMIF($J:$J,J6,$L:$L) -> 42 | N6: =SUMIFS(F:F,E:E,K6,D:D,J6) -> 7 | O6: =SUMIF($J:$J,L6,$L:$L) -> 0 | Q6: Retail & Financial Services | R6: 10 | U6: Technology | V6: =SUMIF($E:$E,U6,$F:$F) -> 31 | X6: SI | Y6: =SUMIF($C:$C,X6,$F:$F) -> 6 | Z6: =VLOOKUP(X6,$AB:$AC,2,FALSE) -> Technology | AB6: CSI | AC6: Commercial | AE6: SOLUTION > In Approval | AF6: {=_xlfn.TEXTSPLIT(AE6,">",)} -> SOLUTION | AG6: In Approval
B7: 5 | C7: CISO | D7: Business Solutions | E7: =VLOOKUP($C7,$AB:$AC,2,FALSE) -> CISO | F7: =H7*SUMIFS($L:$L,$J:$J,D7,$K:$K,E7)/G7 -> 1 | G7: =SUMIFS($H$2:$H$1000,$E$2:$E$1000,E7,$D$2:$D$1000,D7) -> 1 | H7: 1 | J7: eCommerce | K7: Technology | L7: =COUNTIFS(E:E,K7,D:D,J7) -> 6 | M7: =SUMIF($J:$J,J7,$L:$L) -> 42 | N7: =SUMIFS(F:F,E:E,K7,D:D,J7) -> 6 | O7: =SUMIF($J:$J,L7,$L:$L) -> 0 | Q7: Payments | R7: 8 | U7: CISO | V7: =SUMIF($E:$E,U7,$F:$F) -> 6 | X7: CISO | Y7: =SUMIF($C:$C,X7,$F:$F) -> 6 | Z7: =VLOOKUP(X7,$AB:$AC,2,FALSE) -> CISO | AB7: CTTE | AC7: Commercial | AE7: SOLUTION > Ready for Approval | AF7: {=_xlfn.TEXTSPLIT(AE7,">",)} -> SOLUTION | AG7: Ready for Approval
B8: 6 | C8: IAD | D8: Business Solutions | E8: =VLOOKUP($C8,$AB:$AC,2,FALSE) -> Data & AI | F8: =H8*SUMIFS($L:$L,$J:$J,D8,$K:$K,E8)/G8 -> 1 | G8: =SUMIFS($H$2:$H$1000,$E$2:$E$1000,E8,$D$2:$D$1000,D8) -> 1 | H8: 1 | J8: eCommerce | K8: Data & AI | L8: =COUNTIFS(E:E,K8,D:D,J8) -> 1 | M8: =SUMIF($J:$J,J8,$L:$L) -> 42 | N8: =SUMIFS(F:F,E:E,K8,D:D,J8) -> 1 | O8: =SUMIF($J:$J,L8,$L:$L) -> 0 | Q8: Fulfilment | R8: 4 | U8: Data & AI | V8: =SUMIF($E:$E,U8,$F:$F) -> 12 | X8: IAD | Y8: =SUMIF($C:$C,X8,$F:$F) -> 6 | Z8: =VLOOKUP(X8,$AB:$AC,2,FALSE) -> Data & AI | AB8: DNI | AC8: Commercial | AE8: IDEA > Ready for Solution | AF8: {=_xlfn.TEXTSPLIT(AE8,">",)} -> IDEA | AG8: Ready for Solution
B9: 7 | C9: GS | D9: Business Solutions | E9: =VLOOKUP($C9,$AB:$AC,2,FALSE) -> Commercial | F9: =H9*SUMIFS($L:$L,$J:$J,D9,$K:$K,E9)/G9 -> 1 | G9: =SUMIFS($H$2:$H$1000,$E$2:$E$1000,E9,$D$2:$D$1000,D9) -> 9 | H9: 1 | J9: Mail | K9: CISO | L9: =COUNTIFS(E:E,K9,D:D,J9) -> 1 | M9: =SUMIF($J:$J,J9,$L:$L) -> 32 | N9: =SUMIFS(F:F,E:E,K9,D:D,J9) -> 1 | O9: =SUMIF($J:$J,L9,$L:$L) -> 0 | Q9: Banco CTT | R9: 0 | U9: 0 | V9: =SUMIF($E:$E,U9,$F:$F) -> 0 | X9: GS | Y9: =SUMIF($C:$C,X9,$F:$F) -> 6 | Z9: =VLOOKUP(X9,$AB:$AC,2,FALSE) -> Commercial | AB9: ECM | AC9: Commercial | AE9: SOLUTION > High Level Design | AF9: {=_xlfn.TEXTSPLIT(AE9,">",)} -> SOLUTION | AG9: High Level Design
B10: 8 | C10: ACR | D10: Business Solutions | E10: =VLOOKUP($C10,$AB:$AC,2,FALSE) -> Corporate | F10: =H10*SUMIFS($L:$L,$J:$J,D10,$K:$K,E10)/G10 -> 1 | G10: =SUMIFS($H$2:$H$1000,$E$2:$E$1000,E10,$D$2:$D$1000,D10) -> 13 | H10: 1 | J10: Mail | K10: Commercial | L10: =COUNTIFS(E:E,K10,D:D,J10) -> 9 | M10: =SUMIF($J:$J,J10,$L:$L) -> 32 | N10: =SUMIFS(F:F,E:E,K10,D:D,J10) -> 9 | O10: =SUMIF($J:$J,L10,$L:$L) -> 0 | V10: =SUMIF($E:$E,U10,$F:$F) -> 0 | X10: ACR | Y10: =SUMIF($C:$C,X10,$F:$F) -> 6 | Z10: =VLOOKUP(X10,$AB:$AC,2,FALSE) -> Corporate | AB10: GP B2B | AC10: Commercial | AE10: SOLUTION > Ready for Development | AF10: {=_xlfn.TEXTSPLIT(AE10,">",)} -> SOLUTION | AG10: Ready for Development
B11: 9 | C11: EDO | D11: Business Solutions | E11: =VLOOKUP($C11,$AB:$AC,2,FALSE) -> Operations | F11: =H11*SUMIFS($L:$L,$J:$J,D11,$K:$K,E11)/G11 -> 1 | G11: =SUMIFS($H$2:$H$1000,$E$2:$E$1000,E11,$D$2:$D$1000,D11) -> 3 | H11: 1 | J11: Mail | K11: Corporate | L11: =COUNTIFS(E:E,K11,D:D,J11) -> 13 | M11: =SUMIF($J:$J,J11,$L:$L) -> 32 | N11: =SUMIFS(F:F,E:E,K11,D:D,J11) -> 13 | O11: =SUMIF($J:$J,L11,$L:$L) -> 0 | V11: =SUMIF($E:$E,U11,$F:$F) -> 0 | X11: EDO | Y11: =SUMIF($C:$C,X11,$F:$F) -> 7 | Z11: =VLOOKUP(X11,$AB:$AC,2,FALSE) -> Operations | AB11: GP B2C | AC11: Commercial | AE11: SOLUTION > In Definition | AF11: {=_xlfn.TEXTSPLIT(AE11,">",)} -> SOLUTION | AG11: In Definition
B12: 10 | C12: SI-OPS | D12: Business Solutions | E12: =VLOOKUP($C12,$AB:$AC,2,FALSE) -> Technology | F12: =H12*SUMIFS($L:$L,$J:$J,D12,$K:$K,E12)/G12 -> 1 | G12: =SUMIFS($H$2:$H$1000,$E$2:$E$1000,E12,$D$2:$D$1000,D12) -> 5 | H12: 1 | J12: Mail | K12: Operations | L12: =COUNTIFS(E:E,K12,D:D,J12) -> 3 | M12: =SUMIF($J:$J,J12,$L:$L) -> 32 | N12: =SUMIFS(F:F,E:E,K12,D:D,J12) -> 3 | O12: =SUMIF($J:$J,L12,$L:$L) -> 0 | V12: =SUMIF($E:$E,U12,$F:$F) -> 0 | X12: SI-OPS | Y12: =SUMIF($C:$C,X12,$F:$F) -> 6 | Z12: =VLOOKUP(X12,$AB:$AC,2,FALSE) -> Technology | AB12: GP ECL | AC12: Commercial
B13: 11 | C13: DNI | D13: Business Solutions | E13: =VLOOKUP($C13,$AB:$AC,2,FALSE) -> Commercial | F13: =H13*SUMIFS($L:$L,$J:$J,D13,$K:$K,E13)/G13 -> 1 | G13: =SUMIFS($H$2:$H$1000,$E$2:$E$1000,E13,$D$2:$D$1000,D13) -> 9 | H13: 1 | J13: Mail | K13: Technology | L13: =COUNTIFS(E:E,K13,D:D,J13) -> 5 | M13: =SUMIF($J:$J,J13,$L:$L) -> 32 | N13: =SUMIFS(F:F,E:E,K13,D:D,J13) -> 5 | O13: =SUMIF($J:$J,L13,$L:$L) -> 0 | V13: =SUMIF($E:$E,U13,$F:$F) -> 0 | X13: DNI | Y13: =SUMIF($C:$C,X13,$F:$F) -> 6 | Z13: =VLOOKUP(X13,$AB:$AC,2,FALSE) -> Commercial | AB13: GPG | AC13: Commercial
B14: 12 | C14: AVC | D14: Business Solutions | E14: =VLOOKUP($C14,$AB:$AC,2,FALSE) -> Corporate | F14: =H14*SUMIFS($L:$L,$J:$J,D14,$K:$K,E14)/G14 -> 1 | G14: =SUMIFS($H$2:$H$1000,$E$2:$E$1000,E14,$D$2:$D$1000,D14) -> 13 | H14: 1 | J14: Mail | K14: Data & AI | L14: =COUNTIFS(E:E,K14,D:D,J14) -> 1 | M14: =SUMIF($J:$J,J14,$L:$L) -> 32 | N14: =SUMIFS(F:F,E:E,K14,D:D,J14) -> 1 | O14: =SUMIF($J:$J,L14,$L:$L) -> 0 | V14: =SUMIF($E:$E,U14,$F:$F) -> 0 | X14: AVC | Y14: =SUMIF($C:$C,X14,$F:$F) -> 6 | Z14: =VLOOKUP(X14,$AB:$AC,2,FALSE) -> Corporate | AB14: GS | AC14: Commercial
B15: 13 | C15: EM | D15: Business Solutions | E15: =VLOOKUP($C15,$AB:$AC,2,FALSE) -> Operations | F15: =H15*SUMIFS($L:$L,$J:$J,D15,$K:$K,E15)/G15 -> 1 | G15: =SUMIFS($H$2:$H$1000,$E$2:$E$1000,E15,$D$2:$D$1000,D15) -> 3 | H15: 1 | J15: Business Solutions | K15: CISO | L15: =COUNTIFS(E:E,K15,D:D,J15) -> 1 | M15: =SUMIF($J:$J,J15,$L:$L) -> 32 | N15: =SUMIFS(F:F,E:E,K15,D:D,J15) -> 1 | O15: =SUMIF($J:$J,L15,$L:$L) -> 0 | X15: EM | Y15: =SUMIF($C:$C,X15,$F:$F) -> 6 | Z15: =VLOOKUP(X15,$AB:$AC,2,FALSE) -> Operations | AB15: IDC | AC15: Commercial
B16: 14 | C16: SI-PRD | D16: Business Solutions | E16: =VLOOKUP($C16,$AB:$AC,2,FALSE) -> Technology | F16: =H16*SUMIFS($L:$L,$J:$J,D16,$K:$K,E16)/G16 -> 1 | G16: =SUMIFS($H$2:$H$1000,$E$2:$E$1000,E16,$D$2:$D$1000,D16) -> 5 | H16: 1 | J16: Business Solutions | K16: Commercial | L16: =COUNTIFS(E:E,K16,D:D,J16) -> 9 | M16: =SUMIF($J:$J,J16,$L:$L) -> 32 | N16: =SUMIFS(F:F,E:E,K16,D:D,J16) -> 9 | O16: =SUMIF($J:$J,L16,$L:$L) -> 0 | X16: SI-PRD | Y16: =SUMIF($C:$C,X16,$F:$F) -> 6 | Z16: =VLOOKUP(X16,$AB:$AC,2,FALSE) -> Technology | AB16: ACR | AC16: Corporate
B17: 15 | C17: CSI | D17: Business Solutions | E17: =VLOOKUP($C17,$AB:$AC,2,FALSE) -> Commercial | F17: =H17*SUMIFS($L:$L,$J:$J,D17,$K:$K,E17)/G17 -> 1 | G17: =SUMIFS($H$2:$H$1000,$E$2:$E$1000,E17,$D$2:$D$1000,D17) -> 9 | H17: 1 | J17: Business Solutions | K17: Corporate | L17: =COUNTIFS(E:E,K17,D:D,J17) -> 13 | M17: =SUMIF($J:$J,J17,$L:$L) -> 32 | N17: =SUMIFS(F:F,E:E,K17,D:D,J17) -> 13 | O17: =SUMIF($J:$J,L17,$L:$L) -> 0 | X17: CSI | Y17: =SUMIF($C:$C,X17,$F:$F) -> 6 | Z17: =VLOOKUP(X17,$AB:$AC,2,FALSE) -> Commercial | AB17: ATC | AC17: Corporate
B18: 16 | C18: GT | D18: Business Solutions | E18: =VLOOKUP($C18,$AB:$AC,2,FALSE) -> Corporate | F18: =H18*SUMIFS($L:$L,$J:$J,D18,$K:$K,E18)/G18 -> 1 | G18: =SUMIFS($H$2:$H$1000,$E$2:$E$1000,E18,$D$2:$D$1000,D18) -> 13 | H18: 1 | J18: Business Solutions | K18: Operations | L18: =COUNTIFS(E:E,K18,D:D,J18) -> 3 | M18: =SUMIF($J:$J,J18,$L:$L) -> 32 | N18: =SUMIFS(F:F,E:E,K18,D:D,J18) -> 3 | O18: =SUMIF($J:$J,L18,$L:$L) -> 0 | X18: GT | Y18: =SUMIF($C:$C,X18,$F:$F) -> 6 | Z18: =VLOOKUP(X18,$AB:$AC,2,FALSE) -> Corporate | AB18: AVC | AC18: Corporate
B19: 17 | C19: BCTT | D19: Business Solutions | E19: =VLOOKUP($C19,$AB:$AC,2,FALSE) -> Technology | F19: =H19*SUMIFS($L:$L,$J:$J,D19,$K:$K,E19)/G19 -> 1 | G19: =SUMIFS($H$2:$H$1000,$E$2:$E$1000,E19,$D$2:$D$1000,D19) -> 5 | H19: 1 | J19: Business Solutions | K19: Technology | L19: =COUNTIFS(E:E,K19,D:D,J19) -> 5 | M19: =SUMIF($J:$J,J19,$L:$L) -> 32 | N19: =SUMIFS(F:F,E:E,K19,D:D,J19) -> 5 | O19: =SUMIF($J:$J,L19,$L:$L) -> 0 | X19: BCTT | Y19: =SUMIF($C:$C,X19,$F:$F) -> 6 | Z19: =VLOOKUP(X19,$AB:$AC,2,FALSE) -> Technology | AB19: CF | AC19: Corporate
B20: 18 | C20: GP B2C | D20: Business Solutions | E20: =VLOOKUP($C20,$AB:$AC,2,FALSE) -> Commercial | F20: =H20*SUMIFS($L:$L,$J:$J,D20,$K:$K,E20)/G20 -> 1 | G20: =SUMIFS($H$2:$H$1000,$E$2:$E$1000,E20,$D$2:$D$1000,D20) -> 9 | H20: 1 | J20: Business Solutions | K20: Data & AI | L20: =COUNTIFS(E:E,K20,D:D,J20) -> 1 | M20: =SUMIF($J:$J,J20,$L:$L) -> 32 | N20: =SUMIFS(F:F,E:E,K20,D:D,J20) -> 1 | O20: =SUMIF($J:$J,L20,$L:$L) -> 0 | X20: GP B2C | Y20: =SUMIF($C:$C,X20,$F:$F) -> 6 | Z20: =VLOOKUP(X20,$AB:$AC,2,FALSE) -> Commercial | AB20: CFO | AC20: Corporate
B21: 19 | C21: GRH | D21: Business Solutions | E21: =VLOOKUP($C21,$AB:$AC,2,FALSE) -> Corporate | F21: =H21*SUMIFS($L:$L,$J:$J,D21,$K:$K,E21)/G21 -> 1 | G21: =SUMIFS($H$2:$H$1000,$E$2:$E$1000,E21,$D$2:$D$1000,D21) -> 13 | H21: 1 | J21: Retail & Financial Services | K21: CISO | L21: =COUNTIFS(E:E,K21,D:D,J21) -> 1 | M21: =SUMIF($J:$J,J21,$L:$L) -> 32 | N21: =SUMIFS(F:F,E:E,K21,D:D,J21) -> 1 | O21: =SUMIF($J:$J,L21,$L:$L) -> 0 | X21: GRH | Y21: =SUMIF($C:$C,X21,$F:$F) -> 6 | Z21: =VLOOKUP(X21,$AB:$AC,2,FALSE) -> Corporate | AB21: CHR | AC21: Corporate
B22: 20 | C22: SI-CRP | D22: Business Solutions | E22: =VLOOKUP($C22,$AB:$AC,2,FALSE) -> Technology | F22: =H22*SUMIFS($L:$L,$J:$J,D22,$K:$K,E22)/G22 -> 1 | G22: =SUMIFS($H$2:$H$1000,$E$2:$E$1000,E22,$D$2:$D$1000,D22) -> 5 | H22: 1 | J22: Retail & Financial Services | K22: Commercial | L22: =COUNTIFS(E:E,K22,D:D,J22) -> 8 | M22: =SUMIF($J:$J,J22,$L:$L) -> 32 | N22: =SUMIFS(F:F,E:E,K22,D:D,J22) -> 8 | O22: =SUMIF($J:$J,L22,$L:$L) -> 0 | X22: SI-CRP | Y22: =SUMIF($C:$C,X22,$F:$F) -> 6 | Z22: =VLOOKUP(X22,$AB:$AC,2,FALSE) -> Technology | AB22: CL | AC22: Corporate
B23: 21 | C23: GP ECL | D23: Business Solutions | E23: =VLOOKUP($C23,$AB:$AC,2,FALSE) -> Commercial | F23: =H23*SUMIFS($L:$L,$J:$J,D23,$K:$K,E23)/G23 -> 1 | G23: =SUMIFS($H$2:$H$1000,$E$2:$E$1000,E23,$D$2:$D$1000,D23) -> 9 | H23: 1 | J23: Retail & Financial Services | K23: Corporate | L23: =COUNTIFS(E:E,K23,D:D,J23) -> 8 | M23: =SUMIF($J:$J,J23,$L:$L) -> 32 | N23: =SUMIFS(F:F,E:E,K23,D:D,J23) -> 8 | O23: =SUMIF($J:$J,L23,$L:$L) -> 0 | X23: GP ECL | Y23: =SUMIF($C:$C,X23,$F:$F) -> 6 | Z23: =VLOOKUP(X23,$AB:$AC,2,FALSE) -> Commercial | AB23: CMP | AC23: Corporate
B24: 22 | C24: PC | D24: Business Solutions | E24: =VLOOKUP($C24,$AB:$AC,2,FALSE) -> Corporate | F24: =H24*SUMIFS($L:$L,$J:$J,D24,$K:$K,E24)/G24 -> 1 | G24: =SUMIFS($H$2:$H$1000,$E$2:$E$1000,E24,$D$2:$D$1000,D24) -> 13 | H24: 1 | J24: Retail & Financial Services | K24: Operations | L24: =COUNTIFS(E:E,K24,D:D,J24) -> 3 | M24: =SUMIF($J:$J,J24,$L:$L) -> 32 | N24: =SUMIFS(F:F,E:E,K24,D:D,J24) -> 3 | O24: =SUMIF($J:$J,L24,$L:$L) -> 0 | X24: PC | Y24: =SUMIF($C:$C,X24,$F:$F) -> 6 | Z24: =VLOOKUP(X24,$AB:$AC,2,FALSE) -> Corporate | AB24: COM | AC24: Corporate
B25: 23 | C25: GPG | D25: Business Solutions | E25: =VLOOKUP($C25,$AB:$AC,2,FALSE) -> Commercial | F25: =H25*SUMIFS($L:$L,$J:$J,D25,$K:$K,E25)/G25 -> 1 | G25: =SUMIFS($H$2:$H$1000,$E$2:$E$1000,E25,$D$2:$D$1000,D25) -> 9 | H25: 1 | J25: Retail & Financial Services | K25: Technology | L25: =COUNTIFS(E:E,K25,D:D,J25) -> 5 | M25: =SUMIF($J:$J,J25,$L:$L) -> 32 | N25: =SUMIFS(F:F,E:E,K25,D:D,J25) -> 5 | O25: =SUMIF($J:$J,L25,$L:$L) -> 0 | X25: GPG | Y25: =SUMIF($C:$C,X25,$F:$F) -> 6 | Z25: =VLOOKUP(X25,$AB:$AC,2,FALSE) -> Commercial | AB25: DPO | AC25: Corporate
B26: 24 | C26: RS | D26: Business Solutions | E26: =VLOOKUP($C26,$AB:$AC,2,FALSE) -> Corporate | F26: =H26*SUMIFS($L:$L,$J:$J,D26,$K:$K,E26)/G26 -> 1 | G26: =SUMIFS($H$2:$H$1000,$E$2:$E$1000,E26,$D$2:$D$1000,D26) -> 13 | H26: 1 | J26: Retail & Financial Services | K26: Data & AI | L26: =COUNTIFS(E:E,K26,D:D,J26) -> 7 | M26: =SUMIF($J:$J,J26,$L:$L) -> 32 | N26: =SUMIFS(F:F,E:E,K26,D:D,J26) -> 7 | O26: =SUMIF($J:$J,L26,$L:$L) -> 0 | X26: RS | Y26: =SUMIF($C:$C,X26,$F:$F) -> 6 | Z26: =VLOOKUP(X26,$AB:$AC,2,FALSE) -> Corporate | AB26: FL | AC26: Corporate
... B34: 32 | C34: TF | D34: Business Solutions | E34: =VLOOKUP($C34,$AB:$AC,2,FALSE) -> Corporate | F34: =H34*SUMIFS($L:$L,$J:$J,D34,$K:$K,E34)/G34 -> 1 | G34: =SUMIFS($H$2:$H$1000,$E$2:$E$1000,E34,$D$2:$D$1000,D34) -> 13 | H34: 1 | J34: Fulfilment | K34: Commercial | L34: =COUNTIFS(E:E,K34,D:D,J34) -> 9 | M34: =SUMIF($J:$J,J34,$L:$L) -> 32 | N34: =SUMIFS(F:F,E:E,K34,D:D,J34) -> 9 | O34: =SUMIF($J:$J,L34,$L:$L) -> 0 | X34: TF | Y34: =SUMIF($C:$C,X34,$F:$F) -> 6 | Z34: =VLOOKUP(X34,$AB:$AC,2,FALSE) -> Corporate | AB34: COO | AC34: Operations
B35: 1 | C35: COO | D35: eCommerce | E35: =VLOOKUP($C35,$AB:$AC,2,FALSE) -> Operations | F35: 2 | G35: =SUMIFS($H$2:$H$1000,$E$2:$E$1000,E35,$D$2:$D$1000,D35) -> 7 | H35: 2 | J35: Fulfilment | K35: Corporate | L35: =COUNTIFS(E:E,K35,D:D,J35) -> 13 | M35: =SUMIF($J:$J,J35,$L:$L) -> 32 | N35: =SUMIFS(F:F,E:E,K35,D:D,J35) -> 13 | O35: =SUMIF($J:$J,L35,$L:$L) -> 0 | X35: COO | Y35: =SUMIF($C:$C,X35,$F:$F) -> 2 | Z35: =VLOOKUP(X35,$AB:$AC,2,FALSE) -> Operations | AB35: EDO | AC35: Operations
B36: 2 | C36: GP ECL | D36: eCommerce | E36: =VLOOKUP($C36,$AB:$AC,2,FALSE) -> Commercial | F36: =H36*SUMIFS($L:$L,$J:$J,D36,$K:$K,E36)/G36 -> 1 | G36: =SUMIFS($H$2:$H$1000,$E$2:$E$1000,E36,$D$2:$D$1000,D36) -> 12 | H36: 1 | J36: Fulfilment | K36: Operations | L36: =COUNTIFS(E:E,K36,D:D,J36) -> 3 | M36: =SUMIF($J:$J,J36,$L:$L) -> 32 | N36: =SUMIFS(F:F,E:E,K36,D:D,J36) -> 3 | O36: =SUMIF($J:$J,L36,$L:$L) -> 0 | X36: CFO | Y36: =SUMIF($C:$C,X36,$F:$F) -> 1 | Z36: =VLOOKUP(X36,$AB:$AC,2,FALSE) -> Corporate | AB36: EM | AC36: Operations
B37: 3 | C37: CFO | D37: eCommerce | E37: =VLOOKUP($C37,$AB:$AC,2,FALSE) -> Corporate | F37: =H37*SUMIFS($L:$L,$J:$J,D37,$K:$K,E37)/G37 -> 1 | G37: =SUMIFS($H$2:$H$1000,$E$2:$E$1000,E37,$D$2:$D$1000,D37) -> 18 | H37: 1 | J37: Fulfilment | K37: Technology | L37: =COUNTIFS(E:E,K37,D:D,J37) -> 5 | M37: =SUMIF($J:$J,J37,$L:$L) -> 32 | N37: =SUMIFS(F:F,E:E,K37,D:D,J37) -> 5 | O37: =SUMIF($J:$J,L37,$L:$L) -> 0 | X37: CIO | Y37: =SUMIF($C:$C,X37,$F:$F) -> 1 | Z37: =VLOOKUP(X37,$AB:$AC,2,FALSE) -> Technology | AB37: EM | AC37: Operations
B38: 4 | C38: CIO | D38: eCommerce | E38: =VLOOKUP($C38,$AB:$AC,2,FALSE) -> Technology | F38: =H38*SUMIFS($L:$L,$J:$J,D38,$K:$K,E38)/G38 -> 1 | G38: =SUMIFS($H$2:$H$1000,$E$2:$E$1000,E38,$D$2:$D$1000,D38) -> 6 | H38: 1 | J38: Fulfilment | K38: Data & AI | L38: =COUNTIFS(E:E,K38,D:D,J38) -> 1 | M38: =SUMIF($J:$J,J38,$L:$L) -> 32 | N38: =SUMIFS(F:F,E:E,K38,D:D,J38) -> 1 | O38: =SUMIF($J:$J,L38,$L:$L) -> 0 | X38: CMO | Y38: =SUMIF($C:$C,X38,$F:$F) -> 1 | Z38: =VLOOKUP(X38,$AB:$AC,2,FALSE) -> Commercial | AB38: SEO | AC38: Operations
B39: 5 | C39: CISO | D39: eCommerce | E39: =VLOOKUP($C39,$AB:$AC,2,FALSE) -> CISO | F39: =H39*SUMIFS($L:$L,$J:$J,D39,$K:$K,E39)/G39 -> 1 | G39: =SUMIFS($H$2:$H$1000,$E$2:$E$1000,E39,$D$2:$D$1000,D39) -> 1 | H39: 1 | X39: CCO | Y39: =SUMIF($C:$C,X39,$F:$F) -> 1 | Z39: =VLOOKUP(X39,$AB:$AC,2,FALSE) -> Commercial | AB39: BCTT | AC39: Technology
B40: 6 | C40: IAD | D40: eCommerce | E40: =VLOOKUP($C40,$AB:$AC,2,FALSE) -> Data & AI | F40: =H40*SUMIFS($L:$L,$J:$J,D40,$K:$K,E40)/G40 -> 1 | G40: =SUMIFS($H$2:$H$1000,$E$2:$E$1000,E40,$D$2:$D$1000,D40) -> 1 | H40: 1 | X40: ATC | Y40: =SUMIF($C:$C,X40,$F:$F) -> 1 | Z40: =VLOOKUP(X40,$AB:$AC,2,FALSE) -> Corporate | AB40: CIO | AC40: Technology
B41: 7 | C41: GS | D41: eCommerce | E41: =VLOOKUP($C41,$AB:$AC,2,FALSE) -> Commercial | F41: =H41*SUMIFS($L:$L,$J:$J,D41,$K:$K,E41)/G41 -> 1 | G41: =SUMIFS($H$2:$H$1000,$E$2:$E$1000,E41,$D$2:$D$1000,D41) -> 12 | H41: 1 | X41: IDC | Y41: =SUMIF($C:$C,X41,$F:$F) -> 1 | Z41: =VLOOKUP(X41,$AB:$AC,2,FALSE) -> Commercial | AB41: SI | AC41: Technology
B42: 8 | C42: EDO | D42: eCommerce | E42: =VLOOKUP($C42,$AB:$AC,2,FALSE) -> Operations | F42: 2 | G42: =SUMIFS($H$2:$H$1000,$E$2:$E$1000,E42,$D$2:$D$1000,D42) -> 7 | H42: 2 | X42: CHR | Y42: =SUMIF($C:$C,X42,$F:$F) -> 1 | Z42: =VLOOKUP(X42,$AB:$AC,2,FALSE) -> Corporate | AB42: SI-CRP | AC42: Technology
B43: 9 | C43: ACR | D43: eCommerce | E43: =VLOOKUP($C43,$AB:$AC,2,FALSE) -> Corporate | F43: =H43*SUMIFS($L:$L,$J:$J,D43,$K:$K,E43)/G43 -> 1 | G43: =SUMIFS($H$2:$H$1000,$E$2:$E$1000,E43,$D$2:$D$1000,D43) -> 18 | H43: 1 | X43: PRO | Y43: =SUMIF($C:$C,X43,$F:$F) -> 1 | Z43: =VLOOKUP(X43,$AB:$AC,2,FALSE) -> Corporate | AB43: SI-OPS | AC43: Technology
B44: 10 | C44: SI | D44: eCommerce | E44: =VLOOKUP($C44,$AB:$AC,2,FALSE) -> Technology | F44: =H44*SUMIFS($L:$L,$J:$J,D44,$K:$K,E44)/G44 -> 1 | G44: =SUMIFS($H$2:$H$1000,$E$2:$E$1000,E44,$D$2:$D$1000,D44) -> 6 | H44: 1 | X44: COM | Y44: =SUMIF($C:$C,X44,$F:$F) -> 1 | Z44: =VLOOKUP(X44,$AB:$AC,2,FALSE) -> Corporate | AB44: SI-PRD | AC44: Technology
B45: 11 | C45: CMO | D45: eCommerce | E45: =VLOOKUP($C45,$AB:$AC,2,FALSE) -> Commercial | F45: =H45*SUMIFS($L:$L,$J:$J,D45,$K:$K,E45)/G45 -> 1 | G45: =SUMIFS($H$2:$H$1000,$E$2:$E$1000,E45,$D$2:$D$1000,D45) -> 12 | H45: 1 | X45: 0 | AB45: IAD | AC45: Data & AI
B46: 12 | C46: SEO | D46: eCommerce | E46: =VLOOKUP($C46,$AB:$AC,2,FALSE) -> Operations | F46: 2 | G46: =SUMIFS($H$2:$H$1000,$E$2:$E$1000,E46,$D$2:$D$1000,D46) -> 7 | H46: 2
B47: 13 | C47: CF | D47: eCommerce | E47: =VLOOKUP($C47,$AB:$AC,2,FALSE) -> Corporate | F47: =H47*SUMIFS($L:$L,$J:$J,D47,$K:$K,E47)/G47 -> 1 | G47: =SUMIFS($H$2:$H$1000,$E$2:$E$1000,E47,$D$2:$D$1000,D47) -> 18 | H47: 1
B48: 14 | C48: SI-OPS | D48: eCommerce | E48: =VLOOKUP($C48,$AB:$AC,2,FALSE) -> Technology | F48: =H48*SUMIFS($L:$L,$J:$J,D48,$K:$K,E48)/G48 -> 1 | G48: =SUMIFS($H$2:$H$1000,$E$2:$E$1000,E48,$D$2:$D$1000,D48) -> 6 | H48: 1
B49: 15 | C49: CCO | D49: eCommerce | E49: =VLOOKUP($C49,$AB:$AC,2,FALSE) -> Commercial | F49: =H49*SUMIFS($L:$L,$J:$J,D49,$K:$K,E49)/G49 -> 1 | G49: =SUMIFS($H$2:$H$1000,$E$2:$E$1000,E49,$D$2:$D$1000,D49) -> 12 | H49: 1
B50: 17 | C50: BCTT | D50: eCommerce | E50: =VLOOKUP($C50,$AB:$AC,2,FALSE) -> Technology | F50: =H50*SUMIFS($L:$L,$J:$J,D50,$K:$K,E50)/G50 -> 1 | G50: =SUMIFS($H$2:$H$1000,$E$2:$E$1000,E50,$D$2:$D$1000,D50) -> 6 | H50: 1
B51: 18 | C51: ATC | D51: eCommerce | E51: =VLOOKUP($C51,$AB:$AC,2,FALSE) -> Corporate | F51: =H51*SUMIFS($L:$L,$J:$J,D51,$K:$K,E51)/G51 -> 1 | G51: =SUMIFS($H$2:$H$1000,$E$2:$E$1000,E51,$D$2:$D$1000,D51) -> 18 | H51: 1
B52: 19 | C52: SI-PRD | D52: eCommerce | E52: =VLOOKUP($C52,$AB:$AC,2,FALSE) -> Technology | F52: =H52*SUMIFS($L:$L,$J:$J,D52,$K:$K,E52)/G52 -> 1 | G52: =SUMIFS($H$2:$H$1000,$E$2:$E$1000,E52,$D$2:$D$1000,D52) -> 6 | H52: 1
B53: 20 | C53: IDC | D53: eCommerce | E53: =VLOOKUP($C53,$AB:$AC,2,FALSE) -> Commercial | F53: =H53*SUMIFS($L:$L,$J:$J,D53,$K:$K,E53)/G53 -> 1 | G53: =SUMIFS($H$2:$H$1000,$E$2:$E$1000,E53,$D$2:$D$1000,D53) -> 12 | H53: 1
B54: 21 | C54: AVC | D54: eCommerce | E54: =VLOOKUP($C54,$AB:$AC,2,FALSE) -> Corporate | F54: =H54*SUMIFS($L:$L,$J:$J,D54,$K:$K,E54)/G54 -> 1 | G54: =SUMIFS($H$2:$H$1000,$E$2:$E$1000,E54,$D$2:$D$1000,D54) -> 18 | H54: 1
B55: 22 | C55: EM | D55: eCommerce | E55: =VLOOKUP($C55,$AB:$AC,2,FALSE) -> Operations | F55: 1 | G55: =SUMIFS($H$2:$H$1000,$E$2:$E$1000,E55,$D$2:$D$1000,D55) -> 7 | H55: 1
B56: 23 | C56: DNI | D56: eCommerce | E56: =VLOOKUP($C56,$AB:$AC,2,FALSE) -> Commercial | F56: =H56*SUMIFS($L:$L,$J:$J,D56,$K:$K,E56)/G56 -> 1 | G56: =SUMIFS($H$2:$H$1000,$E$2:$E$1000,E56,$D$2:$D$1000,D56) -> 12 | H56: 1
B57: 24 | C57: CHR | D57: eCommerce | E57: =VLOOKUP($C57,$AB:$AC,2,FALSE) -> Corporate | F57: =H57*SUMIFS($L:$L,$J:$J,D57,$K:$K,E57)/G57 -> 1 | G57: =SUMIFS($H$2:$H$1000,$E$2:$E$1000,E57,$D$2:$D$1000,D57) -> 18 | H57: 1
B58: 25 | C58: SI-CRP | D58: eCommerce | E58: =VLOOKUP($C58,$AB:$AC,2,FALSE) -> Technology | F58: =H58*SUMIFS($L:$L,$J:$J,D58,$K:$K,E58)/G58 -> 1 | G58: =SUMIFS($H$2:$H$1000,$E$2:$E$1000,E58,$D$2:$D$1000,D58) -> 6 | H58: 1
B59: 26 | C59: CSI | D59: eCommerce | E59: =VLOOKUP($C59,$AB:$AC,2,FALSE) -> Commercial | F59: =H59*SUMIFS($L:$L,$J:$J,D59,$K:$K,E59)/G59 -> 1 | G59: =SUMIFS($H$2:$H$1000,$E$2:$E$1000,E59,$D$2:$D$1000,D59) -> 12 | H59: 1
B60: 27 | C60: PRO | D60: eCommerce | E60: =VLOOKUP($C60,$AB:$AC,2,FALSE) -> Corporate | F60: =H60*SUMIFS($L:$L,$J:$J,D60,$K:$K,E60)/G60 -> 1 | G60: =SUMIFS($H$2:$H$1000,$E$2:$E$1000,E60,$D$2:$D$1000,D60) -> 18 | H60: 1
B61: 28 | C61: GP B2B | D61: eCommerce | E61: =VLOOKUP($C61,$AB:$AC,2,FALSE) -> Commercial | F61: =H61*SUMIFS($L:$L,$J:$J,D61,$K:$K,E61)/G61 -> 1 | G61: =SUMIFS($H$2:$H$1000,$E$2:$E$1000,E61,$D$2:$D$1000,D61) -> 12 | H61: 1
B62: 29 | C62: DPO | D62: eCommerce | E62: =VLOOKUP($C62,$AB:$AC,2,FALSE) -> Corporate | F62: =H62*SUMIFS($L:$L,$J:$J,D62,$K:$K,E62)/G62 -> 1 | G62: =SUMIFS($H$2:$H$1000,$E$2:$E$1000,E62,$D$2:$D$1000,D62) -> 18 | H62: 1
B63: 30 | C63: GP B2C | D63: eCommerce | E63: =VLOOKUP($C63,$AB:$AC,2,FALSE) -> Commercial | F63: =H63*SUMIFS($L:$L,$J:$J,D63,$K:$K,E63)/G63 -> 1 | G63: =SUMIFS($H$2:$H$1000,$E$2:$E$1000,E63,$D$2:$D$1000,D63) -> 12 | H63: 1
B64: 31 | C64: GT | D64: eCommerce | E64: =VLOOKUP($C64,$AB:$AC,2,FALSE) -> Corporate | F64: =H64*SUMIFS($L:$L,$J:$J,D64,$K:$K,E64)/G64 -> 1 | G64: =SUMIFS($H$2:$H$1000,$E$2:$E$1000,E64,$D$2:$D$1000,D64) -> 18 | H64: 1
B65: 32 | C65: GPG | D65: eCommerce | E65: =VLOOKUP($C65,$AB:$AC,2,FALSE) -> Commercial | F65: =H65*SUMIFS($L:$L,$J:$J,D65,$K:$K,E65)/G65 -> 1 | G65: =SUMIFS($H$2:$H$1000,$E$2:$E$1000,E65,$D$2:$D$1000,D65) -> 12 | H65: 1
B66: 35 | C66: GRH | D66: eCommerce | E66: =VLOOKUP($C66,$AB:$AC,2,FALSE) -> Corporate | F66: =H66*SUMIFS($L:$L,$J:$J,D66,$K:$K,E66)/G66 -> 1 | G66: =SUMIFS($H$2:$H$1000,$E$2:$E$1000,E66,$D$2:$D$1000,D66) -> 18 | H66: 1
B67: 36 | C67: ECM | D67: eCommerce | E67: =VLOOKUP($C67,$AB:$AC,2,FALSE) -> Commercial | F67: =H67*SUMIFS($L:$L,$J:$J,D67,$K:$K,E67)/G67 -> 1 | G67: =SUMIFS($H$2:$H$1000,$E$2:$E$1000,E67,$D$2:$D$1000,D67) -> 12 | H67: 1
... B198: 26 | C198: CL | D198: Retail & Financial Services | E198: =VLOOKUP($C198,$AB:$AC,2,FALSE) -> Corporate | F198: =H198*SUMIFS($L:$L,$J:$J,D198,$K:$K,E198)/G198 -> 1 | G198: =SUMIFS($H$2:$H$1000,$E$2:$E$1000,E198,$D$2:$D$1000,D198) -> 8 | H198: 1
B199: 27 | C199: CTTE | D199: Retail & Financial Services | E199: Data & AI | F199: =H199*SUMIFS($L:$L,$J:$J,D199,$K:$K,E199)/G199 -> 1 | G199: =SUMIFS($H$2:$H$1000,$E$2:$E$1000,E199,$D$2:$D$1000,D199) -> 7 | H199: 1
B200: 28 | C200: DPO | D200: Retail & Financial Services | E200: Data & AI | F200: =H200*SUMIFS($L:$L,$J:$J,D200,$K:$K,E200)/G200 -> 1 | G200: =SUMIFS($H$2:$H$1000,$E$2:$E$1000,E200,$D$2:$D$1000,D200) -> 7 | H200: 1
B201: 29 | C201: CMP | D201: Retail & Financial Services | E201: Data & AI | F201: =H201*SUMIFS($L:$L,$J:$J,D201,$K:$K,E201)/G201 -> 1 | G201: =SUMIFS($H$2:$H$1000,$E$2:$E$1000,E201,$D$2:$D$1000,D201) -> 7 | H201: 1
B202: 30 | C202: ST | D202: Retail & Financial Services | E202: Data & AI | F202: =H202*SUMIFS($L:$L,$J:$J,D202,$K:$K,E202)/G202 -> 1 | G202: =SUMIFS($H$2:$H$1000,$E$2:$E$1000,E202,$D$2:$D$1000,D202) -> 7 | H202: 1
B203: 31 | C203: FL | D203: Retail & Financial Services | E203: Data & AI | F203: =H203*SUMIFS($L:$L,$J:$J,D203,$K:$K,E203)/G203 -> 1 | G203: =SUMIFS($H$2:$H$1000,$E$2:$E$1000,E203,$D$2:$D$1000,D203) -> 7 | H203: 1
B204: 32 | C204: TF | D204: Retail & Financial Services | E204: Data & AI | F204: =H204*SUMIFS($L:$L,$J:$J,D204,$K:$K,E204)/G204 -> 1 | G204: =SUMIFS($H$2:$H$1000,$E$2:$E$1000,E204,$D$2:$D$1000,D204) -> 7 | H204: 1
